Workbook

Sheet Cover
A1: Europe Private Debt & Alternative Credit Investors - Relevance to the CPEF I Curity and Impactus Pyrolysis (IPL) raises
A2: Impactus Private Equity Group - internal working workbook - prepared 22 September 2026 - source article: Cascade Debt, 'Private Debt and Alternative Credit Investors in Europe' (2026 Europe Private ABF Investor Market Map)
A4: Purpose | B4: Map the European private debt / alternative credit investor universe (Cascade 2026 ABF map plus the wider direct lending, special situations, infrastructure credit, venture debt, impact and DFI universe), score each firm for relevance to the IPL (€5m equity + €35m venture debt + senior refinancing optionality) and CPEF (8% note today; €3m to €10m growth facility next) raises, and give a named, channel-specific contact plan.
A5: How to read the tabs | B5: 1 Exec_Summary: headline counts and capacity. 2 Market_Overview: sourced market data. 3 Segment_Map: which credit segment fits which Impactus need. 4 Cascade_Map_2026: the article's investor map transcribed and scored. 5 Investor_Universe: scored target list (firm level). 6 Contacts: named decision-makers with channel recommendation. 7 Existing_Pipeline: warm relationships already in Impactus records. 8 IPL_Debt_Capacity and 9 CPEF_Debt_Capacity: live models. 10 Outreach_Plan and 11 Conferences. 12 Scoring_Weights: change weights here. 13 Sources.
A6: Colour legend | B6: Blue text on yellow = input you can change. Black = formula or fixed data. Green = link to another tab. Scores recalculate when weights on Scoring_Weights change.
A7: Data status | B7: External figures are sourced (see Sources tab, URL per row). Contact emails: only those published on public pages are shown as 'published'; 'pattern - unverified' means the firm's public address format, to be verified before sending. LinkedIn URLs are public profile URLs found in September 2026. Apollo.io enrichment was not available in this session (free plan blocks API search and enrichment), so no purchased data is included.
A8: Analytical stance | B8: Bear case first. Rows flagged 'DD challenge' name the objection an LP due-diligence lead, lender credit committee or CySEC reviewer would raise. The memo (Word) carries the argued position; this workbook carries the evidence and the working models.
A9: Disclaimer | B9: AIFMD Art. 23 disclosure: Impactus RAIF V.C.I.C. Plc is a Registered Alternative Investment Fund (CySEC RAIF16) externally managed by Argus Management Ltd (CySEC AIFM 44/56/2013). This workbook is an internal working document prepared for the Sponsor and is not an offer, solicitation or marketing communication. Interests in the Fund and its sub-funds (Impactus Private Equity Fund, CPEF I Curity, Impactus Pyrolysis / IVP) are available only to professional and well-informed investors within the meaning of AIFMD Art. 4(1)(ag), MiFID II and the Cyprus AIF Law 124(I)/2018. Prospective investors must read the AIFMD Art. 23 disclosure document, the relevant offering supplement and term sheet before investing. Targets are gross, forward-looking and not guaranteed; capital is at risk. Third-party names are used for identification only and do not imply endorsement.

Sheet Exec_Summary
A1: Executive summary - the numbers behind the memo
A2: All counts are live formulas over the scored tabs
A4: Measure | B4: Value | C4: Read-across
A5: Firms scored in the wider universe (Investor_Universe) | B5: =COUNTA(Investor_Universe!A5:A82) | C5: Direct lending, special situations, infrastructure credit, venture debt, impact, DFI, cannabis credit, placement, fund finance
A6: Firms on the Cascade 2026 Europe ABF map (Cascade_Map_2026) | B6: =COUNTA(Cascade_Map_2026!A5:A114) | C6: The article's universe, transcribed and scored
A7: Tier 1 targets - wider universe | B7: =COUNTIF(Investor_Universe!S5:S82,"Tier 1") | C7: Approach in Wave 1 (weeks 1-4)
A8: Tier 1 targets - Cascade map | B8: =COUNTIF(Cascade_Map_2026!S5:S114,"Tier 1") | C8: ABF investors that could still do a single hard asset or a receivables/inventory line
A9: Tier 2 targets - both tabs | B9: =COUNTIF(Investor_Universe!S5:S82,"Tier 2")+COUNTIF(Cascade_Map_2026!S5:S114,"Tier 2") | C9: Wave 2 (weeks 5-10)
A10: Named contacts with a warm path | B10: =COUNTIF(Contacts!I5:I72,"<>") | C10: Use first
A11: Named contacts with a published email | B11: =COUNTIF(Contacts!H5:H72,"published") | C11: Email + LinkedIn note same day
A12: Named contacts with LinkedIn only | B12: =COUNTIFS(Contacts!F5:F72,"<>not found",Contacts!H5:H72,"<>published") | C12: LinkedIn first
A13: Total named contacts | B13: =COUNTA(Contacts!B5:B72)
A14: IPL: senior debt capacity on model CFADS at 1.5x DSCR (€m) | B14: =IPL_Debt_Capacity!E16 | C14: vs €77.4m in the Sponsor plan
A15: IPL: senior debt capacity at contracted gate fee (€62/t on 11ktpa ~ €15/t on 45ktpa), €1,500/t rCB (€m) | B15: =PV(IPL_Debt_Capacity!B19,IPL_Debt_Capacity!B20,-(((IPL_Debt_Capacity!B5*IPL_Debt_Capacity!B6*IPL_Debt_Capacity!B7+IPL_Debt_Capacity!B5*IPL_Debt_Capacity!B8*IPL_Debt_Capacity!B9+IPL_Debt_Capacity!B5*IPL_Debt_Capacity!B10*IPL_Debt_Capacity!B11+IPL_Debt_Capacity!B5*15+IPL_Debt_Capacity!B5*IPL_Debt_Capacity!B13)/1000000-IPL_Debt_Capacity!E11)*(1-IPL_Debt_Capacity!B16)-IPL_Debt_Capacity!B5*IPL_Debt_Capacity!B15/1000000)/IPL_Debt_Capacity!B21) | C15: What a credit committee sizes on today
A16: IPL: funding gap vs plan if capex stress applies (€m) | B16: =IPL_Debt_Capacity!E26 | C16: Negative = shortfall to be filled by private credit or equity
A17: IPL: venture-debt all-in cost | B17: =IPL_Debt_Capacity!E20 | C17: 4% cash + 5% PIK + warrants
A18: IPL: blended cost of capital | B18: =IPL_Debt_Capacity!E29
A19: CPEF: growth-facility headroom at stressed plan (€m) | B19: =CPEF_Debt_Capacity!E8 | C19: At 2.5x leverage on €3.00/g stressed EBITDA
A20: CPEF: all-in cost of a specialist growth facility | B20: =CPEF_Debt_Capacity!E14 | C20: vs 8% note

Sheet Market_Overview
A1: European private debt and alternative credit - market data (sourced)
A2: Figures as published; where sources conflict both are shown. See Sources tab for URLs.
A4: Metric | B4: Value | C4: Unit | D4: Period | E4: Source | F4: Relevance to Impactus raise
A5: European private credit AUM | B5: c.€400b (other estimate US$340b) | C5: €b | D5: 2026 | E5: AllianzGI / Revelle Capital; ctacquisitions (cites Preqin) | F5: The pool is large; the constraint for Impactus is fit, not supply
A6: Global private credit AUM | B6: c.US$1.7t (broader definitions >US$2.5t) | C6: US$t | D6: 2025-26 | E6: Preqin 2025 global report; ctacquisitions | F6: Context only
A7: Europe private debt fundraising FY2025 | B7: US$79.4b (PitchBook); US$69.9b (S&P / With Intelligence) | C7: US$b | D7: FY2025 | E7: PitchBook; S&P press release | F7: Second-highest year ever; +29% to +40% YoY depending on source
A8: Europe share of global private credit fundraising | B8: 23% (2024) to 46% (2025) | C8: % | D8: 2025 | E8: Alternative Credit Investor 16-12-2025; PitchBook | F8: Capital is rotating to Europe - the window for European stories is open
A9: Direct lending share of European capital raised | B9: 61.5% | C9: % | D9: 9M 2025 | E9: Alternative Credit Investor 16-12-2025 (Preqin) | F9: Most of the money is corporate sponsor-backed lending - not IPL or CPEF's segment
A10: Concentration of fundraising | B10: 93.1% of global private debt capital to managers on Fund IV or later | C10: % | D10: 2025 | E10: PitchBook 2025 Annual Global Private Debt Report | F10: LPs back scale; a first-time sub-€100m GP will not raise from these allocators directly
A11: European direct lending deal volume Q2 2026 | B11: €28.4b / 296 deals (Q2 2025: €38.0b / 367); Q1 2026 €34.8b / 303 | C11: €b | D11: Q2 2026 | E11: Alternative Credit Investor 25-08-2026 | F11: Deal flow slowing; lenders have dry powder and are competing for assets
A12: Deloitte Private Debt Deal Tracker H1 2025 | B12: 421 deals; avg deal size €204.9m; 89 lenders | C12: count | D12: H1 2025 | E12: Deloitte UK Private Debt Deal Tracker (Autumn 2025) | F12: Average ticket is 5x to 40x Impactus' need - target the lower-mid and specialist tail
A13: Unitranche pricing, European mid-market | B13: Euribor + 525 to 625bps (traditional mid-market); +500 to 600bps (upper) | C13: bps | D13: Q1-Q2 2026 | E13: Valuation Research Corp Q2 2026 European update | F13: Benchmark for what 'senior' costs a sponsor-backed corporate; IPL is not that credit
A14: Mezzanine / junior yields | B14: 13% to 16% all-in; spreads 450 to 1,300bps by seniority | C14: % | D14: 2026 | E14: ddtalks (secondary source - verify) | F14: The €35m venture-debt tranche at 10% blended is priced below where junior capital clears for a FOAK asset
A15: Special situations fundraising | B15: H1 2026: Alchemy, Metric Capital, Tikehau each closed €1b+ funds; European pipeline c.£100b | C15: €b | D15: H1 2026 | E15: With Intelligence emerging managers 2026; Alternative Credit Investor 19-02-2026 | F15: Special-sits desks have the mandate for hybrid, PIK and warrants that IPL needs
... A28: Specialist cannabis lenders (US) | B28: Chicago Atlantic REFI: US$453m, 26 borrowers, 15.8% weighted YTM; AFC Gamma: US$290m, 13.2% yield, 35.7% non-accrual | C28: US$m | D28: 30-06-2026 | E28: REFI / AFCG 10-Q via research briefing | F28: No European loan on record for any specialist cannabis lender; pricing anchor 13% to 16%

Sheet Segment_Map
A1: Segment map - which part of the credit market fits which Impactus need
A2: Fit scores 0-5 are analyst judgement (basis stated); pricing ranges are market-observed 2025-2026
A4: Segment | B4: Europe size / activity | C4: Typical pricing | D4: Typical ticket | E4: Instruments / hold | F4: IPL fit (0-5) | G4: CPEF fit (0-5) | H4: Why / basis | I4: Representative firms
A5: Asset-based finance (ABF) - the Cascade map universe | B5: Global ABF c.US$6.1t (2025) to c.US$9t by 2029 (Apollo); Europe: warehouse lines to originators, forward-flow, portfolio purchases, specialty-finance equity | C5: Senior warehouse E+300 to 600bps; advance rates 65% to 85%; mezz 10% to 15% | D5: €25m to €500m per facility | E5: Revolving warehouse, forward-flow, portfolio acquisition, real-asset ABL; 2 to 5 years | F5: 1 | G5: 2 | H5: ABF investors lend against granular pools with observable performance data. A single FOAK plant is not a pool. Curity could in time support a small inventory / receivables line once German distribution creates receivables - but no European ABF investor has a cannabis precedent. Only the special-situations and real-asset ABL sub-set of the map (Fortress, Davidson Kempner, Castlelake, Arrow, Pollen Street, Kartesia, Incus, Chenavari, Sixth Street, Apollo) could stretch to a single hard asset. | I5: Fortress, Davidson Kempner, Castlelake, Waterfall, Arrow Global, Pollen Street, Kartesia, Incus Capital, Chenavari, Sixth Street
A6: Sponsor-backed direct lending (senior / unitranche) | B6: 61.5% of European capital raised 9M 2025; H1 2026 volume c.€63b | C6: E+500 to 625bps unitranche; 5.0x to 6.5x EBITDA | D6: €30m to €500m | E6: Unitranche / senior term loans; 5 to 7 years; corporate borrowers with EBITDA | F6: 0 | G6: 1 | H6: Requires positive, audited EBITDA and usually a PE sponsor. IPL has no EBITDA until 2029; Curity has EBITDA below €2m today. Exclude from Wave 1. | I6: Ares, Arcmont, Hayfin, Pemberton, Tikehau, Bridgepoint Credit, Eurazeo, CVC Credit, ICG
A7: Lower-mid-market / SME credit (Southern Europe) | B7: Kartesia KCO VI €1.3b; Capza PD 7 c.€1.4b first close; Beechbrook €2m to €25m bites; Greek AIFs (Elikonos 3 €175m) | C7: 9% to 14% all-in; often with PIK and warrants | D7: €3m to €30m | E7: Senior, unitranche, hybrid; 3 to 6 years | F7: 2 | G7: 3 | H7: The only segment of the core direct-lending market that writes Impactus-sized tickets. Kartesia and Capza have Southern Europe teams; Elikonos / Halcyon are Greek and EIF-backed (state-aid sensitive on cannabis). Fit for a Curity growth facility once revenue is audited; for IPL only as holdco / sponsor-level hybrid. | I7: Kartesia, Capza, Muzinich, Beechbrook, Cordet, Elikonos, Halcyon, Waterwheel, Azimut Direct
A8: Special situations / opportunistic credit | B8: Alchemy, Metric, Tikehau €1b+ funds closed H1 2026; UK / Europe pipeline c.£100b | C8: 12% to 20% IRR targets; PIK, warrants, control rights | D8: €10m to €150m | E8: Bespoke senior / junior, PIK toggles, equity kickers; 3 to 5 years | F8: 4 | G8: 2 | H8: This is the natural home of a €35m FOAK tranche at 10% cash + PIK + warrants. The price will be higher than 10% blended (expect 14% to 18% all-in with 10% to 20% warrant coverage). Cannabis: case by case, most decline on reputational grounds. | I8: Hayfin Special Opportunities, Blantyre, Cheyne Strategic Value Credit, Davidson Kempner, Fortress, Arini, Chenavari, Incus, Fasanara, Pollen Street
A9: Infrastructure and energy-transition debt | B9: Record £68b European infra debt 2025; Infranity €3.2b (2025); Eiffel EET III €1.2b; Rivage REDI HR3 €700m target; CIP Green Credit II €1.3b first close | C9: Senior IG-like: E+150 to 250bps; enhanced-return / sub-IG: 7% to 10% | D9: €20m to €150m | E9: Senior secured project debt, construction-plus-operations; 7 to 20 years | F9: 3 | G9: 0 | H9: Infra-debt funds want contracted cash flows, an EPC wrap and a technology with references. Thermo Lysi has the grant, an EPC under negotiation and a TRL 8-9 process, but no lender-grade offtake yet. Enhanced-return sleeves (Infranity ERDF, Rivage High Yield, Eiffel bridge vs grant receivable) are the realistic entry. No European infra-debt fund has financed a tyre-pyrolysis plant to date. | I9: Infranity (Enhanced Return), Rivage (REDI HR / European Climate Debt Solutions), Eiffel Energy Transition, Polestar Capital, Aquila, Edmond de Rothschild BRIDGE, AXA IM Alts, AllianzGI
A10: Venture debt / growth debt | B10: Kreos/BlackRock >US$7b committed, 830+ deals; Claret IV €575m; Atempo II >€455m | C10: 10% to 13% cash + 5% to 15% warrant coverage | D10: €5m to €40m | E10: 3 to 4 year amortising term loans; VC-backed revenue companies | F10: 2 | G10: 3 | H10: Structurally the closest instrument to the VD tranche, but growth-debt lenders underwrite VC-backed recurring revenue, not construction. Kreos' Aris Constantinides (Greek) is a warm angle. For Curity, growth debt becomes available once 12 months of audited German sales exist; no cannabis exclusion located for Kreos, Claret or Atempo. | I10: Kreos Capital, Claret Capital, Atempo Growth, Columbia Lake, Bootstrap Europe, Flashpoint, Harbert
A11: Development finance and public co-financing | B11: EIB Group Greece €3.5b (2025); EIB venture debt (Joltie €17.5m); EIF InvestEU guarantees; HDB Green Co-Financing; EU Innovation Fund IF25 (€2.9b, results Oct-Nov 2026) | C11: EIB VD: quasi-equity, cash + PIK + warrants c.8% to 12%; HDB: 40% interest-free | D11: €5m to €50m | E11: Venture debt, guarantees, co-financed bank loans | F11: 4 | G11: 1 | H11: EIB Cleantech declined in April 2026 ('mezzanine risk without equity reward') and re-engaged in September via Sirec - the reopened process is the single most valuable live thread. EBRD Greece closed for new deals Dec 2025. HDB / RRF windows closed Aug 2026. Cannabis: no formal exclusion at EIB / EBRD but no precedent. | I11: EIB Cleantech Equity & Growth Capital, EIF InvestEU, HDB, HDBI, Growthfund / HCAP
A12: Impact and climate credit funds | B12: Blue Earth climate strategy US$378m; Rivage European Climate Debt Solutions (EIF-backed); Triodos Energy Transition; Polestar (Xycle senior debt) | C12: 8% to 12% senior impact debt; blended finance structures | D12: €5m to €30m | E12: Senior / mezz impact loans; 5 to 10 years | F12: 4 | G12: 0 | H12: Best mandate fit for IPL: 784,304 tCO2e avoided, EU Innovation Fund validation, STEP seal. Polestar Capital is the only European impact lender with a chemical-recycling senior loan (Xycle). Cannabis excluded by most impact mandates. | I12: Polestar Capital, Rivage ECDS, Blue Earth Capital, Triodos IM, Mirova, SUSI Partners, Climate Fund Managers
A13: Strategic / offtaker capital | B13: BASF €16m + €25m conditional loan into Pyrum; bp €12.5m debt + 8-year offtake to Circtec; Continental 10-year rCB framework; Pirelli / BASF / Synthos tyre-to-tyre | C13: Below-market coupon in exchange for offtake / supply rights | D13: €5m to €25m | E13: Prepayment, offtaker loan, equity | F13: 5 | G13: 3 | H13: The pattern across every financed European pyrolysis project is grant + strategic equity + offtaker-linked debt, not fund debt. For IPL the highest-probability €10m to €15m is an offtaker prepayment or loan (BASF for oil, Continental / Pirelli via Pyrum for rCB, Archirodon deferred EPC payment). For Curity, ELPEN and German importers (Cantourage, Cansativa, Curaleaf International) are the equivalent. | I13: BASF, Continental, Pirelli, Pyrum, Archirodon, VTTI, Vitol; ELPEN, Cantourage, Cansativa, Curaleaf International, Galenica
A14: Specialist cannabis credit | B14: Chicago Atlantic REFI US$453m at 15.8% YTM; AFC Gamma US$290m at 13.2%; Artemis Growth Partners Fund VII US$200m target, c.75% Europe (equity / hybrid) | C14: 13% to 16% senior secured; 10% + equity kicker for European convertibles (Organigram / Sanity 2024) | D14: US$5m to US$50m | E14: Senior secured term loans, convertibles, sale-leasebacks | F14: 0 | G14: 4 | H14: No specialist lender has a documented European loan; Chicago Atlantic (co-founded by John Mazarakis, Greek-American) is the one to test. Artemis is the only fund with a stated European allocation. Expect 13% to 16% and hard-asset security. | I14: Chicago Atlantic, Advanced Flower Capital (AFC Gamma), Artemis Growth Partners, Pelorus (US only), Casa Verde (equity)
A15: Fund finance (capital-call / NAV) | B15: >US$1t market; NAV 28% of European deals; average facility US$285m; banks 88% of new deals | C15: Sub-line E+200 to 300bps; NAV E+500 to 800bps | D15: US$50m minimum for institutional lenders; €5m to €25m from Cyprus / UK boutique banks | E15: Revolving, 1 to 3 years | F15: 1 | G15: 0 | H15: Every institutional NAV lender is above Impactus' scale and every UK lender applies POCA screening to cannabis. Only Eurobank Cyprus (depositary) or Bank of Cyprus could write a small capital-call line for the PE Fund; CPEF must be excluded from any borrowing base. | I15: Eurobank Cyprus, Bank of Cyprus, HSBC Innovation Banking, Investec Fund Solutions, Hark Capital
A16: Placement agents and capital advisors | B16: Success fees 2% to 3% for sub-US$100m funds; retainers US$25k to US$150k; bank-owned groups start at €300m+ | C16: n/a | D16: n/a | E16: Advisory | F16: 2 | G16: 1 | H16: Only Threadmark, Elm, Quest, Cebile, Acanthus and the Greek / Cypriot boutiques (Axia, Ambrosia, Emergo, MeritKapital, Argus) take sub-€150m niche mandates. Every bank-owned PCA excludes cannabis by policy. Impactus already has Venero (debt), KPMG Cyprus (IVP) and Argus (distribution) - add one credit-specialist boutique for the VD tranche, on success fee only. | I16: Threadmark, Elm Capital, Quest Fund Placement, Cebile Capital, Acanthus, Axia Ventures, Ambrosia Capital, Venero (engaged), KPMG Cyprus (engaged)
A17: Cyprus and Greek institutional / family capital | B17: Cyprus provident funds (ETYK, PEO, Cyta, EAC, PASYDY, Doctors', Lawyers', SEK); Greek TEAs (30% alternatives cap); Greek insurers (Ethniki, NN, Generali, Allianz, Interamerican, Eurolife); Growthfund c.€6b; Greek family offices (Latsis, Laskaridis, Martinos, Vardinogiannis backed Greek PE / VC vehicles) | C17: 8% coupon products; equity | D17: €150k to €2m per provident fund; €0.5m to €5m family offices | E17: Fund units, notes, direct co-investment | F17: 3 | G17: 3 | H17: This is where Impactus has actually raised money (SEK, Doctors' Fund, CSE fund, AstroBank, Rodopoulos, Sirec). Scaling it means (a) a note the provident funds can hold under IORP prudent-person rules, (b) Muhanna / Argus as gateways, (c) two or three Greek family offices with VC / PE history as anchors for IVP. | I17: Argus Management, Muhanna & Co, Athlos Capital, Alpha Bank Wealth (Greece), J. Safra Sarasin, KPMG Cyprus

Sheet Cascade_Map_2026
A1: Cascade Map 2026
A2: The article's map transcribed: Cascade Debt 'Private ABF Investor Market Map 2026 - Region: Europe', classified by each firm's dedicated ABL/ABF and private credit strategy. Scores are analyst judgement on public evidence.
A4: Firm | B4: Category | C4: HQ / EU office | D4: Strategy / vehicle | E4: Fund size / AUM | F4: Ticket range | G4: Instruments | H4: Greece / Cyprus / S. Europe evidence | I4: Hard-asset / FOAK evidence | J4: Cannabis stance | K4: S1 IPL fit | L4: S2 CPEF fit | M4: S3 Ticket | N4: S4 Geography | O4: S5 Risk appetite | P4: S6 Warm path | Q4: S7 Speed | R4: Weighted score | S4: Tier | T4: Best use for Impactus | U4: Recommended channel | V4: Warm path via | W4: Source URL
A5: Octopus (Octopus Investments / Real Estate) | B5: Cascade map - AUM < US$5b | C5: London | D5: Specialist lending, real estate and energy [K] | E5: n/a | F5: €5m to €50m | G5: Real-asset lending, energy | H5: UK | I5: Octopus Energy Generation invests in renewables; no pyrolysis | J5: Unknown | K5: 2 | L5: 0 | M5: 4 | N5: 1 | O5: 3 | P5: 1 | Q5: 3 | R5: =ROUND(SUMPRODUCT(K5:Q5,Scoring_Weights!$E$5:$K$5)/Scoring_Weights!$B$12*20,0) | S5: =IF(R5>=Scoring_Weights!$B$15,"Tier 1",IF(R5>=Scoring_Weights!$B$16,"Tier 2","Tier 3")) | T5: Wave 2 - energy / real-asset lending | U5: Cold | W5: Cascade map
A6: Clerville Investment Management | B6: Cascade map - AUM < US$5b | C6: London | D6: Specialty finance credit [K] | E6: n/a | F6: €5m to €30m | G6: ABF | H6: UK / Europe | I6: No | J6: Unknown | K6: 1 | L6: 1 | M6: 4 | N6: 1 | O6: 2 | P6: 1 | Q6: 3 | R6: =ROUND(SUMPRODUCT(K6:Q6,Scoring_Weights!$E$5:$K$5)/Scoring_Weights!$B$12*20,0) | S6: =IF(R6>=Scoring_Weights!$B$15,"Tier 1",IF(R6>=Scoring_Weights!$B$16,"Tier 2","Tier 3")) | T6: Tier 3 | U6: Cold | W6: Cascade map
A7: Invictus Capital Partners | B7: Cascade map - AUM < US$5b | C7: Washington DC | D7: Residential / consumer ABF [K] | E7: n/a | F7: US$10m+ | G7: ABF | H7: US | I7: No | J7: Unknown | K7: 0 | L7: 0 | M7: 3 | N7: 0 | O7: 2 | P7: 1 | Q7: 2 | R7: =ROUND(SUMPRODUCT(K7:Q7,Scoring_Weights!$E$5:$K$5)/Scoring_Weights!$B$12*20,0) | S7: =IF(R7>=Scoring_Weights!$B$15,"Tier 1",IF(R7>=Scoring_Weights!$B$16,"Tier 2","Tier 3")) | T7: Not relevant | U7: n/a | W7: Cascade map
A8: Kirkoswald Asset Management | B8: Cascade map - AUM < US$5b | C8: London | D8: Macro / credit hedge fund [K] | E8: n/a | F8: n/a | G8: Credit | H8: UK | I8: No | J8: Unknown | K8: 0 | L8: 0 | M8: 2 | N8: 0 | O8: 2 | P8: 1 | Q8: 2 | R8: =ROUND(SUMPRODUCT(K8:Q8,Scoring_Weights!$E$5:$K$5)/Scoring_Weights!$B$12*20,0) | S8: =IF(R8>=Scoring_Weights!$B$15,"Tier 1",IF(R8>=Scoring_Weights!$B$16,"Tier 2","Tier 3")) | T8: Not relevant | U8: n/a | W8: Cascade map
A9: Kartesia | B9: Cascade map - AUM < US$5b | C9: Luxembourg | D9: Lower-mid-market credit; KCO VI €1.3b | E9: €1.3b | F9: €10m to €60m | G9: Senior, hybrid, PIK | H9: Southern Europe team | I9: Sponsorless SMEs | J9: Unknown | K9: 3 | L9: 2 | M9: 4 | N9: 3 | O9: 3 | P9: 1 | Q9: 3 | R9: =ROUND(SUMPRODUCT(K9:Q9,Scoring_Weights!$E$5:$K$5)/Scoring_Weights!$B$12*20,0) | S9: =IF(R9>=Scoring_Weights!$B$15,"Tier 1",IF(R9>=Scoring_Weights!$B$16,"Tier 2","Tier 3")) | T9: Holdco hybrid at FID; Curity later | U9: LinkedIn first | W9: kartesia.com
A10: Highlake Capital | B10: Cascade map - AUM < US$5b | C10: London | D10: Specialty finance / ABF [K] | E10: n/a | F10: €5m to €30m | G10: ABF | H10: UK / Europe | I10: No | J10: Unknown | K10: 1 | L10: 1 | M10: 4 | N10: 1 | O10: 2 | P10: 1 | Q10: 3 | R10: =ROUND(SUMPRODUCT(K10:Q10,Scoring_Weights!$E$5:$K$5)/Scoring_Weights!$B$12*20,0) | S10: =IF(R10>=Scoring_Weights!$B$15,"Tier 1",IF(R10>=Scoring_Weights!$B$16,"Tier 2","Tier 3")) | T10: Tier 3 | U10: Cold | W10: Cascade map
A11: Varadero Capital | B11: Cascade map - AUM < US$5b | C11: New York | D11: Structured credit / ABF | E11: n/a | F11: US$10m+ | G11: ABF | H11: US | I11: No | J11: Unknown | K11: 0 | L11: 0 | M11: 3 | N11: 0 | O11: 2 | P11: 1 | Q11: 2 | R11: =ROUND(SUMPRODUCT(K11:Q11,Scoring_Weights!$E$5:$K$5)/Scoring_Weights!$B$12*20,0) | S11: =IF(R11>=Scoring_Weights!$B$15,"Tier 1",IF(R11>=Scoring_Weights!$B$16,"Tier 2","Tier 3")) | T11: Not relevant | U11: n/a | W11: Cascade map
A12: Chorus Capital | B12: Cascade map - AUM < US$5b | C12: London | D12: Bank significant-risk-transfer (SRT) investor | E12: n/a | F12: €20m+ | G12: SRT | H12: Europe | I12: No | J12: Unknown | K12: 0 | L12: 0 | M12: 2 | N12: 1 | O12: 2 | P12: 1 | Q12: 2 | R12: =ROUND(SUMPRODUCT(K12:Q12,Scoring_Weights!$E$5:$K$5)/Scoring_Weights!$B$12*20,0) | S12: =IF(R12>=Scoring_Weights!$B$15,"Tier 1",IF(R12>=Scoring_Weights!$B$16,"Tier 2","Tier 3")) | T12: Not relevant | U12: n/a | W12: Cascade map
A13: Serone Capital Management | B13: Cascade map - AUM < US$5b | C13: London | D13: European structured / ABS credit | E13: n/a | F13: €10m+ | G13: ABS | H13: Europe | I13: No | J13: Unknown | K13: 0 | L13: 0 | M13: 3 | N13: 1 | O13: 2 | P13: 1 | Q13: 2 | R13: =ROUND(SUMPRODUCT(K13:Q13,Scoring_Weights!$E$5:$K$5)/Scoring_Weights!$B$12*20,0) | S13: =IF(R13>=Scoring_Weights!$B$15,"Tier 1",IF(R13>=Scoring_Weights!$B$16,"Tier 2","Tier 3")) | T13: Not relevant | U13: n/a | W13: Cascade map
A14: SPF Investment Management | B14: Cascade map - AUM < US$5b | C14: London | D14: Specialty finance credit | E14: n/a | F14: €5m to €30m | G14: ABF | H14: Europe | I14: No | J14: Unknown | K14: 1 | L14: 1 | M14: 4 | N14: 1 | O14: 2 | P14: 1 | Q14: 3 | R14: =ROUND(SUMPRODUCT(K14:Q14,Scoring_Weights!$E$5:$K$5)/Scoring_Weights!$B$12*20,0) | S14: =IF(R14>=Scoring_Weights!$B$15,"Tier 1",IF(R14>=Scoring_Weights!$B$16,"Tier 2","Tier 3")) | T14: Tier 3 | U14: Cold | W14: Cascade map
A15: Viola Credit | B15: Cascade map - AUM < US$5b | C15: Tel Aviv / London | D15: Venture lending and ABF to fintech / tech companies | E15: n/a | F15: US$5m to US$50m | G15: Venture debt, warehouse | H15: Israel / Europe | I15: Tech lending; Israel cannabis-tolerant ecosystem | J15: Unknown | K15: 1 | L15: 2 | M15: 5 | N15: 2 | O15: 3 | P15: 1 | Q15: 4 | R15: =ROUND(SUMPRODUCT(K15:Q15,Scoring_Weights!$E$5:$K$5)/Scoring_Weights!$B$12*20,0) | S15: =IF(R15>=Scoring_Weights!$B$15,"Tier 1",IF(R15>=Scoring_Weights!$B$16,"Tier 2","Tier 3")) | T15: Wave 2 for Curity (Israeli network, InterCure / Bennu precedent) | U15: LinkedIn first | W15: Cascade map
A16: Orchard Global | B16: Cascade map - AUM < US$5b | C16: London / Singapore | D16: Structured credit, SRT, ABF | E16: n/a | F16: €20m+ | G16: Structured credit | H16: Global | I16: No | J16: Unknown | K16: 0 | L16: 0 | M16: 3 | N16: 1 | O16: 2 | P16: 1 | Q16: 2 | R16: =ROUND(SUMPRODUCT(K16:Q16,Scoring_Weights!$E$5:$K$5)/Scoring_Weights!$B$12*20,0) | S16: =IF(R16>=Scoring_Weights!$B$15,"Tier 1",IF(R16>=Scoring_Weights!$B$16,"Tier 2","Tier 3")) | T16: Not relevant | U16: n/a | W16: Cascade map
... A114: Blackstone (Credit & Insurance; ECRED) | B114: Cascade map - AUM > US$100b | C114: New York / London | D114: ECRED €2.6b NAV; infrastructure credit; 'Thermo Lysi structured product' idea in tracker via Argus | E114: n/a | F114: US$50m+ | G114: All | H114: Global | I114: Infrastructure | J114: Unknown | K114: 2 | L114: 0 | M114: 1 | N114: 1 | O114: 3 | P114: 2 | Q114: 1 | R114: =ROUND(SUMPRODUCT(K114:Q114,Scoring_Weights!$E$5:$K$5)/Scoring_Weights!$B$12*20,0) | S114: =IF(R114>=Scoring_Weights!$B$15,"Tier 1",IF(R114>=Scoring_Weights!$B$16,"Tier 2","Tier 3")) | T114: IVP-level; keep the Argus channel warm | U114: Warm via Argus | W114: Investor tracker; ecred.com

Sheet Investor_Universe
A1: Investor Universe
A2: Wider universe beyond the ABF map: direct lending, special situations, infrastructure and energy-transition credit, venture and growth debt, impact and DFI capital, cannabis-tolerant credit, placement agents and fund-finance providers. Scores are analyst judgement on the public evidence cited.
A4: Firm | B4: Category | C4: HQ / EU office | D4: Strategy / vehicle | E4: Fund size / AUM | F4: Ticket range | G4: Instruments | H4: Greece / Cyprus / S. Europe evidence | I4: Hard-asset / FOAK evidence | J4: Cannabis stance | K4: S1 IPL fit | L4: S2 CPEF fit | M4: S3 Ticket | N4: S4 Geography | O4: S5 Risk appetite | P4: S6 Warm path | Q4: S7 Speed | R4: Weighted score | S4: Tier | T4: Best use for Impactus | U4: Recommended channel | V4: Warm path via | W4: Source URL
A5: EIB - Cleantech Equity & Growth Capital Division (venture debt) | B5: DFI - venture debt | C5: Luxembourg | D5: EIB venture debt (quasi-equity for FOAK cleantech); Joltie €17.5m Greece precedent | E5: EIB Group Greece €3.5b (2025) | F5: €7.5m to €50m | G5: Venture debt: cash + PIK + warrants | H5: Record Greek lending; direct engagement with Impactus Feb-Sep 2026 | I5: Designed for FOAK; declined 30-04-2026 as 'mezzanine risk without equity reward'; re-engaged Sep 2026 via Sirec | J5: No formal exclusion; no precedent | K5: 5 | L5: 1 | M5: 5 | N5: 5 | O5: 4 | P5: 5 | Q5: 2 | R5: =ROUND(SUMPRODUCT(K5:Q5,Scoring_Weights!$E$5:$K$5)/Scoring_Weights!$B$12*20,0) | S5: =IF(R5>=Scoring_Weights!$B$15,"Tier 1",IF(R5>=Scoring_Weights!$B$16,"Tier 2","Tier 3")) | T5: Reopen VD at €20m to €35m with equity-like upside (higher warrant coverage) so the 'reward' objection is answered | U5: Warm - existing thread | V5: Sirec (Papageorgantas); direct to Casorati / Mitrakas | W5: Outlook threads Feb-Sep 2026; EIB press 2026-041
A6: Hellenic Innovation & Infrastructure Fund (HIIF) | B6: Greek impact / infra investor | C6: Athens | D6: Assessing €35m VD tranche at 10% blended; market-operator (state aid) test at IC | E6: n/a | F6: €10m to €50m | G6: Venture debt / hybrid | H6: Greek | I6: Live DD on Thermo Lysi since Jul 2026 | J6: n/a | K6: 5 | L6: 0 | M6: 5 | N6: 5 | O6: 4 | P6: 5 | Q6: 3 | R6: =ROUND(SUMPRODUCT(K6:Q6,Scoring_Weights!$E$5:$K$5)/Scoring_Weights!$B$12*20,0) | S6: =IF(R6>=Scoring_Weights!$B$15,"Tier 1",IF(R6>=Scoring_Weights!$B$16,"Tier 2","Tier 3")) | T6: Re-cut as staged commitment (development tranche now, construction tranche at FID); keep them ahead of the PMO reset | U6: Warm - existing thread | V6: Direct: Vlachos, Fragos, Giannakopoulos | W6: Outlook 'Impactus Group - HIIF' Jul-Aug 2026
A7: Credia Bank (Structured Finance) | B7: Greek bank - senior project debt | C7: Athens | D7: Senior facility term sheet c.€77.4m, 1.5x DSCR; LOI 6.5% / 4+10y / 1.3x avg DSCR | E7: n/a | F7: €20m to €100m | G7: Senior project finance, VAT facility | H7: Greek | I7: Term sheet on 20ktpa; 45ktpa update in credit process | J7: n/a | K7: 5 | L7: 0 | M7: 5 | N7: 5 | O7: 2 | P7: 5 | Q7: 2 | R7: =ROUND(SUMPRODUCT(K7:Q7,Scoring_Weights!$E$5:$K$5)/Scoring_Weights!$B$12*20,0) | S7: =IF(R7>=Scoring_Weights!$B$15,"Tier 1",IF(R7>=Scoring_Weights!$B$16,"Tier 2","Tier 3")) | T7: Deliver firm EPC price, TDD and CP list; run one competing bank (Piraeus or Eurobank PF) for tension | U7: Warm - existing thread | V7: Venero (Chatzilias); direct to Mitrou | W7: Credia LOI thread Jul-Aug 2026
A8: Sirec Energy | B8: Greek energy fund - co-investor | C8: Athens | D8: Executed TS Mar 2026 at c.€34m post-money Thermo Lysi; advising on EIB | E8: n/a | F8: €2m to €10m | G8: Equity | H8: Greek | I8: Co-investor in Thermo Lysi | J8: n/a | K8: 4 | L8: 0 | M8: 4 | N8: 5 | O8: 4 | P8: 5 | Q8: 4 | R8: =ROUND(SUMPRODUCT(K8:Q8,Scoring_Weights!$E$5:$K$5)/Scoring_Weights!$B$12*20,0) | S8: =IF(R8>=Scoring_Weights!$B$15,"Tier 1",IF(R8>=Scoring_Weights!$B$16,"Tier 2","Tier 3")) | T8: Reference co-investor; ask for Greek bank and EIB introductions and a follow-on | U8: Warm | V8: Direct: Papageorgantas, Alissandratos | W8: Outlook 17-09-2026
A9: Piraeus Bank (Structured / Green Finance) | B9: Greek bank - project finance | C9: Athens | D9: Largest Greek PF desk; EIB €950m on-lending line; RRF green loans | E9: Assets >€75b [K] | F9: €20m to €150m | G9: Senior project finance | H9: Greek | I9: Waste / energy SPVs [K] | J9: Unknown | K9: 4 | L9: 1 | M9: 5 | N9: 5 | O9: 2 | P9: 3 | Q9: 2 | R9: =ROUND(SUMPRODUCT(K9:Q9,Scoring_Weights!$E$5:$K$5)/Scoring_Weights!$B$12*20,0) | S9: =IF(R9>=Scoring_Weights!$B$15,"Tier 1",IF(R9>=Scoring_Weights!$B$16,"Tier 2","Tier 3")) | T9: Competing senior bid to Credia; also Ethniki Insurance (Piraeus-owned) as LP | U9: Warm intro via Axia / PwC Greece | V9: Axia (Achilleoudis); PwC Greece (Kantounis) | W9: EIB press 2026-041 [K]
A10: Eurobank (Project Finance) and Eurobank Cyprus | B10: Greek / Cypriot bank | C10: Athens / Nicosia | D10: Project finance Greece; Eurobank Cyprus depositary and first InvestEU guarantee in Cyprus (€62.5m) | E10: n/a | F10: €10m to €100m | G10: Senior PF; small capital-call line | H10: Greek and Cypriot | I10: PF desk for energy / waste [K] | J10: Unknown | K10: 4 | L10: 1 | M10: 5 | N10: 5 | O10: 2 | P10: 3 | Q10: 3 | R10: =ROUND(SUMPRODUCT(K10:Q10,Scoring_Weights!$E$5:$K$5)/Scoring_Weights!$B$12*20,0) | S10: =IF(R10>=Scoring_Weights!$B$15,"Tier 1",IF(R10>=Scoring_Weights!$B$16,"Tier 2","Tier 3")) | T10: Second competing senior bid; capital-call line for the PE Fund (ex-CPEF) | U10: Warm intro via Argus (depositary relationship) | V10: Argus Management | W10: EIF press 2025-343; research briefing
A11: Alpha Bank (Wholesale / Wealth Management Greece) | B11: Greek bank | C11: Athens | D11: Cooperation discussion Sep 2026; wealth-management distribution of Impactus products | E11: n/a | F11: €10m to €100m PF; private-placement distribution | G11: Senior PF; distribution | H11: Greek | I11: PF desk [K] | J11: Unknown | K11: 3 | L11: 2 | M11: 4 | N11: 5 | O11: 2 | P11: 4 | Q11: 3 | R11: =ROUND(SUMPRODUCT(K11:Q11,Scoring_Weights!$E$5:$K$5)/Scoring_Weights!$B$12*20,0) | S11: =IF(R11>=Scoring_Weights!$B$15,"Tier 1",IF(R11>=Scoring_Weights!$B$16,"Tier 2","Tier 3")) | T11: Distribution agreement for professional clients; PF desk as third senior bid | U11: Warm - existing thread | V11: Miltos Michailas (AM relationship) | W11: Outlook 09-09-2026
A12: National Bank of Greece (Project Finance) | B12: Greek bank | C12: Athens | D12: €250m EIB green line; €200m agri / bioeconomy line 2026 | E12: n/a | F12: €20m to €150m | G12: Senior PF | H12: Greek | I12: Green / bioeconomy lines [K] | J12: Unknown | K12: 3 | L12: 1 | M12: 4 | N12: 5 | O12: 2 | P12: 2 | Q12: 2 | R12: =ROUND(SUMPRODUCT(K12:Q12,Scoring_Weights!$E$5:$K$5)/Scoring_Weights!$B$12*20,0) | S12: =IF(R12>=Scoring_Weights!$B$15,"Tier 1",IF(R12>=Scoring_Weights!$B$16,"Tier 2","Tier 3")) | T12: Fourth senior option; bioeconomy line could suit Curity (agri) | U12: Cold / via PwC Greece | V12: PwC Greece | W12: EIB press 2026-041
A13: Hellenic Development Bank (HDB) / HDBI | B13: Greek national promotional bank | C13: Athens | D13: Green Co-Financing (40% interest-free); HDBI is LP in Elikonos 3 | E13: €2b RRF allocation | F13: €1m to €20m | G13: Co-financed loans; fund-of-funds | H13: Greek | I13: RES / energy efficiency focus; disbursement deadline 31-08-2026 | J13: Unknown | K13: 2 | L13: 1 | M13: 4 | N13: 5 | O13: 1 | P13: 2 | Q13: 2 | R13: =ROUND(SUMPRODUCT(K13:Q13,Scoring_Weights!$E$5:$K$5)/Scoring_Weights!$B$12*20,0) | S13: =IF(R13>=Scoring_Weights!$B$15,"Tier 1",IF(R13>=Scoring_Weights!$B$16,"Tier 2","Tier 3")) | T13: Check 2027 windows; HDBI as LP in a Greek-domiciled feeder | U13: Cold / via PwC Greece | V13: PwC Greece | W13: hdb.gr; research briefing
A14: Growthfund / HCAP | B14: Greek sovereign holding | C14: Athens | D14: c.€6b state assets; evolving into National Investment Fund for Growth; BlackRock FMA | E14: €6b | F14: €10m+ | G14: Equity / fund commitments | H14: Greek | I14: Strategic infrastructure | J14: Unlikely | K14: 2 | L14: 0 | M14: 3 | N14: 5 | O14: 2 | P14: 1 | Q14: 1 | R14: =ROUND(SUMPRODUCT(K14:Q14,Scoring_Weights!$E$5:$K$5)/Scoring_Weights!$B$12*20,0) | S14: =IF(R14>=Scoring_Weights!$B$15,"Tier 1",IF(R14>=Scoring_Weights!$B$16,"Tier 2","Tier 3")) | T14: IVP-level conversation only | U14: Cold | W14: growthfund.gr
A15: Elikonos Capital Partners | B15: Greek lower-mid credit / equity AIF | C15: Athens | D15: Elikonos 3 €175m first close (HDBI, EIF, EBRD) | E15: €175m | F15: €3m to €15m | G15: Hybrid, mezz, equity | H15: Greek | I15: SME growth; EIF-backed (state-aid sensitive) | J15: Excluded in practice (EIF LP) | K15: 2 | L15: 1 | M15: 5 | N15: 5 | O15: 2 | P15: 4 | Q15: 3 | R15: =ROUND(SUMPRODUCT(K15:Q15,Scoring_Weights!$E$5:$K$5)/Scoring_Weights!$B$12*20,0) | S15: =IF(R15>=Scoring_Weights!$B$15,"Tier 1",IF(R15>=Scoring_Weights!$B$16,"Tier 2","Tier 3")) | T15: Curity growth facility once EBITDA positive; 'Pantelis Solomis' in the tracker is the warm path | U15: Warm - in tracker | V15: AM (Pantelis Solomis) | W15: elikonos.com
A16: Halcyon Equity Partners | B16: Greek AIF | C16: Athens | D16: €208m AUM | E16: €208m | F16: €3m to €15m | G16: Equity / hybrid | H16: Greek | I16: SME | J16: Unknown | K16: 2 | L16: 1 | M16: 4 | N16: 5 | O16: 2 | P16: 1 | Q16: 3 | R16: =ROUND(SUMPRODUCT(K16:Q16,Scoring_Weights!$E$5:$K$5)/Scoring_Weights!$B$12*20,0) | S16: =IF(R16>=Scoring_Weights!$B$15,"Tier 1",IF(R16>=Scoring_Weights!$B$16,"Tier 2","Tier 3")) | T16: Curity / IPL co-investor | U16: Cold | W16: halcyonequitypartners.com
A17: Waterwheel Capital Management | B17: Greek credit specialist | C17: Athens / London | D17: Hellenic Credit I DAC; Hellenic Opportunities | E17: n/a | F17: €5m to €30m | G17: Special situations credit | H17: Greek | I17: Distressed / NPL heritage | J17: Unknown | K17: 3 | L17: 1 | M17: 4 | N17: 5 | O17: 3 | P17: 1 | Q17: 3 | R17: =ROUND(SUMPRODUCT(K17:Q17,Scoring_Weights!$E$5:$K$5)/Scoring_Weights!$B$12*20,0) | S17: =IF(R17>=Scoring_Weights!$B$15,"Tier 1",IF(R17>=Scoring_Weights!$B$16,"Tier 2","Tier 3")) | T17: Holdco / IPL hybrid; Greek credit expertise | U17: Cold | W17: aum13f.com
A18: Kartesia | B18: Lower-mid-market private credit | C18: Luxembourg / Brussels; Madrid | D18: Kartesia Credit Opportunities VI €1.3b (Jul 2025); c.€6b AUM; on the Cascade map (<US$5b ABF bucket) | E18: €1.3b (KCO VI) | F18: €10m to €60m | G18: Senior, unitranche, hybrid, PIK | H18: Southern Europe team (Iberia, Italy) [K] | I18: Sponsorless SMEs; some real-asset backed | J18: Unknown | K18: 3 | L18: 2 | M18: 4 | N18: 3 | O18: 3 | P18: 1 | Q18: 3 | R18: =ROUND(SUMPRODUCT(K18:Q18,Scoring_Weights!$E$5:$K$5)/Scoring_Weights!$B$12*20,0) | S18: =IF(R18>=Scoring_Weights!$B$15,"Tier 1",IF(R18>=Scoring_Weights!$B$16,"Tier 2","Tier 3")) | T18: Holdco / sponsor-level hybrid for IPL at FID; Curity growth line later | U18: Cold - LinkedIn first | W18: kartesia.com press 04-07-2025
A19: Capza (BNPP AM Alts) | B19: Mid-market private debt | C19: Paris / Madrid | D19: Capza PD 7 c.€1.4b first close; AUM >€9b; Transition strategy | E19: €1.4b | F19: €10m to €80m | G19: Unitranche, mezz | H19: Iberia / Italy | I19: Mid-market corporates | J19: Unknown | K19: 2 | L19: 2 | M19: 3 | N19: 2 | O19: 2 | P19: 1 | Q19: 3 | R19: =ROUND(SUMPRODUCT(K19:Q19,Scoring_Weights!$E$5:$K$5)/Scoring_Weights!$B$12*20,0) | S19: =IF(R19>=Scoring_Weights!$B$15,"Tier 1",IF(R19>=Scoring_Weights!$B$16,"Tier 2","Tier 3")) | T19: Wave 2 | U19: Cold | W19: alts.axa-im.com press
A20: Muzinich & Co (Pan-European Private Debt) | B20: Lower-mid-market private debt | C20: London / Milan / Madrid | D20: c.US$38b AUM; European private debt ELTIF; parallel lending with banks | E20: n/a | F20: €5m to €30m | G20: Senior / unitranche; parallel lending | H20: Italy, Spain, France; no Greek office | I20: Mid-market | J20: Unknown | K20: 2 | L20: 2 | M20: 5 | N20: 2 | O20: 2 | P20: 1 | Q20: 3 | R20: =ROUND(SUMPRODUCT(K20:Q20,Scoring_Weights!$E$5:$K$5)/Scoring_Weights!$B$12*20,0) | S20: =IF(R20>=Scoring_Weights!$B$15,"Tier 1",IF(R20>=Scoring_Weights!$B$16,"Tier 2","Tier 3")) | T20: Curity growth line; ELTIF distribution model to study | U20: Cold | W20: muzinich.com
A21: Beechbrook Capital | B21: Lower-mid-market SME credit | C21: London | D21: UK SME Credit IV £151m first close; €2m to €25m bites | E21: £250m target | F21: €2m to €25m | G21: Senior, unitranche, mezz | H21: UK / Ireland mainly | I21: SMEs with EBITDA ≤£15m | J21: Unknown | K21: 1 | L21: 2 | M21: 5 | N21: 1 | O21: 2 | P21: 1 | Q21: 4 | R21: =ROUND(SUMPRODUCT(K21:Q21,Scoring_Weights!$E$5:$K$5)/Scoring_Weights!$B$12*20,0) | S21: =IF(R21>=Scoring_Weights!$B$15,"Tier 1",IF(R21>=Scoring_Weights!$B$16,"Tier 2","Tier 3")) | T21: Reference for terms; unlikely to lend in Greece | U21: Cold | W21: ACI 07-11-2024
A22: Hayfin Capital Management (Special Opportunities) | B22: Special situations / direct lending | C22: London | D22: DLF V >€15b (Jul 2026); Special Opportunities strategy; on Cascade map (US$20-100b) | E22: >€15b | F22: €25m to €150m | G22: Senior, special sits, hybrid | H22: Pan-European incl. Southern Europe | I22: Special-opportunities book takes asset-backed / complex credits | J22: Unknown | K22: 3 | L22: 1 | M22: 2 | N22: 3 | O22: 4 | P22: 1 | Q22: 2 | R22: =ROUND(SUMPRODUCT(K22:Q22,Scoring_Weights!$E$5:$K$5)/Scoring_Weights!$B$12*20,0) | S22: =IF(R22>=Scoring_Weights!$B$15,"Tier 1",IF(R22>=Scoring_Weights!$B$16,"Tier 2","Tier 3")) | T22: IVP-level or a €35m+ hybrid at FID; ticket floor is the issue | U22: Cold | W22: hayfin.com 2026
A23: Tikehau Capital (Private Debt / Special Opportunities / Decarbonisation) | B23: Private debt, special sits, transition | C23: Paris / Madrid / Milan | D23: European DL VI €5.2b (Jul 2026); special sits €1b+ (H1 2026); on Cascade map | E23: €5.2b | F23: €20m to €100m | G23: Senior, special sits, decarbonisation equity | H23: Iberia, Italy; no Greek office | I23: Decarbonisation strategy invests in transition assets | J23: Unknown | K23: 3 | L23: 1 | M23: 3 | N23: 3 | O23: 3 | P23: 1 | Q23: 2 | R23: =ROUND(SUMPRODUCT(K23:Q23,Scoring_Weights!$E$5:$K$5)/Scoring_Weights!$B$12*20,0) | S23: =IF(R23>=Scoring_Weights!$B$15,"Tier 1",IF(R23>=Scoring_Weights!$B$16,"Tier 2","Tier 3")) | T23: Special Opportunities or Decarbonisation team for IVP / IPL | U23: Cold - LinkedIn first | W23: ACI 24-07-2026
A24: Pemberton Asset Management | B24: Mid-market private credit; NAV | C24: London | D24: MMD IV + Senior Loan €6.1b; NAV Core I US$1.7b; on Cascade map | E24: US$29b AUM | F24: €30m to €150m | G24: Senior, unitranche, NAV | H24: Pan-European | I24: Corporate | J24: Unknown | K24: 1 | L24: 1 | M24: 2 | N24: 2 | O24: 2 | P24: 1 | Q24: 2 | R24: =ROUND(SUMPRODUCT(K24:Q24,Scoring_Weights!$E$5:$K$5)/Scoring_Weights!$B$12*20,0) | S24: =IF(R24>=Scoring_Weights!$B$15,"Tier 1",IF(R24>=Scoring_Weights!$B$16,"Tier 2","Tier 3")) | T24: Tier 3 - keep informed | U24: Cold | W24: creditflux 14-05-2025
A25: Arcmont Asset Management (Impact Lending) | B25: Direct lending | C25: London | D25: DL V €15-17b target; Impact Lending strategy | E25: >€11b raised | F25: €30m to €200m | G25: Senior / unitranche | H25: Pan-European | I25: Impact Lending sleeve | J25: Unknown | K25: 1 | L25: 1 | M25: 2 | N25: 2 | O25: 2 | P25: 1 | Q25: 2 | R25: =ROUND(SUMPRODUCT(K25:Q25,Scoring_Weights!$E$5:$K$5)/Scoring_Weights!$B$12*20,0) | S25: =IF(R25>=Scoring_Weights!$B$15,"Tier 1",IF(R25>=Scoring_Weights!$B$16,"Tier 2","Tier 3")) | T25: Tier 3 | U25: Cold | W25: PitchBook 2026
A26: Blantyre Capital | B26: Special situations | C26: London | D26: Special Situations Fund II | E26: n/a | F26: €10m to €75m | G26: Bespoke capital solutions, PIK | H26: Pan-European incl. Southern Europe [K] | I26: Complex / stressed credits | J26: Unknown | K26: 3 | L26: 1 | M26: 4 | N26: 3 | O26: 5 | P26: 1 | Q26: 3 | R26: =ROUND(SUMPRODUCT(K26:Q26,Scoring_Weights!$E$5:$K$5)/Scoring_Weights!$B$12*20,0) | S26: =IF(R26>=Scoring_Weights!$B$15,"Tier 1",IF(R26>=Scoring_Weights!$B$16,"Tier 2","Tier 3")) | T26: €35m hybrid at 14% to 18% all-in | U26: Cold - LinkedIn first | W26: PitchBook fund profile
A27: Cheyne Capital (Strategic Value Credit) | B27: Special situations / real assets | C27: London | D27: Strategic Value Credit; real-estate credit; on Cascade map | E27: n/a | F27: €20m to €150m | G27: Opportunistic credit, real-asset lending | H27: Pan-European | I27: Real assets | J27: Unknown | K27: 3 | L27: 1 | M27: 3 | N27: 2 | O27: 4 | P27: 1 | Q27: 2 | R27: =ROUND(SUMPRODUCT(K27:Q27,Scoring_Weights!$E$5:$K$5)/Scoring_Weights!$B$12*20,0) | S27: =IF(R27>=Scoring_Weights!$B$15,"Tier 1",IF(R27>=Scoring_Weights!$B$16,"Tier 2","Tier 3")) | T27: Wave 2 | U27: Cold | W27: cheynecapital.com
... A45: Tiger Infrastructure Partners | B45: Growth infrastructure equity | C45: New York / London | D45: Bolder Industries (Antwerp pyrolysis) growth investment Feb 2025; US$25m to US$100m tickets | E45: n/a | F45: US$25m to US$100m | G45: Growth equity | H45: Europe (Antwerp) | I45: Direct pyrolysis precedent | J45: n/a | K45: 4 | L45: 0 | M45: 3 | N45: 2 | O45: 5 | P45: 1 | Q45: 3 | R45: =ROUND(SUMPRODUCT(K45:Q45,Scoring_Weights!$E$5:$K$5)/Scoring_Weights!$B$12*20,0) | S45: =IF(R45>=Scoring_Weights!$B$15,"Tier 1",IF(R45>=Scoring_Weights!$B$16,"Tier 2","Tier 3")) | T45: Wave 1: IVP anchor conversation; they have underwritten Pyrum-comparable risk | U45: Cold - LinkedIn first | W45: PR Newswire Feb 2025
A46: Antin Infrastructure Partners | B46: Infrastructure equity | C46: Paris | D46: Infiniteria (Enviro / Michelin) tyre-pyrolysis JV - now in dispute with Enviro | E46: n/a | F46: €100m+ | G46: Equity | H46: Europe | I46: Direct pyrolysis precedent (troubled) | J46: n/a | K46: 3 | L46: 0 | M46: 1 | N46: 2 | O46: 4 | P46: 3 | Q46: 1 | R46: =ROUND(SUMPRODUCT(K46:Q46,Scoring_Weights!$E$5:$K$5)/Scoring_Weights!$B$12*20,0) | S46: =IF(R46>=Scoring_Weights!$B$15,"Tier 1",IF(R46>=Scoring_Weights!$B$16,"Tier 2","Tier 3")) | T46: Later-stage buyer; 'Secure EoI' already in tracker | U46: Warm - in tracker (Argus) | V46: Argus | W46: antin-ip.com; Enviro releases 2026
A47: Novo Holdings / A.P. Moller Holding | B47: Strategic / evergreen investors | C47: Copenhagen | D47: €75m equity into Circtec (Delfzijl tyre pyrolysis) | E47: n/a | F47: €25m+ | G47: Equity | H47: Europe | I47: Direct pyrolysis precedent | J47: n/a | K47: 3 | L47: 0 | M47: 2 | N47: 1 | O47: 4 | P47: 1 | Q47: 1 | R47: =ROUND(SUMPRODUCT(K47:Q47,Scoring_Weights!$E$5:$K$5)/Scoring_Weights!$B$12*20,0) | S47: =IF(R47>=Scoring_Weights!$B$15,"Tier 1",IF(R47>=Scoring_Weights!$B$16,"Tier 2","Tier 3")) | T47: IVP-level; Circtec is a competitor reference | U47: Cold | W47: apmoller.com May 2024
A48: Invest-NL | B48: Dutch promotional investor | C48: Amsterdam | D48: Xycle, Pryme (chemical recycling) | E48: n/a | F48: €5m to €30m | G48: Equity / debt | H48: Netherlands only | I48: Chemical recycling precedent | J48: n/a | K48: 1 | L48: 0 | M48: 3 | N48: 0 | O48: 4 | P48: 1 | Q48: 2 | R48: =ROUND(SUMPRODUCT(K48:Q48,Scoring_Weights!$E$5:$K$5)/Scoring_Weights!$B$12*20,0) | S48: =IF(R48>=Scoring_Weights!$B$15,"Tier 1",IF(R48>=Scoring_Weights!$B$16,"Tier 2","Tier 3")) | T48: Not eligible (NL mandate); reference only | U48: n/a | W48: invest-nl.nl
A49: Infinity Recycling (Circular Plastics Fund) | B49: Circular-economy VC / growth | C49: Rotterdam | D49: CPF €175m (EIF €50m); Alterra, Itero, Pryme | E49: €175m | F49: €5m to €15m | G49: Equity | H49: Europe | I49: Plastics chemical recycling | J49: n/a | K49: 2 | L49: 0 | M49: 4 | N49: 1 | O49: 4 | P49: 1 | Q49: 3 | R49: =ROUND(SUMPRODUCT(K49:Q49,Scoring_Weights!$E$5:$K$5)/Scoring_Weights!$B$12*20,0) | S49: =IF(R49>=Scoring_Weights!$B$15,"Tier 1",IF(R49>=Scoring_Weights!$B$16,"Tier 2","Tier 3")) | T49: Co-investor in IVP; plastics not tyres | U49: Cold | W49: Packaging Europe
A50: Emerald Technology Ventures | B50: Industrial innovation VC | C50: Zurich | D50: Emerald Industrial Innovation Fund; corporate LPs (BASF etc.) | E50: n/a | F50: €3m to €15m | G50: Equity | H50: Europe | I50: Industrial cleantech | J50: n/a | K50: 2 | L50: 0 | M50: 3 | N50: 1 | O50: 4 | P50: 1 | Q50: 3 | R50: =ROUND(SUMPRODUCT(K50:Q50,Scoring_Weights!$E$5:$K$5)/Scoring_Weights!$B$12*20,0) | S50: =IF(R50>=Scoring_Weights!$B$15,"Tier 1",IF(R50>=Scoring_Weights!$B$16,"Tier 2","Tier 3")) | T50: Co-investor at sponsor level | U50: Cold | W50: emerald.vc [K]
A51: Kreos Capital (BlackRock) | B51: Venture / growth debt | C51: London | D51: >US$7b committed, 830+ deals; Aris Constantinides (General Partner) is Greek | E51: n/a | F51: €5m to €50m | G51: Growth debt with warrants | H51: Pan-European | I51: VC-backed revenue companies | J51: No exclusion located | K51: 2 | L51: 3 | M51: 5 | N51: 2 | O51: 3 | P51: 2 | Q51: 4 | R51: =ROUND(SUMPRODUCT(K51:Q51,Scoring_Weights!$E$5:$K$5)/Scoring_Weights!$B$12*20,0) | S51: =IF(R51>=Scoring_Weights!$B$15,"Tier 1",IF(R51>=Scoring_Weights!$B$16,"Tier 2","Tier 3")) | T51: Curity growth line at 12 months of audited sales; Greek partner as door-opener | U51: LinkedIn first (Constantinides) | V51: Greek diaspora angle | W51: tulacap.com; research briefing
A52: Claret Capital Partners | B52: Growth debt | C52: Dublin / London | D52: Fund IV €575m | E52: €575m | F52: €3m to €30m | G52: Growth debt | H52: Pan-European | I52: VC-backed | J52: No exclusion located | K52: 1 | L52: 3 | M52: 5 | N52: 2 | O52: 3 | P52: 1 | Q52: 4 | R52: =ROUND(SUMPRODUCT(K52:Q52,Scoring_Weights!$E$5:$K$5)/Scoring_Weights!$B$12*20,0) | S52: =IF(R52>=Scoring_Weights!$B$15,"Tier 1",IF(R52>=Scoring_Weights!$B$16,"Tier 2","Tier 3")) | T52: Curity growth line 2027 | U52: Cold | W52: TNW
A53: Atempo Growth | B53: Growth debt | C53: London / Madrid | D53: Fund II >€455m; c.€850m AUM; Santander backing | E53: €455m | F53: €3m to €25m | G53: Growth debt | H53: Southern Europe presence (Madrid) | I53: VC-backed | J53: No exclusion located | K53: 1 | L53: 3 | M53: 5 | N53: 3 | O53: 3 | P53: 1 | Q53: 4 | R53: =ROUND(SUMPRODUCT(K53:Q53,Scoring_Weights!$E$5:$K$5)/Scoring_Weights!$B$12*20,0) | S53: =IF(R53>=Scoring_Weights!$B$15,"Tier 1",IF(R53>=Scoring_Weights!$B$16,"Tier 2","Tier 3")) | T53: Curity growth line 2027 | U53: Cold | W53: capitalranking.com
A54: Chicago Atlantic (REFI / BDC) | B54: Specialist cannabis credit | C54: Chicago | D54: REFI US$453m, 26 borrowers, 15.8% YTM (30-06-2026); co-founder John Mazarakis is Greek-American | E54: US$453m | F54: US$5m to US$50m | G54: Senior secured cannabis loans | H54: US only to date | I54: n/a | J54: Core mandate | K54: 0 | L54: 4 | M54: 5 | N54: 1 | O54: 4 | P54: 1 | Q54: 3 | R54: =ROUND(SUMPRODUCT(K54:Q54,Scoring_Weights!$E$5:$K$5)/Scoring_Weights!$B$12*20,0) | S54: =IF(R54>=Scoring_Weights!$B$15,"Tier 1",IF(R54>=Scoring_Weights!$B$16,"Tier 2","Tier 3")) | T54: Wave 1 for CPEF: test European appetite; €3m to €10m at 13% to 16% | U54: LinkedIn first (Mazarakis) | V54: Greek diaspora angle | W54: REFI 10-Q via research briefing
A55: Advanced Flower Capital (AFC Gamma) | B55: Specialist cannabis credit | C55: West Palm Beach | D55: US$290m, 17 loans, 13.2% yield, 35.7% non-accrual | E55: US$290m | F55: US$5m to US$40m | G55: Senior secured | H55: US only | I55: n/a | J55: Core mandate | K55: 0 | L55: 3 | M55: 5 | N55: 0 | O55: 3 | P55: 1 | Q55: 2 | R55: =ROUND(SUMPRODUCT(K55:Q55,Scoring_Weights!$E$5:$K$5)/Scoring_Weights!$B$12*20,0) | S55: =IF(R55>=Scoring_Weights!$B$15,"Tier 1",IF(R55>=Scoring_Weights!$B$16,"Tier 2","Tier 3")) | T55: Wave 2; distressed book limits appetite | U55: Cold | W55: AFCG 10-Q via research briefing
A56: Artemis Growth Partners | B56: Cannabis growth equity / hybrid | C56: London / New York | D56: Fund VII US$200m target, c.75% Europe; c.US$400m AUM; Bloomwell investor | E56: US$200m | F56: US$5m to US$25m | G56: Equity / hybrid | H56: Europe focus | I56: n/a | J56: Core mandate | K56: 0 | L56: 5 | M56: 5 | N56: 2 | O56: 4 | P56: 1 | Q56: 3 | R56: =ROUND(SUMPRODUCT(K56:Q56,Scoring_Weights!$E$5:$K$5)/Scoring_Weights!$B$12*20,0) | S56: =IF(R56>=Scoring_Weights!$B$15,"Tier 1",IF(R56>=Scoring_Weights!$B$16,"Tier 2","Tier 3")) | T56: Wave 1 for CPEF: only fund with stated European allocation | U56: LinkedIn first | W56: research briefing (cannabis)
A57: Casa Verde Capital | B57: Cannabis VC | C57: Los Angeles | D57: Cansativa Series B lead (€13m, 2022); Sanity Group investor | E57: n/a | F57: US$2m to US$15m | G57: Equity | H57: Europe via portfolio | I57: n/a | J57: Core mandate | K57: 0 | L57: 3 | M57: 5 | N57: 1 | O57: 4 | P57: 1 | Q57: 3 | R57: =ROUND(SUMPRODUCT(K57:Q57,Scoring_Weights!$E$5:$K$5)/Scoring_Weights!$B$12*20,0) | S57: =IF(R57>=Scoring_Weights!$B$15,"Tier 1",IF(R57>=Scoring_Weights!$B$16,"Tier 2","Tier 3")) | T57: Wave 2 co-investor | U57: Cold | W57: research briefing (cannabis)
A58: Curaleaf International | B58: Strategic acquirer (cannabis) | C58: London | D58: US$500m senior secured notes 11.5% (Feb 2026) fund European M&A; bought Four 20 Pharma 100%; Clever Leaves Portugal assets; bid for Aurora | E58: n/a | F58: €2m to €50m | G58: Acquisition / offtake | H58: Germany, Portugal, UK | I58: n/a | J58: Core | K58: 0 | L58: 4 | M58: 5 | N58: 2 | O58: 5 | P58: 1 | Q58: 3 | R58: =ROUND(SUMPRODUCT(K58:Q58,Scoring_Weights!$E$5:$K$5)/Scoring_Weights!$B$12*20,0) | S58: =IF(R58>=Scoring_Weights!$B$15,"Tier 1",IF(R58>=Scoring_Weights!$B$16,"Tier 2","Tier 3")) | T58: Strategic buyer / offtaker for Curity; price discovery for the equity fallback | U58: LinkedIn / corporate development | W58: research briefing (cannabis)
A59: Organigram Global (owner of Sanity Group) | B59: Strategic acquirer (cannabis) | C59: Toronto / Berlin | D59: €11.5m convertible into Sanity at 10% (2024) then acquisition €107m + earnout (Apr 2026); ATB senior facilities | E59: n/a | F59: €5m to €100m | G59: Convertible / acquisition | H59: Germany | I59: n/a | J59: Core | K59: 0 | L59: 4 | M59: 4 | N59: 2 | O59: 5 | P59: 1 | Q59: 3 | R59: =ROUND(SUMPRODUCT(K59:Q59,Scoring_Weights!$E$5:$K$5)/Scoring_Weights!$B$12*20,0) | S59: =IF(R59>=Scoring_Weights!$B$15,"Tier 1",IF(R59>=Scoring_Weights!$B$16,"Tier 2","Tier 3")) | T59: Offtake and convertible precedent for Curity | U59: Cold | W59: research briefing (cannabis)
A60: Cantourage Group SE | B60: German importer / distributor (listed) | C60: Berlin | D60: FY26 guidance €85-95m revenue; net cash €9.3m | E60: n/a | F60: n/a | G60: Offtake / supply agreement | H60: Germany | I60: n/a | J60: Core | K60: 0 | L60: 4 | M60: 5 | N60: 2 | O60: 3 | P60: 1 | Q60: 4 | R60: =ROUND(SUMPRODUCT(K60:Q60,Scoring_Weights!$E$5:$K$5)/Scoring_Weights!$B$12*20,0) | S60: =IF(R60>=Scoring_Weights!$B$15,"Tier 1",IF(R60>=Scoring_Weights!$B$16,"Tier 2","Tier 3")) | T60: Offtake contract = the collateral a lender will value | U60: LinkedIn / commercial | W60: research briefing (cannabis)
A61: ELPEN Pharmaceutical (family office) | B61: Greek pharma family office | C61: Athens | D61: €500k CPEF + €500k IPL discussed Apr 2026 | E61: n/a | F61: €0.5m to €5m | G61: Equity / convertible | H61: Greek | I61: n/a | J61: Tolerant | K61: 1 | L61: 4 | M61: 5 | N61: 5 | O61: 3 | P61: 4 | Q61: 3 | R61: =ROUND(SUMPRODUCT(K61:Q61,Scoring_Weights!$E$5:$K$5)/Scoring_Weights!$B$12*20,0) | S61: =IF(R61>=Scoring_Weights!$B$15,"Tier 1",IF(R61>=Scoring_Weights!$B$16,"Tier 2","Tier 3")) | T61: Natural strategic for Curity; re-open | U61: Warm - in tracker (DP) | V61: DP | W61: Investor tracker 17-04-2026
A62: Argus Management Ltd (AIFM) and its provident-fund channel | B62: AIFM / distributor | C62: Nicosia | D62: AIFM of Impactus RAIF; presents to ETYK, PEO, Cyta, Lawyers' provident funds; JP Morgan / Blackstone / Schroders contacts | E62: n/a | F62: €150k to €2m per fund | G62: Fund units, notes | H62: Cyprus | I62: n/a | J62: Case by case | K62: 3 | L62: 2 | M62: 5 | N62: 5 | O62: 2 | P62: 5 | Q62: 3 | R62: =ROUND(SUMPRODUCT(K62:Q62,Scoring_Weights!$E$5:$K$5)/Scoring_Weights!$B$12*20,0) | S62: =IF(R62>=Scoring_Weights!$B$15,"Tier 1",IF(R62>=Scoring_Weights!$B$16,"Tier 2","Tier 3")) | T62: Convert the two €1m provident-fund IC presentations; design a prudent-person compliant note | U62: Warm | V62: AM | W62: Investor tracker 03-08-2026
A63: Muhanna & Co (pension administrator) | B63: Gateway to Cyprus provident funds | C63: Nicosia | D63: General consultant to PEO fund; administers Doctors' Fund (existing IPL shareholder) | E63: n/a | F63: €200k to €1m per fund | G63: Fund units / direct | H63: Cyprus | I63: n/a | J63: Case by case | K63: 3 | L63: 2 | M63: 5 | N63: 5 | O63: 2 | P63: 5 | Q63: 3 | R63: =ROUND(SUMPRODUCT(K63:Q63,Scoring_Weights!$E$5:$K$5)/Scoring_Weights!$B$12*20,0) | S63: =IF(R63>=Scoring_Weights!$B$15,"Tier 1",IF(R63>=Scoring_Weights!$B$16,"Tier 2","Tier 3")) | T63: Close EY fair-value query, then ask for introductions to the other administered funds | U63: Warm | V63: KM (Theodosiou) | W63: Outlook 17-09-2026
A64: J. Safra Sarasin (Rachel Koen) | B64: Private bank | C64: Geneva / Nicosia | D64: IVP deck to investment analysis director (May 2026); introduced McMillan Woods | E64: n/a | F64: €1m to €10m | G64: Private-client placement | H64: Cyprus / international | I64: n/a | J64: Unlikely (bank policy) | K64: 2 | L64: 0 | M64: 4 | N64: 4 | O64: 2 | P64: 4 | Q64: 2 | R64: =ROUND(SUMPRODUCT(K64:Q64,Scoring_Weights!$E$5:$K$5)/Scoring_Weights!$B$12*20,0) | S64: =IF(R64>=Scoring_Weights!$B$15,"Tier 1",IF(R64>=Scoring_Weights!$B$16,"Tier 2","Tier 3")) | T64: IVP and PE Fund distribution | U64: Warm | V64: AM | W64: Outlook 15-05-2026
A65: KPMG Cyprus (Christos Vasiliou) - placement mandate | B65: Adviser | C65: Nicosia | D65: Mandate to raise c.€150-200m (Oct 2025); KPMG Sweden follow-up | E65: n/a | F65: n/a | G65: Advisory | H65: Cyprus / Nordics | I65: n/a | J65: Policy-constrained | K65: 2 | L65: 0 | M65: 3 | N65: 5 | O65: 2 | P65: 5 | Q65: 2 | R65: =ROUND(SUMPRODUCT(K65:Q65,Scoring_Weights!$E$5:$K$5)/Scoring_Weights!$B$12*20,0) | S65: =IF(R65>=Scoring_Weights!$B$15,"Tier 1",IF(R65>=Scoring_Weights!$B$16,"Tier 2","Tier 3")) | T65: Demand a named target list and 90-day plan | U65: Warm | V65: AM | W65: Investor tracker 22-10-2025
A66: Axia Ventures Group | B66: Greek / Cypriot investment bank | C66: Athens / Nicosia | D66: Meetings 2025-26; 'Infiniteria' update; Curity update Jun 2026 | E66: n/a | F66: n/a | G66: ECM / private placement | H66: Greece / Cyprus | I66: n/a | J66: Case by case | K66: 3 | L66: 2 | M66: 4 | N66: 5 | O66: 3 | P66: 5 | Q66: 3 | R66: =ROUND(SUMPRODUCT(K66:Q66,Scoring_Weights!$E$5:$K$5)/Scoring_Weights!$B$12*20,0) | S66: =IF(R66>=Scoring_Weights!$B$15,"Tier 1",IF(R66>=Scoring_Weights!$B$16,"Tier 2","Tier 3")) | T66: Run a Greek family-office process for IVP / IPL | U66: Warm | V66: AM (Achilleoudis) | W66: Outlook 24-06-2026
A67: Venero Capital Advisors | B67: Debt advisor (engaged) | C67: Athens | D67: Running Credia LOI / senior process; EIB thread | E67: n/a | F67: n/a | G67: Debt advisory | H67: Greece | I67: n/a | J67: n/a | K67: 4 | L67: 0 | M67: 5 | N67: 5 | O67: 3 | P67: 5 | Q67: 4 | R67: =ROUND(SUMPRODUCT(K67:Q67,Scoring_Weights!$E$5:$K$5)/Scoring_Weights!$B$12*20,0) | S67: =IF(R67>=Scoring_Weights!$B$15,"Tier 1",IF(R67>=Scoring_Weights!$B$16,"Tier 2","Tier 3")) | T67: Mandate to open two alternative senior / hybrid lenders in parallel to Credia | U67: Warm | V67: KM (Chatzilias, Politis) | W67: Credia thread
A68: Threadmark | B68: Placement agent - first-time / niche | C68: London | D68: Specialises in first-time managers; US$60b raised | E68: n/a | F68: €50m+ mandates | G68: Placement | H68: Global | I68: n/a | J68: Ask | K68: 2 | L68: 1 | M68: 4 | N68: 2 | O68: 3 | P68: 1 | Q68: 3 | R68: =ROUND(SUMPRODUCT(K68:Q68,Scoring_Weights!$E$5:$K$5)/Scoring_Weights!$B$12*20,0) | S68: =IF(R68>=Scoring_Weights!$B$15,"Tier 1",IF(R68>=Scoring_Weights!$B$16,"Tier 2","Tier 3")) | T68: IVP placement (success-fee only) | U68: Cold | W68: threadmark.com
A69: Elm Capital | B69: Placement agent - boutique | C69: London | D69: PE, credit funds, co-investments; €50m to €200m raises [K] | E69: n/a | F69: €50m+ | G69: Placement | H69: Europe | I69: n/a | J69: Ask | K69: 2 | L69: 1 | M69: 4 | N69: 2 | O69: 3 | P69: 1 | Q69: 3 | R69: =ROUND(SUMPRODUCT(K69:Q69,Scoring_Weights!$E$5:$K$5)/Scoring_Weights!$B$12*20,0) | S69: =IF(R69>=Scoring_Weights!$B$15,"Tier 1",IF(R69>=Scoring_Weights!$B$16,"Tier 2","Tier 3")) | T69: IVP placement | U69: Cold | W69: Companies House / LinkedIn
A70: Cebile Capital | B70: Placement agent - impact / emerging | C70: London | D70: Impact / emerging-manager raises from c.€50m [K] | E70: n/a | F70: €50m+ | G70: Placement | H70: Europe | I70: n/a | J70: Ask | K70: 2 | L70: 1 | M70: 4 | N70: 2 | O70: 3 | P70: 1 | Q70: 3 | R70: =ROUND(SUMPRODUCT(K70:Q70,Scoring_Weights!$E$5:$K$5)/Scoring_Weights!$B$12*20,0) | S70: =IF(R70>=Scoring_Weights!$B$15,"Tier 1",IF(R70>=Scoring_Weights!$B$16,"Tier 2","Tier 3")) | T70: IVP placement | U70: Cold | W70: [K]
A71: Ambrosia Capital | B71: Greek boutique investment bank | C71: Athens | D71: ECM / private placements for Greek issuers [K] | E71: n/a | F71: n/a | G71: Placement | H71: Greece | I71: n/a | J71: Case by case | K71: 2 | L71: 1 | M71: 4 | N71: 5 | O71: 3 | P71: 1 | Q71: 3 | R71: =ROUND(SUMPRODUCT(K71:Q71,Scoring_Weights!$E$5:$K$5)/Scoring_Weights!$B$12*20,0) | S71: =IF(R71>=Scoring_Weights!$B$15,"Tier 1",IF(R71>=Scoring_Weights!$B$16,"Tier 2","Tier 3")) | T71: Greek family-office and insurer process | U71: Cold | W71: [K]
A72: Emergo Wealth / MeritKapital / Argus Stockbrokers | B72: Cyprus CIF distributors | C72: Nicosia / Limassol | D72: CySEC CIF licences permitting placing to well-informed investors | E72: n/a | F72: €100k to €1m per client | G72: Distribution | H72: Cyprus | I72: n/a | J72: Case by case | K72: 2 | L72: 2 | M72: 5 | N72: 5 | O72: 2 | P72: 2 | Q72: 4 | R72: =ROUND(SUMPRODUCT(K72:Q72,Scoring_Weights!$E$5:$K$5)/Scoring_Weights!$B$12*20,0) | S72: =IF(R72>=Scoring_Weights!$B$15,"Tier 1",IF(R72>=Scoring_Weights!$B$16,"Tier 2","Tier 3")) | T72: Distribution of the 8% note products | U72: Warm via Argus / CIFA | W72: CIFA member list
A73: Athlos Capital | B73: Cyprus asset manager | C73: Nicosia | D73: Manages CPEF cash; launching UBS-issued AMC | E73: n/a | F73: €1m to €10m | G73: AMC / certificate wrapper | H73: Cyprus | I73: n/a | J73: Tolerant (existing) | K73: 2 | L73: 3 | M73: 5 | N73: 5 | O73: 2 | P73: 5 | Q73: 4 | R73: =ROUND(SUMPRODUCT(K73:Q73,Scoring_Weights!$E$5:$K$5)/Scoring_Weights!$B$12*20,0) | S73: =IF(R73>=Scoring_Weights!$B$15,"Tier 1",IF(R73>=Scoring_Weights!$B$16,"Tier 2","Tier 3")) | T73: AMC wrapper for the Impactus fixed-income products | U73: Warm | V73: MI | W73: Outlook 21-09-2026
A74: Bank of Cyprus (Corporate / Green lending) | B74: Cyprus bank | C74: Nicosia | D74: Assets €28.6b; provident fund is a large Cyprus LP | E74: €28.6b | F74: €5m to €50m | G74: Corporate loans; small capital-call line | H74: Cyprus | I74: Green lending [K] | J74: Unknown | K74: 2 | L74: 1 | M74: 4 | N74: 5 | O74: 2 | P74: 3 | Q74: 3 | R74: =ROUND(SUMPRODUCT(K74:Q74,Scoring_Weights!$E$5:$K$5)/Scoring_Weights!$B$12*20,0) | S74: =IF(R74>=Scoring_Weights!$B$15,"Tier 1",IF(R74>=Scoring_Weights!$B$16,"Tier 2","Tier 3")) | T74: Capital-call line for PE Fund (ex-CPEF); BoC provident fund as LP | U74: Warm via Argus | W74: research briefing
A75: Hark Capital (Aberdeen) | B75: NAV lender to small sponsors | C75: New York / London | D75: Non-dilutive NAV loans US$5m to US$50m against concentrated portfolios [K] | E75: n/a | F75: US$5m to US$50m | G75: NAV loans | H75: Global | I75: n/a | J75: Excluded | K75: 1 | L75: 0 | M75: 4 | N75: 1 | O75: 3 | P75: 1 | Q75: 3 | R75: =ROUND(SUMPRODUCT(K75:Q75,Scoring_Weights!$E$5:$K$5)/Scoring_Weights!$B$12*20,0) | S75: =IF(R75>=Scoring_Weights!$B$15,"Tier 1",IF(R75>=Scoring_Weights!$B$16,"Tier 2","Tier 3")) | T75: Only NAV lender plausibly at Impactus' scale; cannabis must be outside borrowing base | U75: Cold | W75: harkcap.com
A76: 17Capital (Oaktree) | B76: NAV finance | C76: London | D76: Largest buyout managers; loans typically €50m+ [K] | E76: n/a | F76: €50m+ | G76: NAV | H76: Global | I76: n/a | J76: Excluded | K76: 0 | L76: 0 | M76: 1 | N76: 1 | O76: 2 | P76: 1 | Q76: 2 | R76: =ROUND(SUMPRODUCT(K76:Q76,Scoring_Weights!$E$5:$K$5)/Scoring_Weights!$B$12*20,0) | S76: =IF(R76>=Scoring_Weights!$B$15,"Tier 1",IF(R76>=Scoring_Weights!$B$16,"Tier 2","Tier 3")) | T76: Not relevant at this scale | U76: n/a | W76: 17capital.com
A77: HSBC Innovation Banking (ex-SVB UK) | B77: Emerging-manager sub-lines | C77: London | D77: Capital-call lines for emerging managers | E77: n/a | F77: £10m+ | G77: Sub-line | H77: UK / EU | I77: n/a | J77: Excluded (POCA) | K77: 1 | L77: 0 | M77: 3 | N77: 1 | O77: 2 | P77: 1 | Q77: 3 | R77: =ROUND(SUMPRODUCT(K77:Q77,Scoring_Weights!$E$5:$K$5)/Scoring_Weights!$B$12*20,0) | S77: =IF(R77>=Scoring_Weights!$B$15,"Tier 1",IF(R77>=Scoring_Weights!$B$16,"Tier 2","Tier 3")) | T77: PE Fund sub-line if ≥€25m institutional commitments | U77: Cold | W77: hsbcinnovationbanking.com
A78: Pyrum Innovations AG (BASF, Continental investors) | B78: Technology provider / strategic | C78: Dillingen | D78: ≥10% intended stake in Thermo Lysi; BASF €25m conditional loan to Pyrum; rights issue €13m (Dec 2025) | E78: n/a | F78: €2m to €10m | G78: Equity roll-in; supplier credit | H78: Germany / Greece | I78: n/a | J78: n/a | K78: 4 | L78: 0 | M78: 4 | N78: 4 | O78: 4 | P78: 5 | Q78: 3 | R78: =ROUND(SUMPRODUCT(K78:Q78,Scoring_Weights!$E$5:$K$5)/Scoring_Weights!$B$12*20,0) | S78: =IF(R78>=Scoring_Weights!$B$15,"Tier 1",IF(R78>=Scoring_Weights!$B$16,"Tier 2","Tier 3")) | T78: Convert intended stake into cash equity or deferred supply payments; secure Continental supplier-approval letter for EIB | U78: Warm | V78: KM (Pascal Klein) | W78: Pyrum EQS releases; Snapshot
A79: Archirodon Group | B79: EPC contractor / strategic | C79: Athens / Dubai | D79: ECI since Nov 2025; interest as operations partner; c.US$1.5b revenue | E79: n/a | F79: €5m to €20m | G79: Contractor equity; deferred payment | H79: Greece | I79: n/a | J79: n/a | K79: 4 | L79: 0 | M79: 4 | N79: 5 | O79: 3 | P79: 5 | Q79: 3 | R79: =ROUND(SUMPRODUCT(K79:Q79,Scoring_Weights!$E$5:$K$5)/Scoring_Weights!$B$12*20,0) | S79: =IF(R79>=Scoring_Weights!$B$15,"Tier 1",IF(R79>=Scoring_Weights!$B$16,"Tier 2","Tier 3")) | T79: Deferred EPC payment or contractor equity as quasi-mezz | U79: Warm | V79: KM | W79: Snapshot p.8
A80: BASF (ChemCycling) | B80: Offtaker / strategic | C80: Ludwigshafen | D80: €16m equity + €25m conditional loan into Pyrum; heads of terms for Thermo Lysi oil (€515/t floor) | E80: n/a | F80: €5m to €25m | G80: Offtaker prepayment / loan | H80: Germany | I80: Direct pyrolysis precedent | J80: n/a | K80: 5 | L80: 0 | M80: 4 | N80: 3 | O80: 4 | P80: 4 | Q80: 2 | R80: =ROUND(SUMPRODUCT(K80:Q80,Scoring_Weights!$E$5:$K$5)/Scoring_Weights!$B$12*20,0) | S80: =IF(R80>=Scoring_Weights!$B$15,"Tier 1",IF(R80>=Scoring_Weights!$B$16,"Tier 2","Tier 3")) | T80: Wave 1: convert HoT into a take-or-pay with prepayment (bp / Circtec model) | U80: Warm via Pyrum | V80: Pyrum | W80: BASF press 2020; EQS
A81: Continental / Pirelli (via Pyrum rCB framework) | B81: Offtakers | C81: Hanover / Milan | D81: Continental 10-year framework with advance payment; Pirelli long-term supply (Jul 2026) | E81: n/a | F81: €5m to €20m | G81: Advance payment / prepayment | H81: Germany / Italy | I81: Direct precedent (Continental advance to Pyrum) | J81: n/a | K81: 5 | L81: 0 | M81: 4 | N81: 3 | O81: 4 | P81: 4 | Q81: 2 | R81: =ROUND(SUMPRODUCT(K81:Q81,Scoring_Weights!$E$5:$K$5)/Scoring_Weights!$B$12*20,0) | S81: =IF(R81>=Scoring_Weights!$B$15,"Tier 1",IF(R81>=Scoring_Weights!$B$16,"Tier 2","Tier 3")) | T81: Wave 1: rCB prepayment for Line A through Pyrum | U81: Warm via Pyrum | V81: Pyrum | W81: Pyrum EQS 24-07-2026; Snapshot
A82: Ecoelastika S.A. | B82: Statutory ELT collector | C82: Athens | D82: Pre-agreement min 20ktpa; gate fee €62/t on 11ktpa contracted | E82: n/a | F82: n/a | G82: Gate-fee contract | H82: Greece | I82: n/a | J82: n/a | K82: 5 | L82: 0 | M82: 5 | N82: 5 | O82: 2 | P82: 5 | Q82: 3 | R82: =ROUND(SUMPRODUCT(K82:Q82,Scoring_Weights!$E$5:$K$5)/Scoring_Weights!$B$12*20,0) | S82: =IF(R82>=Scoring_Weights!$B$15,"Tier 1",IF(R82>=Scoring_Weights!$B$16,"Tier 2","Tier 3")) | T82: Amendment No.2 to whole throughput is worth more than any lender conversation (every €10/t = c.€1.7m senior capacity) | U82: Warm | V82: KM | W82: PMO MoM 03-09-2026

Sheet Contacts
A1: Named contacts - decision-makers, with the channel most likely to get a reply
A2: Channel rule: warm intro > published email + LinkedIn note same day > LinkedIn InMail with a one-line hook > conference. Emails marked 'pattern - unverified' must be verified (bounce test / mutual contact) before sending. No data was purchased.
A4: Firm | B4: Person | C4: Title | D4: Category | E4: Target sub-fund | F4: LinkedIn URL | G4: Email | H4: Email status | I4: Warm path via | J4: Recommended channel | K4: Hook / message angle (one line) | L4: Confidence | M4: Evidence URL | N4: Owner | O4: Status
A5: EIB - Cleantech Equity & Growth Capital | B5: Alberto Casorati | C5: Cleantech Equity & Growth Capital Division | D5: DFI venture debt | E5: IPL | F5: https://www.linkedin.com/search/results/people/?keywords=Alberto%20Casorati%20European%20Investment%20Bank | G5: a.casorati@eib.org | H5: published | I5: Sirec (Papageorgantas) / direct thread | J5: =IF(I5<>"","Warm intro via "&I5,IF(H5="published","Email + LinkedIn note same day",IF(AND(H5="pattern - unverified",F5<>"not found"),"LinkedIn first; verify email then follow up",IF(F5<>"not found","LinkedIn InMail / connection note","Firm switchboard or conference")))) | K5: Answer the April objection head-on: offer equity-like reward (warrant coverage 15% to 20% or a conversion right) so VD is not 'mezzanine risk without reward' | L5: High | M5: Outlook thread Feb-Apr 2026 | N5: KM | O5: Not started
A6: EIB - Cleantech Equity & Growth Capital | B6: Stephan Mitrakas | C6: Investment Officer (VD team) | D6: DFI venture debt | E6: IPL | F6: https://www.linkedin.com/search/results/people/?keywords=Stephan%20Mitrakas%20European%20Investment%20Bank | G6: s.mitrakas@eib.org | H6: published | I6: Direct thread | J6: =IF(I6<>"","Warm intro via "&I6,IF(H6="published","Email + LinkedIn note same day",IF(AND(H6="pattern - unverified",F6<>"not found"),"LinkedIn first; verify email then follow up",IF(F6<>"not found","LinkedIn InMail / connection note","Firm switchboard or conference")))) | K6: Deliver the three items from the 14-09-2026 committee: Credia CP explainer, Continental supplier-approval letter, Sokolov comparison | L6: High | M6: Outlook 'EIB responses - follow up' 15-09-2026 | N6: KM | O6: Not started
A7: EIB | B7: Francois Gaudet | C7: EIB (cc on VD thread) | D7: DFI venture debt | E7: IPL | F7: https://www.linkedin.com/search/results/people/?keywords=Francois%20Gaudet%20European%20Investment%20Bank | G7: f.gaudet@eib.org | H7: published | I7: Direct thread | J7: =IF(I7<>"","Warm intro via "&I7,IF(H7="published","Email + LinkedIn note same day",IF(AND(H7="pattern - unverified",F7<>"not found"),"LinkedIn first; verify email then follow up",IF(F7<>"not found","LinkedIn InMail / connection note","Firm switchboard or conference")))) | K7: Senior sponsor inside EIB; copy on the reopened file | L7: Medium | M7: Outlook 30-04-2026 cc list | N7: KM | O7: Not started
A8: Hellenic Innovation & Infrastructure Fund (HIIF) | B8: Alexandros Vlachos | C8: Vice President, Investments | D8: Greek impact / infra investor | E8: IPL | F8: https://www.linkedin.com/search/results/people/?keywords=Alexandros%20Vlachos%20HIIF | G8: avlachos@hiif.gr | H8: published | I8: Direct thread | J8: =IF(I8<>"","Warm intro via "&I8,IF(H8="published","Email + LinkedIn note same day",IF(AND(H8="pattern - unverified",F8<>"not found"),"LinkedIn first; verify email then follow up",IF(F8<>"not found","LinkedIn InMail / connection note","Firm switchboard or conference")))) | K8: Staged commitment proposal; market-operator test framing (pari passu with Sirec equity) | L8: High | M8: Outlook 04-08-2026 | N8: KM | O8: Not started
A9: HIIF | B9: Stelios Fragos | C9: HIIF investment team | D9: Greek impact / infra investor | E9: IPL | F9: https://www.linkedin.com/search/results/people/?keywords=Stelios%20Fragos%20HIIF | G9: sfragos@hiif.gr | H9: published | I9: Direct thread | J9: =IF(I9<>"","Warm intro via "&I9,IF(H9="published","Email + LinkedIn note same day",IF(AND(H9="pattern - unverified",F9<>"not found"),"LinkedIn first; verify email then follow up",IF(F9<>"not found","LinkedIn InMail / connection note","Firm switchboard or conference")))) | K9: Same | L9: High | M9: Outlook 04-08-2026 | N9: KM | O9: Not started
A10: HIIF | B10: Andreas Giannakopoulos | C10: HIIF investment team | D10: Greek impact / infra investor | E10: IPL | F10: https://www.linkedin.com/search/results/people/?keywords=Andreas%20Giannakopoulos%20HIIF | G10: agiannakopoulos@hiif.gr | H10: published | I10: Direct thread | J10: =IF(I10<>"","Warm intro via "&I10,IF(H10="published","Email + LinkedIn note same day",IF(AND(H10="pattern - unverified",F10<>"not found"),"LinkedIn first; verify email then follow up",IF(F10<>"not found","LinkedIn InMail / connection note","Firm switchboard or conference")))) | K10: Same | L10: High | M10: Outlook 04-08-2026 | N10: KM | O10: Not started
A11: Credia Bank - Structured Finance | B11: Evangelos Mitrou | C11: Senior Relationship Manager, Structured Finance | D11: Greek bank - senior | E11: IPL | F11: https://www.linkedin.com/search/results/people/?keywords=Evangelos%20Mitrou%20Credia%20Bank | G11: mitrou.evangelos@crediabank.com | H11: published | I11: Venero (Chatzilias) | J11: =IF(I11<>"","Warm intro via "&I11,IF(H11="published","Email + LinkedIn note same day",IF(AND(H11="pattern - unverified",F11<>"not found"),"LinkedIn first; verify email then follow up",IF(F11<>"not found","LinkedIn InMail / connection note","Firm switchboard or conference")))) | K11: Firm EPC price 31-10; ask for the credit-committee calendar and the CP list in writing | L11: High | M11: Credia LOI thread Aug 2026 | N11: KM / Venero | O11: Not started
A12: Credia Bank - Structured Finance | B12: Christos Masouras | C12: Structured Finance | D12: Greek bank - senior | E12: IPL | F12: https://www.linkedin.com/search/results/people/?keywords=Christos%20Masouras%20Credia%20Bank | G12: masouras.christos@crediabank.com | H12: published | I12: Venero | J12: =IF(I12<>"","Warm intro via "&I12,IF(H12="published","Email + LinkedIn note same day",IF(AND(H12="pattern - unverified",F12<>"not found"),"LinkedIn first; verify email then follow up",IF(F12<>"not found","LinkedIn InMail / connection note","Firm switchboard or conference")))) | K12: Same | L12: High | M12: Credia LOI thread | N12: Venero | O12: Not started
A13: Credia Bank - Structured Finance | B13: Christos Iliopoulos | C13: Structured Finance | D13: Greek bank - senior | E13: IPL | F13: https://www.linkedin.com/search/results/people/?keywords=Christos%20Iliopoulos%20Credia%20Bank | G13: iliopoulos.christos@crediabank.com | H13: published | I13: Venero | J13: =IF(I13<>"","Warm intro via "&I13,IF(H13="published","Email + LinkedIn note same day",IF(AND(H13="pattern - unverified",F13<>"not found"),"LinkedIn first; verify email then follow up",IF(F13<>"not found","LinkedIn InMail / connection note","Firm switchboard or conference")))) | K13: Same | L13: High | M13: Credia LOI thread | N13: Venero | O13: Not started
A14: Sirec Energy | B14: George Papageorgantas | C14: Partner (advising on EIB; co-investor) | D14: Greek energy fund | E14: IPL | F14: https://www.linkedin.com/search/results/people/?keywords=George%20Papageorgantas%20Sirec%20Energy | G14: g.papageorgantas@sirecenergy.com | H14: published | I14: Direct | J14: =IF(I14<>"","Warm intro via "&I14,IF(H14="published","Email + LinkedIn note same day",IF(AND(H14="pattern - unverified",F14<>"not found"),"LinkedIn first; verify email then follow up",IF(F14<>"not found","LinkedIn InMail / connection note","Firm switchboard or conference")))) | K14: Ask for Piraeus / Eurobank PF introductions and for a Greek family-office list from Sirec's own LP base | L14: High | M14: Outlook 15-09-2026 | N14: KM | O14: Not started
A15: Sirec Energy | B15: Dionissis Alissandratos | C15: Sirec Energy | D15: Greek energy fund | E15: IPL | F15: https://www.linkedin.com/search/results/people/?keywords=Dionissis%20Alissandratos%20Sirec%20Energy | G15: d.alissandratos@sirecenergy.com | H15: published | I15: Direct | J15: =IF(I15<>"","Warm intro via "&I15,IF(H15="published","Email + LinkedIn note same day",IF(AND(H15="pattern - unverified",F15<>"not found"),"LinkedIn first; verify email then follow up",IF(F15<>"not found","LinkedIn InMail / connection note","Firm switchboard or conference")))) | K15: Same | L15: High | M15: Outlook 15-09-2026 | N15: KM | O15: Not started
A16: Venero Capital Advisors | B16: Argyris Chatzilias | C16: Debt advisor (engaged) | D16: Advisor | E16: IPL | F16: https://www.linkedin.com/search/results/people/?keywords=Argyrios%20Chatzilias%20Venero%20Capital | G16: argy@venerocapitaladvisors.com | H16: published | I16: Direct | J16: =IF(I16<>"","Warm intro via "&I16,IF(H16="published","Email + LinkedIn note same day",IF(AND(H16="pattern - unverified",F16<>"not found"),"LinkedIn first; verify email then follow up",IF(F16<>"not found","LinkedIn InMail / connection note","Firm switchboard or conference")))) | K16: Mandate: open Piraeus and one impact lender (Rivage / Eiffel / Polestar) in parallel to Credia within 30 days | L16: High | M16: Credia thread | N16: KM | O16: Not started
... A38: Sergo Vashakmadze | B38: Sergo Vashakmadze | C38: Intermediary (5% / 2.5% success fee) | D38: Introducer | E38: IPL | F38: https://www.linkedin.com/search/results/people/?keywords=Sergo%20Vashakmadze%20 | G38: not found | H38: not found | I38: Direct (call Jun 2025) | J38: =IF(I38<>"","Warm intro via "&I38,IF(H38="published","Email + LinkedIn note same day",IF(AND(H38="pattern - unverified",F38<>"not found"),"LinkedIn first; verify email then follow up",IF(F38<>"not found","LinkedIn InMail / connection note","Firm switchboard or conference")))) | K38: Named-investor basis only | L38: Medium | M38: Fathom 23-06-2025 | N38: KM | O38: Not started
A39: Rivage Investment | B39: Head of European Climate Debt Solutions (name to verify) | C39: Climate-tech deployment debt (EIF InvestEU) | D39: Infra / climate debt | E39: IPL | F39: https://www.linkedin.com/search/results/people/?keywords=Rivage%20Investment%20climate%20debt | G39: not found | H39: not found | J39: =IF(I39<>"","Warm intro via "&I39,IF(H39="published","Email + LinkedIn note same day",IF(AND(H39="pattern - unverified",F39<>"not found"),"LinkedIn first; verify email then follow up",IF(F39<>"not found","LinkedIn InMail / connection note","Firm switchboard or conference")))) | K39: Only European climate-debt mandate built for facility deployment; EIF InvestEU backing aligns with the Innovation Fund grant | L39: Low - name not verified in session | M39: rivageinvestment.com strategy page | N39: KM | O39: Not started
A40: Eiffel Investment Group | B40: Pierre-Antoine Machelon (Head of Infrastructure) [verify] | C40: Energy Transition Infrastructure | D40: Infra / energy-transition debt | E40: IPL | F40: https://www.linkedin.com/search/results/people/?keywords=Pierre-Antoine%20Machelon%20Eiffel%20Investment%20Group | G40: not found | H40: not found | J40: =IF(I40<>"","Warm intro via "&I40,IF(H40="published","Email + LinkedIn note same day",IF(AND(H40="pattern - unverified",F40<>"not found"),"LinkedIn first; verify email then follow up",IF(F40<>"not found","LinkedIn InMail / connection note","Firm switchboard or conference")))) | K40: Bridge against the €29.4m CINEA receivable (WP2 €24.4m at entry into operation) - a product Eiffel already runs for renewables | L40: Low - analyst knowledge [K] | M40: IPE Real Assets (EET III) | N40: KM | O40: Not started
A41: Polestar Capital | B41: Investment team (name to verify) | C41: Impact senior debt (Xycle lender) | D41: Impact debt | E41: IPL | F41: https://www.linkedin.com/search/results/people/?keywords=Polestar%20Capital%20Xycle | G41: not found | H41: not found | J41: =IF(I41<>"","Warm intro via "&I41,IF(H41="published","Email + LinkedIn note same day",IF(AND(H41="pattern - unverified",F41<>"not found"),"LinkedIn first; verify email then follow up",IF(F41<>"not found","LinkedIn InMail / connection note","Firm switchboard or conference")))) | K41: Only European fund with a chemical-recycling senior loan on its book - ask for their Xycle covenant package as a template | L41: Low | M41: Recycling Today (Xycle financing) | N41: KM | O41: Not started
A42: Infranity | B42: Philippe Benaroya (CEO) [verify] | C42: Infrastructure debt - Enhanced Return Debt Fund | D42: Infra debt | E42: IPL | F42: https://www.linkedin.com/search/results/people/?keywords=Philippe%20Benaroya%20Infranity | G42: not found | H42: not found | J42: =IF(I42<>"","Warm intro via "&I42,IF(H42="published","Email + LinkedIn note same day",IF(AND(H42="pattern - unverified",F42<>"not found"),"LinkedIn first; verify email then follow up",IF(F42<>"not found","LinkedIn InMail / connection note","Firm switchboard or conference")))) | K42: Sub-IG senior sleeve with 50% climate target; approach at FID with EPC wrap and TDD | L42: Low - analyst knowledge [K] | M42: ACI 18-12-2025 | N42: Venero | O42: Not started
A43: Tiger Infrastructure Partners | B43: Emil Henry (CEO) [verify] | C43: Growth infrastructure equity (Bolder Industries investor) | D43: Growth infra equity | E43: IVP / IPL | F43: https://www.linkedin.com/search/results/people/?keywords=Emil%20Henry%20Tiger%20Infrastructure%20Partners | G43: not found | H43: not found | J43: =IF(I43<>"","Warm intro via "&I43,IF(H43="published","Email + LinkedIn note same day",IF(AND(H43="pattern - unverified",F43<>"not found"),"LinkedIn first; verify email then follow up",IF(F43<>"not found","LinkedIn InMail / connection note","Firm switchboard or conference")))) | K43: They underwrote Bolder Antwerp (86ktpa) - IVP is the same thesis with an EU grant attached | L43: Low - analyst knowledge [K] | M43: PR Newswire Feb 2025 | N43: KM | O43: Not started
A44: Kartesia | B44: Jaime Prieto (Managing Partner) [verify]; Southern Europe origination head | C44: Lower-mid-market credit | D44: Private credit | E44: IPL / CPEF | F44: https://www.linkedin.com/search/results/people/?keywords=Jaime%20Prieto%20Kartesia | G44: not found | H44: not found | J44: =IF(I44<>"","Warm intro via "&I44,IF(H44="published","Email + LinkedIn note same day",IF(AND(H44="pattern - unverified",F44<>"not found"),"LinkedIn first; verify email then follow up",IF(F44<>"not found","LinkedIn InMail / connection note","Firm switchboard or conference")))) | K44: KCO VI does sponsorless hybrids in Southern Europe at €10m to €60m; on the Cascade map | L44: Low - analyst knowledge [K] | M44: kartesia.com | N44: Venero | O44: Not started
A45: Incus Capital | B45: Alejandro Moya (Co-founder) [verify] | C45: Iberian real-asset special situations | D45: Special situations | E45: IPL | F45: https://www.linkedin.com/search/results/people/?keywords=Alejandro%20Moya%20Incus%20Capital | G45: not found | H45: not found | J45: =IF(I45<>"","Warm intro via "&I45,IF(H45="published","Email + LinkedIn note same day",IF(AND(H45="pattern - unverified",F45<>"not found"),"LinkedIn first; verify email then follow up",IF(F45<>"not found","LinkedIn InMail / connection note","Firm switchboard or conference")))) | K45: Real-asset backed €10m to €50m; ask whether Greece is in mandate | L45: Low - analyst knowledge [K] | M45: Cascade map | N45: Venero | O45: Not started
A46: Cross Ocean Partners | B46: European special situations team (name to verify) | C46: Special situations / ABF | D46: Special situations | E46: IPL | F46: https://www.linkedin.com/search/results/people/?keywords=Cross%20Ocean%20Partners%20special%20situations | G46: not found | H46: not found | J46: =IF(I46<>"","Warm intro via "&I46,IF(H46="published","Email + LinkedIn note same day",IF(AND(H46="pattern - unverified",F46<>"not found"),"LinkedIn first; verify email then follow up",IF(F46<>"not found","LinkedIn InMail / connection note","Firm switchboard or conference")))) | K46: Asset-backed special sits with Southern Europe history; on the Cascade map | L46: Low | M46: Cascade map | N46: Venero | O46: Not started
A47: Blantyre Capital | B47: Mubashir Mukadam (Founder) [verify] | C47: Special situations | D47: Special situations | E47: IPL | F47: https://www.linkedin.com/search/results/people/?keywords=Mubashir%20Mukadam%20Blantyre%20Capital | G47: not found | H47: not found | J47: =IF(I47<>"","Warm intro via "&I47,IF(H47="published","Email + LinkedIn note same day",IF(AND(H47="pattern - unverified",F47<>"not found"),"LinkedIn first; verify email then follow up",IF(F47<>"not found","LinkedIn InMail / connection note","Firm switchboard or conference")))) | K47: €35m FOAK hybrid at 14% to 18% all-in with warrants | L47: Low - analyst knowledge [K] | M47: PitchBook fund profile | N47: Venero | O47: Not started
A48: Hayfin Capital Management | B48: Head of Special Opportunities (name to verify) | C48: Special Opportunities | D48: Special situations | E48: IPL / IVP | F48: https://www.linkedin.com/search/results/people/?keywords=Hayfin%20Special%20Opportunities | G48: not found | H48: not found | J48: =IF(I48<>"","Warm intro via "&I48,IF(H48="published","Email + LinkedIn note same day",IF(AND(H48="pattern - unverified",F48<>"not found"),"LinkedIn first; verify email then follow up",IF(F48<>"not found","LinkedIn InMail / connection note","Firm switchboard or conference")))) | K48: Ticket floor c.€25m; only for the full VD tranche or IVP | L48: Low | M48: hayfin.com | N48: Venero | O48: Not started
A49: Tikehau Capital | B49: Cecile Mayer-Levi (Head of Private Debt) [verify]; Special Opportunities team | C49: Private debt / special sits / decarbonisation | D49: Private credit | E49: IVP / IPL | F49: https://www.linkedin.com/search/results/people/?keywords=Cecile%20Mayer-Levi%20Tikehau%20Capital | G49: not found | H49: not found | J49: =IF(I49<>"","Warm intro via "&I49,IF(H49="published","Email + LinkedIn note same day",IF(AND(H49="pattern - unverified",F49<>"not found"),"LinkedIn first; verify email then follow up",IF(F49<>"not found","LinkedIn InMail / connection note","Firm switchboard or conference")))) | K49: Decarbonisation strategy plus special sits; Southern Europe offices | L49: Low - analyst knowledge [K] | M49: ACI 24-07-2026 | N49: KM | O49: Not started
A50: Davidson Kempner (Greece) | B50: Head of Greek investments (name to verify) | C50: Special situations; owner of Cepal | D50: Special situations | E50: IPL / IVP | F50: https://www.linkedin.com/search/results/people/?keywords=Davidson%20Kempner%20Greece | G50: not found | H50: not found | J50: =IF(I50<>"","Warm intro via "&I50,IF(H50="published","Email + LinkedIn note same day",IF(AND(H50="pattern - unverified",F50<>"not found"),"LinkedIn first; verify email then follow up",IF(F50<>"not found","LinkedIn InMail / connection note","Firm switchboard or conference")))) | K50: Largest foreign credit investor in Greece; hard-asset hybrid at IVP scale | L50: Low | M50: hellaz.eu | N50: Axia | O50: Not started
A51: Kreos Capital | B51: Aris Constantinides (General Partner) [verify] | C51: Venture / growth debt | D51: Growth debt | E51: CPEF | F51: https://www.linkedin.com/search/results/people/?keywords=Aris%20Constantinides%20Kreos%20Capital | G51: not found | H51: not found | I51: Greek diaspora | J51: =IF(I51<>"","Warm intro via "&I51,IF(H51="published","Email + LinkedIn note same day",IF(AND(H51="pattern - unverified",F51<>"not found"),"LinkedIn first; verify email then follow up",IF(F51<>"not found","LinkedIn InMail / connection note","Firm switchboard or conference")))) | K51: Greek GP at Europe's largest growth-debt house; Curity growth line once 12 months of German sales are audited | L51: Medium - analyst knowledge [K] | M51: tulacap.com | N51: KM | O51: Not started
A52: Claret Capital Partners | B52: Johan Kampe (Managing Partner) [verify] | C52: Growth debt | D52: Growth debt | E52: CPEF | F52: https://www.linkedin.com/search/results/people/?keywords=Johan%20Kampe%20Claret%20Capital%20Partners | G52: not found | H52: not found | J52: =IF(I52<>"","Warm intro via "&I52,IF(H52="published","Email + LinkedIn note same day",IF(AND(H52="pattern - unverified",F52<>"not found"),"LinkedIn first; verify email then follow up",IF(F52<>"not found","LinkedIn InMail / connection note","Firm switchboard or conference")))) | K52: Fund IV €575m; €3m to €30m; no cannabis exclusion located | L52: Low - analyst knowledge [K] | M52: TNW | N52: KM | O52: Not started
A53: Atempo Growth | B53: Madrid office (name to verify) | C53: Growth debt, Southern Europe | D53: Growth debt | E53: CPEF | F53: https://www.linkedin.com/search/results/people/?keywords=Atempo%20Growth%20Madrid | G53: not found | H53: not found | J53: =IF(I53<>"","Warm intro via "&I53,IF(H53="published","Email + LinkedIn note same day",IF(AND(H53="pattern - unverified",F53<>"not found"),"LinkedIn first; verify email then follow up",IF(F53<>"not found","LinkedIn InMail / connection note","Firm switchboard or conference")))) | K53: Southern Europe growth debt; Fund II >€455m | L53: Low | M53: capitalranking.com | N53: KM | O53: Not started
A54: Chicago Atlantic | B54: John Mazarakis (Co-founder) [verify] | C54: Specialist cannabis credit | D54: Cannabis credit | E54: CPEF | F54: https://www.linkedin.com/search/results/people/?keywords=John%20Mazarakis%20Chicago%20Atlantic | G54: not found | H54: not found | I54: Greek diaspora | J54: =IF(I54<>"","Warm intro via "&I54,IF(H54="published","Email + LinkedIn note same day",IF(AND(H54="pattern - unverified",F54<>"not found"),"LinkedIn first; verify email then follow up",IF(F54<>"not found","LinkedIn InMail / connection note","Firm switchboard or conference")))) | K54: Greek-American co-founder of the largest cannabis lender; no European loan yet - be the first, at 13% to 16% with EU-GMP plant and Galenica offtake as security | L54: Medium - analyst knowledge [K] | M54: REFI filings via research briefing | N54: KM | O54: Not started
A55: Advanced Flower Capital (AFC Gamma) | B55: Daniel Neville (CEO) [verify] | C55: Specialist cannabis credit | D55: Cannabis credit | E55: CPEF | F55: https://www.linkedin.com/search/results/people/?keywords=Daniel%20Neville%20AFC%20Gamma | G55: not found | H55: not found | J55: =IF(I55<>"","Warm intro via "&I55,IF(H55="published","Email + LinkedIn note same day",IF(AND(H55="pattern - unverified",F55<>"not found"),"LinkedIn first; verify email then follow up",IF(F55<>"not found","LinkedIn InMail / connection note","Firm switchboard or conference")))) | K55: Wave 2; 35.7% non-accrual limits appetite | L55: Low - analyst knowledge [K] | M55: AFCG filings via research briefing | N55: KM | O55: Not started
A56: Artemis Growth Partners | B56: Investment team (name to verify) | C56: Cannabis growth equity / hybrid; Fund VII c.75% Europe | D56: Cannabis equity | E56: CPEF | F56: https://www.linkedin.com/search/results/people/?keywords=Artemis%20Growth%20Partners%20cannabis | G56: not found | H56: not found | J56: =IF(I56<>"","Warm intro via "&I56,IF(H56="published","Email + LinkedIn note same day",IF(AND(H56="pattern - unverified",F56<>"not found"),"LinkedIn first; verify email then follow up",IF(F56<>"not found","LinkedIn InMail / connection note","Firm switchboard or conference")))) | K56: Only fund with a stated European cannabis allocation; hybrid instrument into Curity alongside the note | L56: Low | M56: research briefing (cannabis) | N56: KM | O56: Not started
A57: Casa Verde Capital | B57: Karan Wadhera (Managing Partner) [verify] | C57: Cannabis VC (Cansativa, Sanity) | D57: Cannabis equity | E57: CPEF | F57: https://www.linkedin.com/search/results/people/?keywords=Karan%20Wadhera%20Casa%20Verde%20Capital | G57: not found | H57: not found | J57: =IF(I57<>"","Warm intro via "&I57,IF(H57="published","Email + LinkedIn note same day",IF(AND(H57="pattern - unverified",F57<>"not found"),"LinkedIn first; verify email then follow up",IF(F57<>"not found","LinkedIn InMail / connection note","Firm switchboard or conference")))) | K57: Co-investor; German distribution relationships via Cansativa | L57: Low - analyst knowledge [K] | M57: research briefing (cannabis) | N57: KM | O57: Not started
A58: Curaleaf International | B58: Corporate development (name to verify) | C58: Strategic acquirer / offtaker | D58: Strategic | E58: CPEF | F58: https://www.linkedin.com/search/results/people/?keywords=Curaleaf%20International%20corporate%20development | G58: not found | H58: not found | J58: =IF(I58<>"","Warm intro via "&I58,IF(H58="published","Email + LinkedIn note same day",IF(AND(H58="pattern - unverified",F58<>"not found"),"LinkedIn first; verify email then follow up",IF(F58<>"not found","LinkedIn InMail / connection note","Firm switchboard or conference")))) | K58: US$500m notes fund European M&A; price discovery for the Curity equity fallback and offtake for EU-GMP flower | L58: Low | M58: research briefing (cannabis) | N58: AM | O58: Not started
A59: Cantourage Group SE | B59: Philip Schetter (CEO) [verify] | C59: German importer / distributor | D59: Offtaker | E59: CPEF | F59: https://www.linkedin.com/search/results/people/?keywords=Philip%20Schetter%20Cantourage | G59: not found | H59: not found | J59: =IF(I59<>"","Warm intro via "&I59,IF(H59="published","Email + LinkedIn note same day",IF(AND(H59="pattern - unverified",F59<>"not found"),"LinkedIn first; verify email then follow up",IF(F59<>"not found","LinkedIn InMail / connection note","Firm switchboard or conference")))) | K59: Offtake contract = collateral a lender will value; FY26 revenue guidance €85-95m | L59: Medium - analyst knowledge [K] | M59: research briefing (cannabis) | N59: AM | O59: Not started
A60: Bloomwell Group | B60: Niklas Kouparanis (CEO) [verify] | C60: German cannabis platform (Artemis-backed) | D60: Strategic / offtaker | E60: CPEF | F60: https://www.linkedin.com/search/results/people/?keywords=Niklas%20Kouparanis%20Bloomwell | G60: not found | H60: not found | I60: Greek-German founder | J60: =IF(I60<>"","Warm intro via "&I60,IF(H60="published","Email + LinkedIn note same day",IF(AND(H60="pattern - unverified",F60<>"not found"),"LinkedIn first; verify email then follow up",IF(F60<>"not found","LinkedIn InMail / connection note","Firm switchboard or conference")))) | K60: Greek-German founder; distribution partner and route to Artemis | L60: Medium - analyst knowledge [K] | M60: research briefing (cannabis) | N60: AM | O60: Not started
A61: Organigram Global / Sanity Group | B61: Corporate development (name to verify) | C61: Strategic acquirer | D61: Strategic | E61: CPEF | F61: https://www.linkedin.com/search/results/people/?keywords=Organigram%20Sanity%20Group | G61: not found | H61: not found | J61: =IF(I61<>"","Warm intro via "&I61,IF(H61="published","Email + LinkedIn note same day",IF(AND(H61="pattern - unverified",F61<>"not found"),"LinkedIn first; verify email then follow up",IF(F61<>"not found","LinkedIn InMail / connection note","Firm switchboard or conference")))) | K61: Convertible-then-acquire precedent (10% coupon, 36 months) for Curity | L61: Low | M61: research briefing (cannabis) | N61: AM | O61: Not started
A62: Viola Credit | B62: European origination (name to verify) | C62: Venture lending / ABF; Israel-Europe | D62: Venture debt | E62: CPEF | F62: https://www.linkedin.com/search/results/people/?keywords=Viola%20Credit%20Europe | G62: not found | H62: not found | J62: =IF(I62<>"","Warm intro via "&I62,IF(H62="published","Email + LinkedIn note same day",IF(AND(H62="pattern - unverified",F62<>"not found"),"LinkedIn first; verify email then follow up",IF(F62<>"not found","LinkedIn InMail / connection note","Firm switchboard or conference")))) | K62: Israeli lender familiar with regulated cannabis (InterCure / Bennu ecosystem); on the Cascade map | L62: Low | M62: Cascade map | N62: KM | O62: Not started
A63: Threadmark | B63: Bruce Chapman (Managing Partner) [verify] | C63: Placement agent - first-time managers | D63: Placement | E63: IVP | F63: https://www.linkedin.com/search/results/people/?keywords=Bruce%20Chapman%20Threadmark | G63: not found | H63: not found | J63: =IF(I63<>"","Warm intro via "&I63,IF(H63="published","Email + LinkedIn note same day",IF(AND(H63="pattern - unverified",F63<>"not found"),"LinkedIn first; verify email then follow up",IF(F63<>"not found","LinkedIn InMail / connection note","Firm switchboard or conference")))) | K63: Specialises in first-time / niche managers; success-fee IVP mandate | L63: Low - analyst knowledge [K] | M63: threadmark.com | N63: KM | O63: Not started
A64: Elm Capital | B64: Etienne Deshormes (Managing Partner) [verify] | C64: Placement agent - boutique | D64: Placement | E64: IVP | F64: https://www.linkedin.com/search/results/people/?keywords=Etienne%20Deshormes%20Elm%20Capital | G64: not found | H64: not found | J64: =IF(I64<>"","Warm intro via "&I64,IF(H64="published","Email + LinkedIn note same day",IF(AND(H64="pattern - unverified",F64<>"not found"),"LinkedIn first; verify email then follow up",IF(F64<>"not found","LinkedIn InMail / connection note","Firm switchboard or conference")))) | K64: €50m to €200m raises; credit and impact | L64: Low - analyst knowledge [K] | M64: Companies House / LinkedIn | N64: KM | O64: Not started
A65: Cebile Capital | B65: Sunaina Sinha Haldea (Founder) [verify] | C65: Placement agent - impact / emerging | D65: Placement | E65: IVP | F65: https://www.linkedin.com/search/results/people/?keywords=Sunaina%20Sinha%20Cebile%20Capital | G65: not found | H65: not found | J65: =IF(I65<>"","Warm intro via "&I65,IF(H65="published","Email + LinkedIn note same day",IF(AND(H65="pattern - unverified",F65<>"not found"),"LinkedIn first; verify email then follow up",IF(F65<>"not found","LinkedIn InMail / connection note","Firm switchboard or conference")))) | K65: Emerging-manager and impact specialist | L65: Low - analyst knowledge [K] | M65: [K] | N65: KM | O65: Not started
A66: Alantra (Athens office) | B66: Athens office head (name to verify) | C66: Mid-market advisory and private debt | D66: Advisor / lender | E66: IVP / IPL | F66: https://www.linkedin.com/search/results/people/?keywords=Alantra%20Athens | G66: not found | H66: not found | J66: =IF(I66<>"","Warm intro via "&I66,IF(H66="published","Email + LinkedIn note same day",IF(AND(H66="pattern - unverified",F66<>"not found"),"LinkedIn first; verify email then follow up",IF(F66<>"not found","LinkedIn InMail / connection note","Firm switchboard or conference")))) | K66: Greek office of a Cascade-map private-debt manager; advisory plus lending | L66: Low | M66: Cascade map | N66: AM | O66: Not started
A67: BASF (ChemCycling / Pyrum stake) | B67: ChemCycling business lead (name to verify) | C67: Offtaker / strategic investor in Pyrum | D67: Strategic | E67: IPL | F67: https://www.linkedin.com/search/results/people/?keywords=BASF%20ChemCycling%20pyrolysis%20oil | G67: not found | H67: not found | I67: Pyrum | J67: =IF(I67<>"","Warm intro via "&I67,IF(H67="published","Email + LinkedIn note same day",IF(AND(H67="pattern - unverified",F67<>"not found"),"LinkedIn first; verify email then follow up",IF(F67<>"not found","LinkedIn InMail / connection note","Firm switchboard or conference")))) | K67: Convert HoT into take-or-pay with prepayment (bp / Circtec precedent: €12.5m debt + 8-year offtake) | L67: Low | M67: BASF press 2020; Circtec release May 2024 | N67: KM | O67: Not started
A68: Continental (via Pyrum framework) | B68: Continental sustainability / rCB procurement (name to verify) | C68: rCB offtaker with advance-payment precedent | D68: Strategic | E68: IPL | F68: https://www.linkedin.com/search/results/people/?keywords=Continental%20recovered%20carbon%20black%20Pyrum | G68: not found | H68: not found | I68: Pyrum | J68: =IF(I68<>"","Warm intro via "&I68,IF(H68="published","Email + LinkedIn note same day",IF(AND(H68="pattern - unverified",F68<>"not found"),"LinkedIn first; verify email then follow up",IF(F68<>"not found","LinkedIn InMail / connection note","Firm switchboard or conference")))) | K68: Supplier-approval letter for EIB; advance payment for Line A rCB | L68: Low | M68: Pyrum / Continental release 30-07-2024 | N68: KM | O68: Not started
A69: Ecoelastika S.A. | B69: Board / general manager (existing relationship) | C69: Statutory ELT collector | D69: Feedstock | E69: IPL | F69: https://www.linkedin.com/search/results/people/?keywords=Ecoelastika%20 | G69: not found | H69: not found | I69: Direct (BoD meeting May 2025) | J69: =IF(I69<>"","Warm intro via "&I69,IF(H69="published","Email + LinkedIn note same day",IF(AND(H69="pattern - unverified",F69<>"not found"),"LinkedIn first; verify email then follow up",IF(F69<>"not found","LinkedIn InMail / connection note","Firm switchboard or conference")))) | K69: Amendment No.2: gate fee across whole throughput is worth c.€1.7m of senior capacity per €10/t | L69: High | M69: Investor tracker; PMO MoM | N69: KM | O69: Not started
A70: Growthfund / HCAP | B70: Investment team (name to verify) | C70: Greek sovereign holding | D70: Sovereign | E70: IVP | F70: https://www.linkedin.com/search/results/people/?keywords=Growthfund%20HCAP | G70: not found | H70: not found | J70: =IF(I70<>"","Warm intro via "&I70,IF(H70="published","Email + LinkedIn note same day",IF(AND(H70="pattern - unverified",F70<>"not found"),"LinkedIn first; verify email then follow up",IF(F70<>"not found","LinkedIn InMail / connection note","Firm switchboard or conference")))) | K70: IVP only; BlackRock FMA advising | L70: Low | M70: growthfund.gr | N70: AM | O70: Not started
A71: Piraeus Bank - Structured Finance | B71: Head of Project Finance (name to verify) | C71: Greek bank PF desk | D71: Greek bank | E71: IPL | F71: https://www.linkedin.com/search/results/people/?keywords=Piraeus%20Bank%20project%20finance | G71: not found | H71: not found | I71: PwC Greece / Axia | J71: =IF(I71<>"","Warm intro via "&I71,IF(H71="published","Email + LinkedIn note same day",IF(AND(H71="pattern - unverified",F71<>"not found"),"LinkedIn first; verify email then follow up",IF(F71<>"not found","LinkedIn InMail / connection note","Firm switchboard or conference")))) | K71: Competing senior bid; EIB €950m on-lending line | L71: Low | M71: EIB press 2026-041 | N71: Venero | O71: Not started
A72: Eurobank - Project Finance | B72: Head of Project Finance (name to verify) | C72: Greek bank PF desk | D72: Greek bank | E72: IPL | F72: https://www.linkedin.com/search/results/people/?keywords=Eurobank%20project%20finance | G72: not found | H72: not found | I72: Argus (Eurobank Cyprus depositary) | J72: =IF(I72<>"","Warm intro via "&I72,IF(H72="published","Email + LinkedIn note same day",IF(AND(H72="pattern - unverified",F72<>"not found"),"LinkedIn first; verify email then follow up",IF(F72<>"not found","LinkedIn InMail / connection note","Firm switchboard or conference")))) | K72: Competing senior bid; Eurobank Cyprus capital-call line for PE Fund | L72: Low | M72: EIF press 2025-343 | N72: Venero | O72: Not started

Sheet Existing_Pipeline
A1: Existing and warm relationships already in Impactus records (Outlook, SharePoint tracker, Fathom calls)
A2: Use these paths before any cold outreach - a warm introduction converts 5x to 10x better than a cold LinkedIn message (see Outreach_Plan)
A4: Counterparty | B4: Type | C4: Owner | D4: Status / last step | E4: Relevance | F4: Suggested next action | G4: Source
A5: Credia Bank (Structured Finance) - Evangelos Mitrou, Christos Masouras, Christos Iliopoulos | B5: Greek bank - senior project debt | C5: KM / Venero | D5: Non-binding LOI for CINEA delivered Aug 2026; indicative 6.5%, 4+10y, 1.3x DSCR; credit process on firm EPC price | E5: IPL senior | F5: Bring firm EPC price 31-10; run TÜV Nord TDD in parallel; agree CP list (Papageorgantas list of 15-09) | G5: Outlook thread 'Credia <> Impactus' Jul-Aug 2026
A6: EIB Venture Debt team (Stephan) | B6: DFI - venture debt | C6: KM / Sirec Energy | D6: Committee discussed project 14-09-2026; clarifications on Credia CPs, Continental audit letter, Sokolov comparison | E6: IPL VD €35m alternative / complement | F6: Answer three questions within the week; obtain Continental supplier-approval letter via Pyrum | G6: Outlook 'EIB responses - follow up' 15-09-2026
A7: HIIF (institutional investor assessing €35m VD) | B7: Impact / infrastructure investor | C7: KM | D7: €35m at 10% blended offered; internal assessment; Impactus priority: firm commitment by Dec 2026 | E7: IPL VD | F7: Re-cut as staged commitment (development tranche now, construction tranche at FID) before the PMO reset reaches them | G7: PMO MoM 03-09-2026; Snapshot p.9
A8: Sirec Energy (George Papageorgantas, Dionissis Alissandratos) | B8: Greek energy fund - co-investor | C8: KM | D8: Term sheet executed Mar 2026 at c.€34m post-money for Thermo Lysi; advising on EIB | E8: IPL equity / advisory | F8: Use as reference co-investor in outreach; ask for EIB and Greek bank introductions | G8: Outlook 17-09-2026 to Muhanna; EIB thread
A9: EMMA Capital | B9: Investor - term sheet | C9: AM | D9: TS submitted 15-10-2025; €4.54m loan capital referenced | E9: IPL / Thermo Lysi | F9: Confirm status; if lapsed, re-approach with Sep 2026 pack | G9: Investor tracker 22-10-2025
A10: Argus Management (AIFM) channel: ETYK, PEO, Cyta, Lawyers' Provident Funds; JP Morgan, Blackstone, Schroders | B10: Cyprus provident funds / global AMs via AIFM | C10: AM / Argus | D10: ETYK and PEO €1m each estimated; IVP deck presented to three banks - initial interest | E10: IPL €5m; IVP | F10: Convert ETYK/PEO IC presentations; structure a fund-level note the provident funds can hold | G10: Investor tracker 03-08-2026
A11: Muhanna & Co (Marinos Theodosiou) - Doctors' Provident Fund (Tameio Iatron) | B11: Cyprus pension administrator / LP | C11: KM | D11: Existing shareholder (415 shares, 4.73%); EY audit queries on fair value answered 17-09-2026 | E11: IPL follow-on; gateway to other funds | F11: Close the IFRS 13 point with EY; then ask Muhanna for introductions to the other funds it administers | G11: Outlook 'Re: Impactus Pyrolisis' 17-09-2026
A12: KPMG Cyprus (Christos Vasiliou) | B12: Adviser - placement mandate €150-200m | C12: AM | D12: Mandate to raise c.€150-200m (Oct 2025); KPMG Sweden follow-up | E12: IVP | F12: Demand a named target list and a 90-day plan from KPMG; tie fee to first close | G12: Investor tracker 22-10-2025
A13: Axia Ventures (Antonis Achilleoudis) | B13: Greek/Cypriot investment bank | C13: AM | D13: Meetings Athens 2025; Infiniteria update | E13: IVP / IPL | F13: Ask Axia to run a targeted process with Greek family offices and Piraeus/Eurobank PF desks | G13: Investor tracker
A14: Venero Capital Advisors (Argyris Chatzilias, Giannos Politis) | B14: Capital advisor - engaged | C14: KM | D14: Running Credia LOI; 'KM & AC to meet Pascal' | E14: IPL debt | F14: Mandate Venero to open two alternative senior/ VD lenders as competitive tension to Credia | G14: Credia thread
A15: Oak Chase Global | B15: Capital introduction - ~180 investors | C15: KM | D15: Call 20-03-2026; NDA and VDR access; €100m equity for €340m pipeline | E15: IVP | F15: Check output since March; if none, drop | G15: Fathom 20-03-2026
... A30: Pyrum Innovations AG | B30: Technology provider (BASF, Continental investors) | C30: KM | D30: Letter 18-12-2025; supply agreement at FID | E30: IPL - strategic | F30: Request Continental supplier-approval letter for EIB; explore Pyrum equity roll-in | G30: Snapshot p.6; EIB thread

Sheet IPL_Debt_Capacity
A1: IPL / Thermo Lysi - what the credit market can carry, and what is left for equity
A2: Live model: change blue inputs. Base inputs per PwC Greece model Iteration 3 v.6 (2031 full year) and Credia LOI; PMO reset items flagged.
A4: OPERATING INPUTS (2031 full year) | D4: OUTPUTS
A5: Throughput (t) | B5: 44776 | D5: rCB revenue (€m) | E5: =B5*B6*B7/1000000
A6: rCB yield | B6: 0.303 | D6: Oil revenue (€m) | E6: =B5*B8*B9/1000000
A7: rCB price (€/t) | B7: 1500 | D7: Steel revenue (€m) | E7: =B5*B10*B11/1000000
A8: Pyrolysis oil yield | B8: 0.2 | D8: Gate fee revenue (€m) | E8: =B5*B12/1000000
A9: Oil price (€/t) | B9: 845 | D9: Carbon credit revenue (€m) | E9: =B5*B13/1000000
A10: Steel yield | B10: 0.245 | D10: Total revenue (€m) | E10: =SUM(E5:E9)
A11: Steel price (€/t) | B11: 250 | D11: Cash opex (€m) | E11: =B5*B14/1000000
A12: Gate fee (€/t) on all throughput | B12: 100 | D12: EBITDA (€m) | E12: =E10-E11
A13: Carbon credits (€/t) | B13: 25 | D13: EBITDA margin | E13: =IF(E10=0,0,E12/E10)
A14: Cash opex (€/t) | B14: 317 | D14: CFADS proxy (€m) = EBITDA x (1 - tax) - maintenance capex | E14: =E12*(1-B16)-B5*B15/1000000
A15: Maintenance capex (€/t) | B15: 20
A16: Corporate tax rate (Greece) | B16: 0.22 | D16: Senior debt capacity at DSCR (€m) | E16: =PV(B19,B20,-E14/B21)
D17: Senior capacity vs Sponsor plan (€m) | E17: =E16-B22
A18: SENIOR DEBT INPUTS (Credia LOI, Aug 2026) | D18: Senior capacity at 1.3x DSCR (LOI average) (€m) | E18: =PV(B19,B20,-E14/1.3)
A19: Interest rate (all-in) | B19: 0.065
A20: Repayment tenor (years, post availability) | B20: 10 | D20: VD all-in cost (cash + PIK + warrant amortised) | E20: =B26+B27+B28/B29
A21: Minimum DSCR (sizing) | B21: 1.5 | D21: VD annual cash interest (€m) | E21: =B25*B26
A22: Senior facility in Sponsor plan (€m) | B22: 77.4 | D22: VD balance at maturity with PIK (€m) | E22: =B25*(1+B27)^B29
A24: VENTURE DEBT / PRIVATE CREDIT TRANCHE | D24: Sources check (€m): grant + equity + SHL + VAT + senior plan + VD | E24: =B32+B33+B34+B35+B22+B25
A25: Tranche size (€m) | B25: 35 | D25: Gap vs total sources required (€m) | E25: =E24-B36
A26: Cash coupon | B26: 0.04 | D26: Gap if capex stress applies (€m) | E26: =E25-B37
A27: PIK coupon | B27: 0.05 | D27: Gap if senior sized on model CFADS instead of plan (€m) | E27: =E25+E17
A28: Warrant value (% of tranche, PV) | B28: 0.03
A29: Term (years) | B29: 7 | D29: Blended cost of capital (senior, VD, SHL, equity) | E29: =(B22*B19+B25*E20+B34*0.10+B33*B38)/(B22+B25+B34+B33)
D30: Interest cover: EBITDA / (senior cash interest + VD cash interest) | E30: =IF((B22*B19+E21)=0,0,E12/(B22*B19+E21))
A31: OTHER SOURCES (€m)
A32: EU Innovation Fund grant | B32: 29.4
A33: Shareholder equity committed | B33: 15
A34: Shareholder loans (10% simple) | B34: 6
A35: VAT facility | B35: 13.3
A36: Total sources required (Sponsor plan) | B36: 176
A37: Capex stress (PMO high case €150m plant vs €118.5m) - uplift | B37: 31.5
A38: Target equity IRR | B38: 0.22
A41: SENSITIVITY - senior debt capacity (€m) by gate fee (rows, €/t) and rCB price (columns, €/t), all other inputs as above
A42: Gate fee €/t \ rCB €/t | B42: 1000 | C42: 1250 | D42: 1500 | E42: 1750
A43: 0 | B43: =PV($B$19,$B$20,-((($B$5*$B$6*B$42+$B$5*$B$8*$B$9+$B$5*$B$10*$B$11+$B$5*$A43+$B$5*$B$13)/1000000-$E$11)*(1-$B$16)-$B$5*$B$15/1000000)/$B$21) | C43: =PV($B$19,$B$20,-((($B$5*$B$6*C$42+$B$5*$B$8*$B$9+$B$5*$B$10*$B$11+$B$5*$A43+$B$5*$B$13)/1000000-$E$11)*(1-$B$16)-$B$5*$B$15/1000000)/$B$21) | D43: =PV($B$19,$B$20,-((($B$5*$B$6*D$42+$B$5*$B$8*$B$9+$B$5*$B$10*$B$11+$B$5*$A43+$B$5*$B$13)/1000000-$E$11)*(1-$B$16)-$B$5*$B$15/1000000)/$B$21) | E43: =PV($B$19,$B$20,-((($B$5*$B$6*E$42+$B$5*$B$8*$B$9+$B$5*$B$10*$B$11+$B$5*$A43+$B$5*$B$13)/1000000-$E$11)*(1-$B$16)-$B$5*$B$15/1000000)/$B$21)
A44: 30 | B44: =PV($B$19,$B$20,-((($B$5*$B$6*B$42+$B$5*$B$8*$B$9+$B$5*$B$10*$B$11+$B$5*$A44+$B$5*$B$13)/1000000-$E$11)*(1-$B$16)-$B$5*$B$15/1000000)/$B$21) | C44: =PV($B$19,$B$20,-((($B$5*$B$6*C$42+$B$5*$B$8*$B$9+$B$5*$B$10*$B$11+$B$5*$A44+$B$5*$B$13)/1000000-$E$11)*(1-$B$16)-$B$5*$B$15/1000000)/$B$21) | D44: =PV($B$19,$B$20,-((($B$5*$B$6*D$42+$B$5*$B$8*$B$9+$B$5*$B$10*$B$11+$B$5*$A44+$B$5*$B$13)/1000000-$E$11)*(1-$B$16)-$B$5*$B$15/1000000)/$B$21) | E44: =PV($B$19,$B$20,-((($B$5*$B$6*E$42+$B$5*$B$8*$B$9+$B$5*$B$10*$B$11+$B$5*$A44+$B$5*$B$13)/1000000-$E$11)*(1-$B$16)-$B$5*$B$15/1000000)/$B$21)
A45: 62 | B45: =PV($B$19,$B$20,-((($B$5*$B$6*B$42+$B$5*$B$8*$B$9+$B$5*$B$10*$B$11+$B$5*$A45+$B$5*$B$13)/1000000-$E$11)*(1-$B$16)-$B$5*$B$15/1000000)/$B$21) | C45: =PV($B$19,$B$20,-((($B$5*$B$6*C$42+$B$5*$B$8*$B$9+$B$5*$B$10*$B$11+$B$5*$A45+$B$5*$B$13)/1000000-$E$11)*(1-$B$16)-$B$5*$B$15/1000000)/$B$21) | D45: =PV($B$19,$B$20,-((($B$5*$B$6*D$42+$B$5*$B$8*$B$9+$B$5*$B$10*$B$11+$B$5*$A45+$B$5*$B$13)/1000000-$E$11)*(1-$B$16)-$B$5*$B$15/1000000)/$B$21) | E45: =PV($B$19,$B$20,-((($B$5*$B$6*E$42+$B$5*$B$8*$B$9+$B$5*$B$10*$B$11+$B$5*$A45+$B$5*$B$13)/1000000-$E$11)*(1-$B$16)-$B$5*$B$15/1000000)/$B$21)
A46: 100 | B46: =PV($B$19,$B$20,-((($B$5*$B$6*B$42+$B$5*$B$8*$B$9+$B$5*$B$10*$B$11+$B$5*$A46+$B$5*$B$13)/1000000-$E$11)*(1-$B$16)-$B$5*$B$15/1000000)/$B$21) | C46: =PV($B$19,$B$20,-((($B$5*$B$6*C$42+$B$5*$B$8*$B$9+$B$5*$B$10*$B$11+$B$5*$A46+$B$5*$B$13)/1000000-$E$11)*(1-$B$16)-$B$5*$B$15/1000000)/$B$21) | D46: =PV($B$19,$B$20,-((($B$5*$B$6*D$42+$B$5*$B$8*$B$9+$B$5*$B$10*$B$11+$B$5*$A46+$B$5*$B$13)/1000000-$E$11)*(1-$B$16)-$B$5*$B$15/1000000)/$B$21) | E46: =PV($B$19,$B$20,-((($B$5*$B$6*E$42+$B$5*$B$8*$B$9+$B$5*$B$10*$B$11+$B$5*$A46+$B$5*$B$13)/1000000-$E$11)*(1-$B$16)-$B$5*$B$15/1000000)/$B$21)
A47: 130 | B47: =PV($B$19,$B$20,-((($B$5*$B$6*B$42+$B$5*$B$8*$B$9+$B$5*$B$10*$B$11+$B$5*$A47+$B$5*$B$13)/1000000-$E$11)*(1-$B$16)-$B$5*$B$15/1000000)/$B$21) | C47: =PV($B$19,$B$20,-((($B$5*$B$6*C$42+$B$5*$B$8*$B$9+$B$5*$B$10*$B$11+$B$5*$A47+$B$5*$B$13)/1000000-$E$11)*(1-$B$16)-$B$5*$B$15/1000000)/$B$21) | D47: =PV($B$19,$B$20,-((($B$5*$B$6*D$42+$B$5*$B$8*$B$9+$B$5*$B$10*$B$11+$B$5*$A47+$B$5*$B$13)/1000000-$E$11)*(1-$B$16)-$B$5*$B$15/1000000)/$B$21) | E47: =PV($B$19,$B$20,-((($B$5*$B$6*E$42+$B$5*$B$8*$B$9+$B$5*$B$10*$B$11+$B$5*$A47+$B$5*$B$13)/1000000-$E$11)*(1-$B$16)-$B$5*$B$15/1000000)/$B$21)
A49: Reading: the contracted position today (€62/t on 11ktpa, i.e. c.€15/t on 45ktpa) sits between the 0 and 30 rows. The Sponsor plan senior of €77.4m requires the €100/t row at €1,500/t rCB or better. Every €10/t of gate fee on 45ktpa is c.€0.45m EBITDA and c.€1.7m of senior capacity at 6.5% / 10y / 1.5x.
A52: SENSITIVITY - EBITDA (€m) by oil price (rows, €/t) and rCB price (columns, €/t)
A53: Oil €/t \ rCB €/t | B53: 1000 | C53: 1250 | D53: 1500 | E53: 1750
A54: 515 | B54: =($B$5*$B$6*B$53+$B$5*$B$8*$A54+$B$5*$B$10*$B$11+$B$5*$B$12+$B$5*$B$13)/1000000-$E$11 | C54: =($B$5*$B$6*C$53+$B$5*$B$8*$A54+$B$5*$B$10*$B$11+$B$5*$B$12+$B$5*$B$13)/1000000-$E$11 | D54: =($B$5*$B$6*D$53+$B$5*$B$8*$A54+$B$5*$B$10*$B$11+$B$5*$B$12+$B$5*$B$13)/1000000-$E$11 | E54: =($B$5*$B$6*E$53+$B$5*$B$8*$A54+$B$5*$B$10*$B$11+$B$5*$B$12+$B$5*$B$13)/1000000-$E$11
A55: 650 | B55: =($B$5*$B$6*B$53+$B$5*$B$8*$A55+$B$5*$B$10*$B$11+$B$5*$B$12+$B$5*$B$13)/1000000-$E$11 | C55: =($B$5*$B$6*C$53+$B$5*$B$8*$A55+$B$5*$B$10*$B$11+$B$5*$B$12+$B$5*$B$13)/1000000-$E$11 | D55: =($B$5*$B$6*D$53+$B$5*$B$8*$A55+$B$5*$B$10*$B$11+$B$5*$B$12+$B$5*$B$13)/1000000-$E$11 | E55: =($B$5*$B$6*E$53+$B$5*$B$8*$A55+$B$5*$B$10*$B$11+$B$5*$B$12+$B$5*$B$13)/1000000-$E$11
A56: 845 | B56: =($B$5*$B$6*B$53+$B$5*$B$8*$A56+$B$5*$B$10*$B$11+$B$5*$B$12+$B$5*$B$13)/1000000-$E$11 | C56: =($B$5*$B$6*C$53+$B$5*$B$8*$A56+$B$5*$B$10*$B$11+$B$5*$B$12+$B$5*$B$13)/1000000-$E$11 | D56: =($B$5*$B$6*D$53+$B$5*$B$8*$A56+$B$5*$B$10*$B$11+$B$5*$B$12+$B$5*$B$13)/1000000-$E$11 | E56: =($B$5*$B$6*E$53+$B$5*$B$8*$A56+$B$5*$B$10*$B$11+$B$5*$B$12+$B$5*$B$13)/1000000-$E$11
A57: 1000 | B57: =($B$5*$B$6*B$53+$B$5*$B$8*$A57+$B$5*$B$10*$B$11+$B$5*$B$12+$B$5*$B$13)/1000000-$E$11 | C57: =($B$5*$B$6*C$53+$B$5*$B$8*$A57+$B$5*$B$10*$B$11+$B$5*$B$12+$B$5*$B$13)/1000000-$E$11 | D57: =($B$5*$B$6*D$53+$B$5*$B$8*$A57+$B$5*$B$10*$B$11+$B$5*$B$12+$B$5*$B$13)/1000000-$E$11 | E57: =($B$5*$B$6*E$53+$B$5*$B$8*$A57+$B$5*$B$10*$B$11+$B$5*$B$12+$B$5*$B$13)/1000000-$E$11
A59: DD challenge (lender credit committee): the model EBITDA of €21.9m rests on €1,500/t rCB and €100/t gate fee across 45ktpa; neither is contracted at that level today. A credit committee will size on contracted cash flows only, which is why the venture-debt / private-credit tranche exists - it is the price of the gap between contracted and modelled revenue, not a cheaper alternative to equity.

Sheet CPEF_Debt_Capacity
A1: CPEF I Curity / Curity Pharma - how much growth debt the asset can carry, and at what price
A2: Live model. Base inputs from the Meerkat valuation business plan (stressed case) and the June 2026 Investor Pack; refresh with FY2025 actuals before external use.
A4: OPERATING INPUTS | D4: OUTPUTS
A5: Grams sold p.a. | B5: 3498219 | D5: Revenue (€m) | E5: =B5*B6/1000000
A6: Net price (€/g) | B6: 3 | D6: EBITDA (€m) | E6: =E5*B7
A7: EBITDA margin | B7: 0.5 | D7: Total debt capacity at target leverage (€m) | E7: =E6*B14
A8: Tax rate (Greece) | B8: 0.22 | D8: Headroom for growth facility after existing debt (€m) | E8: =MAX(0,E7-B10)
A9: Maintenance capex (€m) | B9: 0.11 | D9: Annual cash interest on growth facility (€m) | E9: =E8*B15
A10: Existing senior bank debt (€m) | B10: 5.57 | D10: Total cash interest (existing + growth) (€m) | E10: =B10*B11+E9
A11: Existing bank rate | B11: 0.06 | D11: Interest cover (EBITDA / cash interest) | E11: =IF(E10=0,0,E6/E10)
D12: Free cash after tax, capex and interest (€m) | E12: =E6*(1-B8)-B9-E10
A13: GROWTH FACILITY INPUTS | D13: Debt service capacity (FCF / (growth facility / tenor)) | E13: =IF(E8=0,0,E12/(E8/B16))
A14: Target leverage (net debt / EBITDA) | B14: 2.5 | D14: All-in cost of growth facility | E14: =B15+B17/B16
A15: Growth facility rate (cash) | B15: 0.13 | D15: Spread of growth facility over CPEF 8% note | E15: =E14-B18
A16: Tenor (years) | B16: 4
A17: Warrants / fees (% of facility, PV) | B17: 0.04 | D17: Look-through: CPEF share of Curity equity value (€m) | E17: =B19*B20
A18: CPEF note coupon (reference) | B18: 0.08 | D18: Implied EV / EBITDA at last mark (with existing debt) | E18: =IF(E6=0,0,(B19+B10)/E6)
A19: Curity Pharma last-marked equity value (€m) | B19: 22.2
A20: CPEF holding in Curity | B20: 0.3375
A23: SENSITIVITY - growth-facility headroom (€m) by price €/g (rows) and grams sold (columns)
A24: €/g \ grams | B24: 1500000 | C24: 2500000 | D24: 3500000 | E24: 5100000
A25: 2.5 | B25: =MAX(0,B$24*$A25/1000000*$B$7*$B$14-$B$10) | C25: =MAX(0,C$24*$A25/1000000*$B$7*$B$14-$B$10) | D25: =MAX(0,D$24*$A25/1000000*$B$7*$B$14-$B$10) | E25: =MAX(0,E$24*$A25/1000000*$B$7*$B$14-$B$10)
A26: 3 | B26: =MAX(0,B$24*$A26/1000000*$B$7*$B$14-$B$10) | C26: =MAX(0,C$24*$A26/1000000*$B$7*$B$14-$B$10) | D26: =MAX(0,D$24*$A26/1000000*$B$7*$B$14-$B$10) | E26: =MAX(0,E$24*$A26/1000000*$B$7*$B$14-$B$10)
A27: 3.75 | B27: =MAX(0,B$24*$A27/1000000*$B$7*$B$14-$B$10) | C27: =MAX(0,C$24*$A27/1000000*$B$7*$B$14-$B$10) | D27: =MAX(0,D$24*$A27/1000000*$B$7*$B$14-$B$10) | E27: =MAX(0,E$24*$A27/1000000*$B$7*$B$14-$B$10)
A28: 4.85 | B28: =MAX(0,B$24*$A28/1000000*$B$7*$B$14-$B$10) | C28: =MAX(0,C$24*$A28/1000000*$B$7*$B$14-$B$10) | D28: =MAX(0,D$24*$A28/1000000*$B$7*$B$14-$B$10) | E28: =MAX(0,E$24*$A28/1000000*$B$7*$B$14-$B$10)
A30: DD challenge (LP due-diligence lead): Curity is early-revenue (first exports 2026, Galenica distribution from October 2026). Until twelve months of audited sales exist, the only lenders are specialist cannabis credit funds at 12-16% or an asset-based lender against EU-GMP inventory and receivables. The 8% note is therefore priced below where a third-party lender would price the same risk; the difference is being carried by the Sponsor's relationship with its own investor base.

Sheet Outreach_Plan
A1: Outreach plan - waves, channels, cadence, KPIs
A2: Response-rate assumptions are analyst estimates from placement-agent practice (basis stated); track actuals in the Contacts tab and replace
A4: Wave | B4: Timing | C4: Who (segment) | D4: Objective | E4: Channel and cadence | F4: Material | G4: KPI / exit criterion | H4: Owner
A5: Wave 0 | B5: Now to 31-10-2026 | C5: Live threads: EIB VD, HIIF, Credia, Sirec, Ecoelastika, Pyrum / Continental / BASF | D5: Convert the three items EIB asked for; staged HIIF commitment; Credia CP list; gate-fee amendment; supplier-approval letter | E5: Direct email + call within 48h; weekly cadence; one owner per thread | F5: Sep 2026 Snapshot; EIB Q&A pack; HIIF IM 001; PwC model v.6; PMO reset with end-date and budget (do not circulate the reset without them) | G5: EIB 'Go' or written 'No' by 31-10; HIIF IC date fixed; Credia credit calendar; Ecoelastika amendment signed | H5: KM
A6: Wave 1 | B6: Weeks 1-4 (Oct 2026) | C6: Tier 1 cold targets: Rivage ECDS, Eiffel bridge, Polestar, Tiger Infrastructure, Incus, Cross Ocean, Blantyre; CPEF: Chicago Atlantic, Artemis, Kreos (Constantinides), Cantourage / Curaleaf offtake | D6: One meeting per firm; test appetite and price for the €35m hybrid and a €3m to €10m Curity facility | E6: LinkedIn connection note (2 lines, one hook) + email same day where published; follow-up day 5 and day 12; stop after 3 touches | F6: 3-page teaser per sub-fund (no PMO reset language); data-room index; term-sheet skeleton | G6: ≥6 first meetings; ≥2 indicative term sheets by week 8 | H6: KM / Venero
A7: Wave 2 | B7: Weeks 5-10 (Nov-Dec 2026) | C7: Tier 2: Kartesia, Tikehau Special Opps, Hayfin Special Opps, Castlelake, Davidson Kempner Greece, Arrow, Chenavari, NorthWall, Arcano, Alantra Athens, Infranity ERDF; Greek banks Piraeus / Eurobank / NBG; placement boutiques (Threadmark, Elm, Cebile, Axia process) | D7: Build competitive tension for the senior and hybrid tranches; select one placement boutique for IVP | E7: Warm intro where available (PwC, Axia, Argus, Sirec), else LinkedIn first; Ecomondo (3-6 Nov) and Capital Link NY (7 Dec) meetings pre-booked | F7: Firm EPC price (31-10) and TDD summary; refreshed returns | G7: ≥3 competing senior / hybrid indications; placement mandate signed on success fee | H7: Venero / AM
A8: Wave 3 | B8: Q1-Q2 2027 | C8: Cyprus / Greek institutional: ETYK, PEO, Cyta, Lawyers', BoC provident funds; Greek TEAs; Ethniki / NN / Generali Hellas; Greek family offices (Laskaridis, Martinos, Latsis, Vardinogiannis); Gulf FOs (IPL only) | D8: Fund-level notes and IVP anchors | E8: Argus / Muhanna / Axia introductions; Cyprus Funds Summit (Nov 2026), SuperReturn Private Credit Europe (8-10 Mar 2027), PDI Europe (May 2027) | F8: IORP-compliant note structure; AIFMD Art. 23 pack; ELTIF feasibility memo | G8: €5m IPL closed; IVP first close plan with named anchors | H8: AM / CE
A10: CHANNEL ECONOMICS (assumptions - replace with actuals)
A11: Channel | B11: Reply rate (assumed) | C11: Meeting rate (assumed) | D11: Cost / effort | E11: When to use | F11: Basis
A12: Warm introduction (Argus / Venero / Sirec / KPMG / PwC / Pyrum / EIB) | B12: 60-80% | C12: 40-60% | D12: Low cash, high relationship capital | E12: Always first where a path exists | F12: Placement-agent convention; Impactus own history (Rodopoulos, Sirec, AstroBank all came via intermediaries)
A13: Published work email + same-day LinkedIn connection note | B13: 15-25% | C13: 8-12% | D13: Low | E13: Named decision-maker, no warm path | F13: Cold outreach benchmarks for institutional capital raising (Preqin / placement agents cite 10-20% reply to targeted, personalised notes)
A14: LinkedIn InMail / connection note only | B14: 8-15% | C14: 3-6% | D14: Low | E14: When email unknown or bounces | F14: LinkedIn Sales Navigator published InMail benchmarks 10-25% for personalised messages; institutional investors lower
A15: Conference meeting request (pre-booked via app) | B15: 30-50% | C15: 20-35% | D15: High (travel, pass) | E15: Tier-1 targets clustered at one event | F15: PDI / SuperReturn organiser data on pre-booked meeting acceptance
A16: Placement agent / capital advisor | B16: n/a | C16: n/a | D16: 2-5% success fee; retainer risk | E16: Only for IVP-scale raise with a named target list | F16: Sergo proposal 5% / 2.5%; KPMG mandate; Venero engaged
A18: MESSAGE ANGLES BY AUDIENCE
A19: Audience | B19: Lead with (the bear case they will raise, answered) | C19: Proof point to attach | D19: Do not say
A20: EIB / DFI venture debt | B20: Bear case: 'mezzanine risk without equity reward' (EIB, 30-04-2026). Answer: offer conversion right or 15% to 20% warrant coverage; show the Sokolov comparison and the Continental audit letter | C20: Innovation Fund GA GAP-101250821; STEP seal; Sirec executed TS at €34m post-money | D20: Do not say 'financing entirely secured' (Pyrum release) - EIB has read the fiche with FC 31-12-2026
A21: Greek bank credit committee (Credia, Piraeus, Eurobank) | B21: Bear case: contracted gate fee is €62/t on 11ktpa, not €100/t on 45ktpa; rCB at €1,500/t is a CIF Dillingen price. Answer: size senior on contracted volumes; Ecoelastika amendment No.2; Pyrum letter for total rCB output | C21: Credia LOI 6.5% / 4+10y / 1.3x; TÜV Nord TDD; FIDIC Yellow Book EPC with guaranteed values | D21: Do not present the €176m sources table before the firm EPC price; do not cite Munich Re cover (withdrawn Feb 2026)
A22: Special-situations / hybrid lender | B22: Bear case: every European pyrolysis project was funded by grant + strategic equity; no fund has done non-recourse debt; Enviro / Plastic Energy / Quantafuel failed in 2026. Answer: this tranche prices that risk - 14% to 18% all-in with warrants, senior to €21m of shareholder capital | C22: Circtec bp €12.5m offtaker-debt precedent; Bolder / Tiger; Xycle / Polestar senior | D22: Do not lead with 22% IRR / 3.0x equity targets to a credit investor
A23: Impact / climate credit fund | B23: Bear case: FOAK technology plus licensor (Pyrum) financial fragility (FY2025 revenue €4.1m, breakeven delayed). Answer: TRL 8-9 with 8-year reference; 784,304 tCO2e; EU Innovation Fund validation; reactor-level warranty back-to-back with EPC | C23: CINEA grant; RHDHV TDD 2025; TÜV Nord 2026 | D23: Do not describe the plant as 'proven at scale' - it is the first 45ktpa deployment
A24: Cyprus provident fund / Greek TEA | B24: Bear case (LP DD lead): 8% coupon on the PE Fund has been serviced while assets are pre-revenue; internal note Aug 2025 sought c.€3m of new money for 2027-28 opex and coupon. Answer: show the coupon-coverage bridge from Curity distributions and Thermo Lysi fees, and ring-fence the note collateral | C24: Audited RAIF accounts; AIFMD Art. 23 document; Argus as AIFM; EY-reviewed fair value | D24: Do not describe the coupon as 'paid from returns' unless the cash bridge shows it
A25: Specialist cannabis lender (Chicago Atlantic, AFC, Artemis) | B25: Bear case: German price €8.33/g to €4.52/g in 15 months; GKV flower reimbursement removed 30-07-2026; every European distressed exit recovered a fraction of cost (Clever Leaves €2.5m). Answer: underwrite at ≤€2.30/g BfArM reference; security over EU-GMP plant, land and Galenica / German offtake receivables | C25: EOF GMP licence; first exports; Galenica distribution from Oct 2026; €22.2m last mark | D25: Do not cite the €4.85/g base case as the underwriting case
A26: Placement agent / capital advisor | B26: Bear case: first-time GP, sub-€100m, two sectors most LPs screen out, no institutional anchor. Answer: name the anchors (Sirec, HIIF, Cyprus provident funds), the grant, and the exit thesis to industrials | C26: Track record page; 5.75x realised partial exit; 8% coupon record | D26: Do not accept a retainer above €25k without a named target list
A27: Strategic / offtaker (BASF, Continental, Pirelli, Archirodon) | B27: Bear case: they can wait for the market to prove itself and buy later. Answer: prepayment secures supply at a floor price and pre-empts the VTTI / Antwerp 90ktpa plant on the same technology | C27: Continental advance-payment precedent; bp / Circtec; Pirelli tyre-to-tyre | D27: Do not ask for equity first - ask for the prepayment

Sheet Conferences
A1: Where these allocators are in the next twelve months
A2: Dates as published by organisers at the time of research; verify before booking
A4: Event | B4: Dates | C4: Location | D4: Audience | E4: Relevance | F4: Action | G4: Source URL
A5: Ecomondo 2026 | B5: 3-6 Nov 2026 | C5: Rimini | D5: 1,700 exhibitors; pyrolysis offtakers; ETRA members | E5: IPL offtake and feedstock; rCB buyers | F5: Pre-book Continental / Pirelli / BASF / Ecoelastika meetings | G5: https://www.ecomondo.com/en/exhibit/dates-and-set-up-times
A6: 12th Cyprus International Funds Summit & Expo (IMH) | B6: Nov 2026 (confirm date) | C6: Limassol | D6: CySEC, CIFA, Cyprus provident funds, depositaries | E6: Wave 3 provident funds; Eurobank Cyprus | F6: Speaking slot on Innovation Fund-backed infrastructure | G6: https://cyprusfundssummit.com/
A7: European Chemical Recycling Forum (Inventu) | B7: 2-3 Dec 2026 | C7: TBC | D7: Chemical recycling investors and operators | E7: IPL / IVP peer investors (Infinity, Polestar, Invest-NL) | F7: Invitation received Sep 2026 - attend | G7: Outlook 17-09-2026 (lp@igfunds.eu)
A8: 28th Capital Link Invest in Greece Forum | B8: 7 Dec 2026 | C8: New York | D8: Greek insurers, HCAP, Greek-American family offices, Greek banks | E8: IVP anchors; Chicago Atlantic (Mazarakis) diaspora angle | F8: Book meetings with Piraeus / Eurobank / NBG delegations | G8: https://capitallink.com/forums/28th-annual-capital-link-invest-in-greece-forum/
A9: IPEM Wealth 2027 | B9: 2-4 Feb 2027 | C9: Cannes | D9: Wealth / semi-liquid distributors | E9: PE Fund and note distribution | F9: Optional | G9: https://www.ipem-market.com/ipem-wealth/
A10: FFA 16th Global Fund Finance Symposium | B10: Feb 2027 | C10: Miami Beach | D10: NAV / sub-line lenders | E10: Low - scale mismatch | F10: Skip | G10: https://fundfinanceassociation.com/events/americas/02-01-27-global-symposium/
A11: SuperReturn Private Credit Europe 2027 | B11: 8-10 Mar 2027 | C11: London | D11: Credit allocators, special-sits and ABF desks (ABF summit day) | E11: Wave 2 hybrid lenders in one room | F11: Pre-book 10 meetings via app; attend ABF day | G11: https://www.neventum.com/tradeshows/superreturn-private-credite-europe
A12: 32nd ETRA Conference on Tyre Recycling | B12: Mar 2027 (TBC) | C12: Brussels | D12: Tyre recyclers, rCB offtakers, regulators | E12: Feedstock and offtake; ELVR review | F12: Attend; present Thermo Lysi | G12: https://etra-eu.org/events
A13: ICBC Berlin 2027 | B13: 13-15 Apr 2027 | C13: Berlin | D13: Cannabis operators and investors | E13: CPEF: Artemis, Casa Verde, Cantourage, Bloomwell, Chicago Atlantic | F13: Attend with Curity management | G13: https://internationalcbc.com/berlin/schedule/
A14: PDI Europe Summit 2027 | B14: May 2027 (2026: 5-6 May) | C14: London | D14: c.150 private-credit LPs | E14: IVP credit sleeve; placement agents | F14: Attend if IVP is in market | G14: https://live.peievents.com/private-credit/europe
A15: Cannabis Europa London 2027 | B15: TBA (2026: 26-27 May) | C15: London | D15: European cannabis capital | E15: CPEF investors and offtakers | F15: Attend | G15: https://cannabis-europa.com/events/cannabis-europa-london-2026/
... A18: Infrastructure Investor Global Summit 2027 | B18: Mar 2027 (Berlin; booking live) | C18: Berlin | D18: 1,200+ LPs; infra debt funds | E18: IVP / infra debt at operations | F18: Invitation in mailbox (Jul / Sep 2026) | G18: Outlook insight@mail.infrastructureinvestor.com

Sheet Scoring_Weights
A1: Scoring weights - change here; Investor_Universe and Cascade_Map_2026 recalculate
A2: Each criterion is scored 0 to 5 per firm; weighted score = SUMPRODUCT(scores, weights) / SUM(weights) x 20 -> 0 to 100
A4: Criterion | B4: Weight | C4: What 5 means | E4: Helper row (weights transposed for SUMPRODUCT - do not edit)
A5: Strategy fit - IPL (hard-asset / infra / FOAK credit) | B5: 25 | C5: Runs a strategy that lends to or invests in single-asset industrial / energy-transition projects at construction or pre-completion stage | E5: =B5 | F5: =B6 | G5: =B7 | H5: =B8 | I5: =B9 | J5: =B10 | K5: =B11
A6: Strategy fit - CPEF (pharma / cannabis / growth credit) | B6: 15 | C6: Lends to regulated pharma-adjacent or cannabis producers, or runs healthcare growth credit with no cannabis exclusion
A7: Ticket fit (€5m to €40m) | B7: 15 | C7: Minimum ticket at or below €10m and sweet spot inside €5m to €40m
A8: Geography (Greece / Cyprus / Southern Europe) | B8: 15 | C8: Has an office, portfolio or repeated deal history in Greece or Cyprus
A9: Risk appetite (FOAK, PIK, warrants, sub-IG) | B9: 10 | C9: Documented appetite for first-of-a-kind technology, PIK, warrants or construction risk
A10: Warm path (existing Impactus relationship or one-step intro) | B10: 10 | C10: Already in the Impactus pipeline, or reachable via Argus, Venero, Sirec, KPMG, PwC, Axia, Pyrum, Archirodon, EIB
A11: Speed / decision process | B11: 10 | C11: Documented ability to close in under six months; small IC; local decision-maker
A12: Total weight | B12: =SUM(B5:B11)
A14: Tier thresholds (weighted score 0-100)
A15: Tier 1 - approach in Wave 1 (score >=) | B15: 70
A16: Tier 2 - approach in Wave 2 (score >=) | B16: 50
A17: Tier 3 - keep informed only (below Tier 2)

Sheet Raise_Parameters
A1: Raise parameters and internal reference points (Sponsor sources, September 2026)
A2: All figures as they stand in the Sponsor's own working documents; PMO 02-09-2026 reset flagged where relevant
A4: Item | B4: Value | C4: Unit | D4: Source | E4: Comment / DD flag
A5: Sub-fund / vehicle | B5: Impactus Pyrolysis Ltd (IPL) - sponsor vehicle of Thermo Lysi S.A. | D5: Thermolysi Company Snapshot Sep 2026 v2
A6: Current ask (IPL) | B6: 5 | C6: €m | D6: Indicative Term Sheet 11-09-2026 v2 | E6: Share capital increase, €50m pre-money, c.9.1% at full subscription
A7: Target return (IPL) | B7: 22% IRR / 3.0x over 5 years | D7: Sponsor IM Feb 2026 | E7: Gross; to be refreshed on firm EPC price (31-10-2026)
A8: Plant capacity | B8: 45 | C8: ktpa | D8: Snapshot p.5 | E8: Two lines of 22.5ktpa; six Pyrum TD3 reactors
A9: Plant capex (PwC Iteration 3 v.6) | B9: 118.5 | C9: €m | D9: Snapshot p.9 | E9: 2 x €59.2m; PMO 02-09-2026 flags €120m vs €150m unresolved
A10: Total sources of funds | B10: 176 | C10: €m | D10: Snapshot p.9 | E10: Includes development, fees, WC, reserves
A11: EU Innovation Fund grant (signed 09-03-2026) | B11: 29.4 | C11: €m | D11: GAP-101250821 | E11: Lump sum; WP1 €2.06m, WP2 €24.4m at entry into operation
A12: Shareholder capital committed | B12: 21 | C12: €m | D12: Snapshot p.9 | E12: €15m equity + €6m shareholder loans at 10% simple
A13: VAT facility | B13: 13.3 | C13: €m | D13: Snapshot p.9 | E13: Construction VAT bridge
A14: Venture debt tranche (offered, not committed) | B14: 35 | C14: €m | D14: Snapshot p.9 | E14: 4% cash + 5% PIK + warrants; 10% blended; offered to an institutional investor (HIIF)
A15: Senior facility (Credia Bank term sheet) | B15: 77.4 | C15: €m | D15: Snapshot p.9; Credia LOI thread Aug 2026 | E15: Sized at 1.5x DSCR; indicative 6.5% p.a., 4+10y, 1.3x average DSCR; credit approval on firm EPC price
A16: EIB Venture Debt | B16: In process | D16: EIB responses thread 15-09-2026 | E16: Committee discussed project; clarifications requested (Credia CPs, Continental audit letter, Sokolov comparison)
A17: 2031 revenue (PwC model) | B17: 36.1 | C17: €m | D17: Snapshot p.7 | E17: rCB €1,500/t, TPO €845/t, steel €250/t, gate fee €100/t, carbon €25/t
A18: 2031 EBITDA (PwC model) | B18: 21.9 | C18: €m | D18: Snapshot p.7 | E18: €489 EBITDA per tonne
A19: Gate fee contracted today | B19: 62 | C19: €/t | D19: PMO MoM 03-09-2026 | E19: On 11ktpa only vs €100/t on 45ktpa in the model - the swing item
A20: FID target | B20: 31-12-2026 (PMO: not feasible; controlled reset proposed) | D20: PMO MoM 03-09-2026 | E20: Firm EPC offer 31-10-2026; ECI to 18-11-2026
A21: Sub-fund / vehicle | B21: CPEF I Curity Ltd - holds 33.75% of Curity Pharma S.A. | D21: Investor Pack Q2 2026
A22: Current instrument (CPEF) | B22: 8% CPEF I Curity Note, 48 months, up to €435k, min €10k | D22: Note term sheet 2026 | E22: Back-to-back to Curity convertible loan; conversion fallback at €22.2m valuation (~1.96%)
A23: Curity Pharma last-marked equity value | B23: 22.2 | C23: €m | D23: Capital increase 2025-26 | E23: Facility €14m; EOF GMP licence; Larissa; Galenica distribution from Oct 2026
A24: Curity stressed plan (Meerkat FY2023) | B24: 3.5m g at €3.00/g -> revenue €10.5m, EBITDA c.€5.3m | D24: Meerkat valuation 31-12-2023, App. IV | E24: Base case €4.85/g -> €24.8m sales, €18.8m EBITDA (Sponsor figures, not diligenced)
A25: Curity existing bank debt (plan) | B25: 5.57 | C25: €m | D25: Meerkat valuation 31-12-2023 | E25: Greek commercial bank, 6-8y; plus €2.8m grant bridge
A26: Platform raise (IVP) | B26: 88 | C26: €m | D26: Investor Pack Q2 2026 | E26: 4 assets, €410m platform capital, 21.8% / 29.5% blended gross IRR
A27: PE Fund coupon | B27: 8% p.a. net, paid since 2022 | D27: Investor Pack Q2 2026 | E27: Internal note Aug 2025: c.€3m needed for 2027-28 opex and coupon - DD challenge (see memo)

Sheet Sources
A1: Sources
A2: Every external figure in this workbook traces to one of these; internal figures trace to the Sponsor documents named on the Raise_Parameters tab
A4: # | B4: Source | C4: Publisher / type | D4: Date | E4: URL | F4: Used for
A5: 1 | B5: Cascade Debt - Private Debt and Alternative Credit Investors in Europe (2026 Europe Private ABF Investor Market Map) | C5: Cascade Debt | D5: 2026 | E5: https://www.cascadedebt.com/insights/private-debt-and-alternative-credit-investors-in-europe | F5: Cascade_Map_2026 tab (map image supplied by user; page itself blocked from this environment)
A6: 2 | B6: Europe grows share of private credit fundraising in 2025 | C6: Alternative Credit Investor | D6: 16-12-2025 | E6: https://alternativecreditinvestor.com/2025/12/16/europe-grows-share-of-private-credit-fundraising-in-2025/ | F6: Market_Overview
A7: 3 | B7: Record European private debt fundraising signals shift in global capital allocation | C7: PitchBook | D7: 2026 | E7: https://pitchbook.com/news/articles/record-european-private-debt-fundraising-signals-shift-in-global-capital-allocation | F7: Market_Overview
A8: 4 | B8: All eyes on Europe as cracks emerge in private credit | C8: S&P Global / With Intelligence | D8: 2026 | E8: https://www.spglobal.com/en/press/press-release/all-eyes-on-europe-as-cracks-emerge-in-private-credit | F8: Market_Overview
A9: 5 | B9: European direct lending hits record despite Q2 dip | C9: Alternative Credit Investor | D9: 25-08-2026 | E9: https://alternativecreditinvestor.com/2026/08/25/european-direct-lending-hits-record-despite-q2-dip/ | F9: Market_Overview
A10: 6 | B10: Private Debt Deal Tracker (Autumn 2025) | C10: Deloitte UK | D10: 2025 | E10: https://www.deloitte.com/uk/en/services/consulting-financial/research/private-debt-deal-tracker.html | F10: Market_Overview
A11: 7 | B11: European Private Market Update Q2 2026 | C11: Valuation Research Corp | D11: 2026 | E11: https://www.valuationresearch.com/insights/european-private-market-update-q2-2026/ | F11: Pricing
A12: 8 | B12: 2025 Annual Global Private Debt Report | C12: PitchBook | D12: 2026 | E12: https://pitchbook.com/news/reports/2025-annual-global-private-debt-report | F12: Concentration
A13: 9 | B13: Private Credit Outlook 2026: Market Faces First Big Test | C13: With Intelligence | D13: 2026 | E13: https://www.withintelligence.com/insights/private-credit-outlook-2026/ | F13: Market_Overview
A14: 10 | B14: Private credit - investors are turning to Europe | C14: Allianz Global Investors | D14: 2026 | E14: https://www.allianzgi.com/en/insights/private-credit-investors-are-turning-to-Europe | F14: AUM
A15: 11 | B15: ECB Financial Stability Review May 2026 - special feature on private credit | C15: ECB | D15: May 2026 | E15: https://www.ecb.europa.eu/press/financial-stability-publications/fsr/special/html/ecb.fsrart202605_04~3f2135af91.en.html | F15: LP base
A16: 12 | B16: ECB monetary policy decision 11 June 2026 | C16: ECB | D16: 11-06-2026 | E16: https://www.ecb.europa.eu/press/pr/date/2026/html/ecb.mp260611~4d41bd5e83.en.html | F16: Rates
... A52: 48 | B52: Internal: Thermolysi Project - Company Snapshot Sep 2026 v2; Indicative Term Sheet 11-09-2026; PMO Change of Strategy MoM 03-09-2026; Investor Pack Q2 2026 v4; Credia / EIB / HIIF Outlook threads; investor tracker 03-08-2026; Meerkat Curity valuation FY2023; Fathom calls 23-06-2025 and 20-03-2026 | C52: Impactus records (SharePoint / Outlook / Fathom) | D52: 2025-26 | E52: internal | F52: Raise_Parameters, Existing_Pipeline, models
