Workbook

Sheet Summary
B2: instrAction - two cases, every line, one workbook
B3: Expanded version of the two-case model of 04-08-2026. Case 1 = the sponsors' business plan of 17-07-2026 with EVERY line of their model on one page, to the 2029 returns. Case 2 = the company as we understand it after diligence and the management discussion of 04-08-2026, same depth. EUR m throughout.
B5: HOW TO READ THIS FILE
B6: BLUE figures are plugged from the sponsors' plan unchanged. RED figures are our additions - each carries its rationale alongside. Black figures are calculations.
B7: Each case sheet reads top to bottom as one argument: model controls > product economics > every revenue line > P&L > cash flow > balance sheet > the 2029 exit waterfall and the return on the EUR 2m.
B9: HEADLINE COMPARISON
C10: Case 1 - as given | D10: Case 2 - as understood | E10: Difference | J10: Notes
B11: Revenue 2026 H2 | C11: ='Case 1 - As Given'!C65 -> 0.21 | D11: ='Case 2 - As Understood'!C30 -> 0.3 | E11: =D11-C11 -> 0.09 | J11: Their four layers vs our three tracks.
B12: Revenue 2027 | C12: ='Case 1 - As Given'!D65 -> 2.17 | D12: ='Case 2 - As Understood'!D30 -> 0.9 | E12: =D12-C12 -> -1.27
B13: Revenue 2028 | C13: ='Case 1 - As Given'!E65 -> 6.86 | D13: ='Case 2 - As Understood'!E30 -> 3 | E13: =D13-C13 -> -3.86
B14: Revenue 2029 | C14: ='Case 1 - As Given'!F65 -> 8.02 | D14: ='Case 2 - As Understood'!F30 -> 6 | E14: =D14-C14 -> -2.02
B15: EBITDA 2028 | C15: ='Case 1 - As Given'!E71 -> 1.513 | D15: ='Case 2 - As Understood'!E54 -> -1.95 | E15: =D15-C15 -> -3.463 | J15: Their profitability year vs our still-negative year - findings 1 and 2 in money.
B16: EBITDA 2029 | C16: ='Case 1 - As Given'!F71 -> 1.643 | D16: ='Case 2 - As Understood'!F54 -> -0.246 | E16: =D16-C16 -> -1.889
B17: Lowest year-end cash | C17: =MIN('Case 1 - As Given'!C83:F83) -> 1.16 | D17: =MIN('Case 2 - As Understood'!C65:F65) -> 0.4695 | E17: =D17-C17 -> -0.6905 | J17: Case 2 stays positive only because of the assumed 2027 top-up.
B18: External equity required 2026-29 | C18: =4 -> 4 | D18: =9 -> 9 | E18: =D18-C18 -> 5 | J18: Their single EUR 4m close vs EUR 4m + the EUR 5m top-up their plan does not mention.
B19: Certification budget carried | C19: =0 -> 0 | D19: =2.2 -> 2.2 | E19: =D19-C19 -> 2.2 | J19: Finding 1 - zero in their use of funds; itemised on Case 2, section D.
B20: Exit equity value 2029 (base, 5.0x revenue) | C20: ='Case 1 - As Given'!C97 -> 43.84 | D20: ='Case 2 - As Understood'!C80 -> 30.4695 | E20: =D20-C20 -> -13.3705
B21: EUR 2m fully diluted share at exit | C21: ='Case 1 - As Given'!C108 -> 0.094733333 | D21: ='Case 2 - As Understood'!C92 -> 0.0758 | E21: =D21-C21 -> -0.018933333 | J21: Dilution x0.8 from the top-up round.
B22: EUR 2m participation - proceeds | C22: ='Case 1 - As Given'!C107 -> 4.1531093 | D22: ='Case 2 - As Understood'!C91 -> 2.3095881 | E22: =D22-C22 -> -1.8435212
B23: EUR 2m participation - multiple | C23: ='Case 1 - As Given'!D107 -> 2.0765547 | D23: ='Case 2 - As Understood'!D91 -> 1.1547941 | E23: =D23-C23 -> -0.92176062
B24: EUR 2m participation - IRR (3 yrs) | C24: ='Case 1 - As Given'!E107 -> 0.27579567 | D24: ='Case 2 - As Understood'!E91 -> 0.049143383
B26: SENSITIVITY - EUR 2m MULTIPLE OF MONEY BY EXIT EQUITY VALUE
B27: Exit equity value (EUR m) | C27: Case 1 - as given | D27: Case 2 - as understood | J27: Notes
B28: 35 | C28: =MAX(2,0.0947*B28)/2 -> 1.65725 | D28: =MAX(2,0.0758*B28)/2 -> 1.3265 | J28: The 1x preference floors the downside below c.EUR 22m exits.
B29: 55 | C29: =MAX(2,0.0947*B29)/2 -> 2.60425 | D29: =MAX(2,0.0758*B29)/2 -> 2.0845 | J29: The base the 1-pagers argue for - clears hurdles in both cases.
B30: 90 | C30: =MAX(2,0.0947*B30)/2 -> 4.2615 | D30: =MAX(2,0.0758*B30)/2 -> 3.411 | J30: A strategic contest (Xylem / Veolia class) over a certified, contracted asset.
B32: OUR FINDINGS IN FIVE LINES (detail: Case 2, section A)
B33: 1. No certification budget in the use of funds - yet the utility track and the exit multiple depend on starting it now (EUR 2.2m, itemised).
B34: 2. Frameworks are 12-month tests - volume and price only from c.Oct-27, which breaks 'profitable in 18-24 months' and forces a EUR 5m top-up in 2027.
B35: 3. AFFF is project revenue in a closing window (2030) - the recurring story behind the EUR 15m pre-money is the certification-gated utility track.
B36: 4. Destruction-only disposal for POP-loaded resin - contract it before volumes start; no regeneration revenue on Track 1.
B37: 5. The historic preference stack (c.EUR 12m of down rounds) is preserved in the term sheet - worth c.EUR 1m to us at mid exits; settle it in the documents.
B39: THE DIFFERENCE BETWEEN THE TWO CASES, IN ONE SENTENCE
B40: One year of commercial timing, EUR 2.2m of certification money the plan does not carry, a EUR 5m top-up round the plan does not mention - and the dilution that comes with it.
B42: Working model for discussion - not investment advice. Sources: business plan model and term sheet 17-07-2026 (all Case-1 lines transcribed from the model's Revenue Inputs and dashboard); management call 04-08-2026; Programme workbook and funding assessment 31-07-2026; Pyrum public record 2018-2026.

Sheet Case 1 - As Given
B2: Case 1 - the business plan as given (17-07-2026) - expanded to every line of their model
B3: One page: their model controls, product economics, all revenue lines, P&L, cash flow, balance sheet - leading to the 2029 exit waterfall and returns. BLUE = their figures unchanged. EUR m unless marked EUR k.
B5: STAGES ON THE PLAN'S TIMELINE
C6: 2026 H2 | D6: 2027 | E6: 2028 | F6: 2029 | G6: 2030 memo | H6: 2031 memo
C7: Second close + ramp-up | D7: Scale-up year | E7: EBITDA turns positive | F7: Exit window (projected) | G7: (beyond their exit story) | H7: (beyond their exit story)
B9: A. THEIR MODEL CONTROLS AND SCENARIO SETTINGS (sheet 'Instructions & Scenario')
B10: Active scenario | C10: Base | J10: Their model also carries Downside (pipeline x70%, top-down x60%, COGS x110%) and Upside (x130% / x150% / x95%) multiplier sets; everything below is the Base case they present.
B11: Probability weighting of named pipeline | C11: Yes | J11: Named-pipeline rows enter revenue at their sales-stage probability; existing and contracted rows enter at 100%.
B12: Starting cash (01-Jul-26) | C12: 0.35 | J12: EUR 0.35m opening cash - MIG's first EUR 1m of 2026 already inside.
B13: Planning grid | C13: monthly | J13: 30 monthly periods Jul-26 to Dec-28, then semi-annual to 2031. Annualised on this page.
B14: Default annual price increase / COGS improvement | C14: 0.02 | D14: 0.03 | J14: Applied to unit-priced products; top-down segment targets are entered as direct EUR revenue.
B16: B. PRODUCT ECONOMICS - THEIR FULL PRICE AND COGS TABLE
B17: Product (ID - group) | C17: Unit | D17: Std price EUR | E17: COGS EUR | F17: COGS % | G17: Gross margin | H17: Type | J17: Notes
B18: PFAS-BULK - PFAS resin bulk | C18: Liter | D18: 45 | E18: 12 | F18: 0.27 | G18: 0.733 | H18: Recurring | J18: Carries the two System-Integrator / Water-Utility segments - the volume story.
B19: PFAS-FILTER - filter / cartridge | C19: Unit | D19: 2500 | E19: 900 | F19: 0.36 | G19: 0.64 | H19: Recurring | J19: Carries the NA AFFF segment, the OEM segment and two named rows.
B20: PILOT - pilot equipment / MTU | C20: Project | D20: 35000 | E20: 18000 | F20: 0.51 | G20: 0.49 | H20: One-off | J20: Carries the EU AFFF (MTU) segment and three named rows; thinnest margin in the book.
B21: MTU - MTU operational | C21: Unit | D21: 35000 | E21: 18000 | F21: 0.51 | G21: 0.49 | H21: One-off | J21: Defined but unused by any revenue line in the Base case.
B22: HMR - heavy metal resin | C22: Liter | D22: 35 | E22: 10 | F22: 0.29 | G22: 0.714 | H22: Recurring | J22: Defined but unused - no revenue line attached.
B23: POU-MEDIA - point-of-use / OEM media | C23: Unit | D23: 12 | E23: 4 | F23: 0.33 | G23: 0.667 | H23: Recurring | J23: Carries the EU PoU/PoE segment.
B24: ANALYTICS - analytics / services | C24: Project | D24: 10000 | F24: 0.3 | G24: 0.7 | H24: One-off | J24: Defined but unused.
B25: ADVISORY - consulting services | C25: Project | D25: 10000 | F25: 0.3 | G25: 0.7 | H25: One-off | J25: Defined but unused.
B26: LICENSE - license / milestone | C26: Contract | F26: 0.05 | G26: 0.95 | H26: One-off | J26: Defined but unused - no licensing revenue anywhere in the plan.
B27: REGEN - regeneration / exchange service | C27: Service | D27: 15000 | F27: 0.35 | G27: 0.65 | H27: Recurring | J27: Defined but unused in the Base case - and the POP destruction constraint challenges it (see Case 2, finding 4).
B28: Six of ten products carry no revenue in the Base case - the plan runs on four: PILOT, PFAS-FILTER, PFAS-BULK, POU-MEDIA.
B30: C. THEIR SALES-STAGE PROBABILITY LADDER
B31: Sales stage | C31: Probability | J31: Definition (theirs, verbatim)
B32: Contracted / PO | C32: 1 | J32: Signed contract or purchase order received
B33: Awarded | C33: 0.9 | J33: Customer has made a clear decision in principle
B34: Contract Negotiation | C34: 0.75 | J34: Contract terms are being negotiated
B35: Commercial Proposal | C35: 0.5 | J35: Formal commercial proposal submitted
B36: Qualified Pilot | C36: 0.3 | J36: Specific pilot with a defined decision path
B37: Early Discussion | C37: 0.1 | J37: Initial customer discussion
B38: Unidentified | C38: n/a | J38: No named customer yet - enters revenue at 100% of the segment target, unweighted
B39: The asymmetry to note: a named customer at first discussion counts at 10% - a target segment with NO customer at all counts at 100%.
B41: D. THE REVENUE BUILD-UP - EVERY LINE IN THEIR MODEL (EUR k, as they enter the P&L)
B42: EUR k | C42: 2026 H2 | D42: 2027 | E42: 2028 | F42: 2029 | G42: 2030 memo | H42: 2031 memo | J42: Notes
B43: Named customers - bottom-up (probability-weighted values, i.e. what their model books):
B44: REV-001 Existing - pilot equipment (Awarded, 90%) | C44: 35 | D44: 0 | E44: 0 | F44: 0 | G44: 0 | H44: 0 | J44: 'Accumulated existing pipeline', PILOT product. EUR 8k Jul-26 + 5k Aug + 22k Sep - all of it in three months of 2026.
B45: REV-002 Existing - filters (Awarded, 90%) | C45: 6 | D45: 0 | E45: 0 | F45: 0 | G45: 0 | H45: 0 | J45: PFAS-FILTER. EUR 2k each Jul / Sep / Oct-26.
B46: REV-003 Contracted - pilots (Contract Negotiation, 75%) | C46: 46 | D46: 37 | E46: 0 | F46: 0 | G46: 0 | H46: 0 | J46: PILOT. Runs Aug-26 to Mar-27 and then STOPS - their contracted book is empty from Apr-27 onward.
B47: REV-004 Named pipeline - filters (Early Discussion, 10%) | C47: 5.5 | D47: 127.2 | E47: 0.1 | F47: 0 | G47: 0 | H47: 0 | J47: Gross entries of EUR 1.33m booked at 10%: EUR 555k Jan-27, 265k Feb-27, 320k Mar-27 are the bulk - one cluster of early discussions.
B48: REV-005 Named pipeline - pilots (Early Discussion, 10%) | C48: 2.3 | D48: 70.6 | E48: 0 | F48: 0 | G48: 0 | H48: 0 | J48: Gross entries of EUR 0.73m booked at 10%: EUR 209k / 260k / 187k in Jan-Mar-27.
B49: Named customers - subtotal | C49: =SUM(C44:C48) -> 94.8 | D49: =SUM(D44:D48) -> 234.8 | E49: =SUM(E44:E48) -> 0.1 | F49: =SUM(F44:F48) -> 0 | G49: =SUM(G44:G48) -> 0 | H49: =SUM(H44:H48) -> 0 | J49: Everything with a name attached. It peaks at EUR 0.23m (2027) and is finished by early 2028.
B51: Top-down segment targets - no named customer behind any figure below (their own dashboard flags this):
B52: SEG-EU-IND Europe - AFFF (MTU) - pilot equipment | C52: 20 | D52: 650 | E52: 1840 | F52: 1500 | G52: 1750 | H52: 1937.3 | J52: Ramps EUR 5k/month (Oct-26) to EUR 200k/month (end-28); then +5% per half-year. The AFFF servicing story, Europe.
B53: SEG-NA-IND North America - AFFF (filters) | C53: 5 | D53: 142.5 | E53: 370 | F53: 310 | G53: 215.3 | H53: 237.3 | J53: PFAS-FILTER. Small, steady ramp; oddly DECLINES after an H1-29 spike of EUR 210k.
B54: SEG-EU-LAND Europe - system integrators - bulk resin | C54: 60 | D54: 300 | E54: 2120 | F54: 1800 | G54: 2460 | H54: 2712.2 | J54: PFAS-BULK. Jumps EUR 50k to 150k/month at Jan-28 - the single biggest step in the whole plan, no trigger named.
B55: SEG-NA-LAND North America - water utilities - bulk resin | C55: 0 | D55: 375 | E55: 1500 | F55: 1900 | G55: 2152.5 | H55: 2373.1 | J55: PFAS-BULK. Quarterly from Mar-27, EUR 150k/month through 2028 - assumes US municipal sales with NSF certification nowhere in the budget.
B56: SEG-EU-MUN Europe - PoU / PoE - OEM media | C56: 25 | D56: 270 | E56: 680 | F56: 710 | G56: 753.4 | H56: 830.6 | J56: POU-MEDIA at EUR 12/unit - implies c.5m units/yr by 2028 via unnamed OEM channels.
B57: SEG-GLOBAL-OEM Global - strategic industry partners | C57: 0 | D57: 190 | E57: 350 | F57: 1800 | G57: 3200 | H57: 5000 | J57: PFAS-FILTER. Lumpy milestone-like entries, then EUR 1.8m (2029) to EUR 5m (2031) - by 2031 the largest single line; entirely unnamed.
B58: Top-down segments - subtotal | C58: =SUM(C52:C57) -> 110 | D58: =SUM(D52:D57) -> 1927.5 | E58: =SUM(E52:E57) -> 6860 | F58: =SUM(F52:F57) -> 8020 | G58: =SUM(G52:G57) -> 10531.2 | H58: =SUM(H52:H57) -> 13090.5 | J58: 70.8% of even the NEXT 12 MONTHS' revenue is from these unnamed segments - their model's own validation panel says so.
B59: Total revenue, all lines (EUR k) | C59: =C49+C58 -> 204.8 | D59: =D49+D58 -> 2162.3 | E59: =E49+E58 -> 6860.1 | F59: =F49+F58 -> 8020 | G59: =G49+G58 -> 10531.2 | H59: =H49+H58 -> 13090.5
B60: Their dashboard total (EUR k) | C60: 210 | D60: 2170 | E60: 6860 | F60: 8020 | G60: 10530 | H60: 13090 | J60: The headline series their dashboard reports (EUR 0.21m / 2.17m / 6.86m / 8.02m / 10.53m / 13.09m).
B61: Check - line build-up vs their dashboard | C61: =C59-C60 -> -5.2 | D61: =D59-D60 -> -7.7 | E61: =E59-E60 -> 0.1 | F61: =F59-F60 -> 0 | G61: =G59-G60 -> 1.2 | H61: =H59-H60 -> 0.5 | J61: Differences of EUR 8k or less per year - rounding inside their 30 monthly columns. The transcription is complete.
B63: E. P&L - AS THEIR MODEL STATES IT
B64: EUR m | C64: 2026 H2 | D64: 2027 | E64: 2028 | F64: 2029 | G64: 2030 memo | H64: 2031 memo | J64: Notes
B65: Total revenue | C65: 0.21 | D65: 2.17 | E65: 6.86 | F65: 8.02 | G65: 10.53 | H65: 13.09 | J65: Their dashboard series, unchanged. 2030-31 shown for completeness - their exit story ends 2029.
B66: Cost of sales | C66: 0.08 | D66: 0.66 | E66: 1.93 | F66: 2.34 | G66: 3.1 | H66: 3.91 | J66: Blended from the product COGS table; 2030-31 derived from their stated gross profit.
B67: Gross profit | C67: =C65-C66 -> 0.13 | D67: =D65-D66 -> 1.51 | E67: =E65-E66 -> 4.93 | F67: =F65-F66 -> 5.68 | G67: =G65-G66 -> 7.43 | H67: =H65-H66 -> 9.18
B68: Gross margin | C68: =C67/C65 -> 0.61904762 | D68: =D67/D65 -> 0.69585253 | E68: =E67/E65 -> 0.71865889 | F68: =F67/F65 -> 0.70822943 | G68: =G67/G65 -> 0.70560304 | H68: =H67/H65 -> 0.7012987
B69: Personnel | C69: 0.7 | D69: 1.55 | E69: 1.8 | F69: 2.1 | J69: Their cost plan to 2029; beyond 2029 their model reports only combined running costs.
B70: Other operating costs | C70: =C67-C69-C71 -> 0.7 | D70: =D67-D69-D71 -> 1.35 | E70: =E67-E69-E71 -> 1.617 | F70: =F67-F69-F71 -> 1.937 | J70: Derived so the P&L reconciles exactly to their stated EBITDA - as in the source workbook.
B71: EBITDA | C71: -1.27 | D71: -1.39 | E71: 1.513 | F71: 1.643 | G71: 2.6 | H71: 3.7 | J71: Their stated operating result. Loss-making through 2027, positive from 2028 on their numbers.
B72: Running costs (personnel + other) | C72: =C69+C70 -> 1.4 | D72: =D69+D70 -> 2.9 | E72: =E69+E70 -> 3.417 | F72: =F69+F70 -> 4.037 | G72: =G67-G71 -> 4.83 | H72: =H67-H71 -> 5.48 | J72: 2030-31: gross profit less their stated EBITDA (c.EUR 4.8m / 5.5m - matches the funding assessment).
B73: memo: depreciation | C73: 0.03 | D73: 0.1 | E73: 0.17 | F73: 0.22 | J73: Below-EBITDA memo, from their model.
B75: F. CASH FLOW - AS THEIR MODEL STATES IT
B76: EUR m | C76: 2026 H2 | D76: 2027 | E76: 2028 | F76: 2029 | G76: 2030 memo | H76: 2031 memo | J76: Notes
B77: EBITDA | C77: =C71 -> -1.27 | D77: =D71 -> -1.39 | E77: =E71 -> 1.513 | F77: =F71 -> 1.643 | G77: =G71 -> 2.6 | H77: =H71 -> 3.7
B78: Equipment spend | C78: 0.15 | D78: 0.38 | E78: 0.326 | F78: 0.25 | G78: 0.15 | H78: 0 | J78: Small by design - resin produced by third parties; mobile units c.EUR 0.2-0.3m each.
B79: Change in working capital | C79: 0 | D79: 0 | E79: 0 | F79: 0 | G79: 0 | H79: 0 | J79: The plan models NO working capital at all - no inventory, no receivables. Flagged; corrected in Case 2.
B80: New equity raised | C80: 4 | D80: 0 | E80: 0 | F80: 0 | G80: 0 | H80: 0 | J80: EUR 4m second close Sep-26 (EUR 1m MIG + EUR 3m new investors) - and NOTHING after it, ever. The plan claims self-sufficiency from one round.
B81: Net cash flow | C81: =C77-C78-C79+C80 -> 2.58 | D81: =D77-D78-D79+D80 -> -1.77 | E81: =E77-E78-E79+E80 -> 1.187 | F81: =F77-F78-F79+F80 -> 1.393 | G81: =G77-G78-G79+G80 -> 2.45 | H81: =H77-H78-H79+H80 -> 3.7
B82: Opening cash | C82: 0.35 | D82: =C83 -> 2.93 | E82: =D83 -> 1.16 | F82: =E83 -> 2.347 | G82: =F83 -> 3.74 | H82: =G83 -> 6.19
B83: Closing cash | C83: =C82+C81 -> 2.93 | D83: =D82+D81 -> 1.16 | E83: =E82+E81 -> 2.347 | F83: =F82+F81 -> 3.74 | G83: =G82+G81 -> 6.19 | H83: =H82+H81 -> 9.89 | J83: Reconciles to their dashboard (1.16 in 2027 ... 3.74 in 2029 ... 9.89 in 2031). Their own monthly view briefly dips below zero in 2027.
B85: G. BALANCE SHEET (year-end, simplified) - TO THE 2029 EXIT
B86: EUR m | C86: 2026 H2 | D86: 2027 | E86: 2028 | F86: 2029 | J86: Notes
B87: Cash | C87: =C83 -> 2.93 | D87: =D83 -> 1.16 | E87: =E83 -> 2.347 | F87: =F83 -> 3.74
B88: Working capital | C88: 0 | D88: 0 | E88: 0 | F88: 0 | J88: Zero throughout - see the flag above.
B89: Fixed assets, net | C89: =C78-C73 -> 0.12 | D89: =C89+D78-D73 -> 0.4 | E89: =D89+E78-E73 -> 0.556 | F89: =E89+F78-F73 -> 0.586
B90: Total assets | C90: =C87+C89 -> 3.05 | D90: =D87+D89 -> 1.56 | E90: =E87+E89 -> 2.903 | F90: =F87+F89 -> 4.326
B91: Equity (capital raised less accumulated losses) | C91: =C90 -> 3.05 | D91: =D90 -> 1.56 | E91: =E90 -> 2.903 | F91: =F90 -> 4.326 | J91: No debt anywhere in the plan - the whole balance sheet is equity-funded. Simplified single-line equity.
B93: H. EXIT 2029 - CASH WATERFALL AND RETURNS (WHERE THE PAGE HAS BEEN LEADING)
B94: EV / revenue multiple at exit | C94: 5 | J94: Trade-sale multiple on 2029 revenue - change it and everything below recalculates. The Summary sensitivity works from equity values directly.
B95: Enterprise value | C95: =C94*F65 -> 40.1
B96: plus: cash at exit | C96: =F83 -> 3.74
B97: Equity value | C97: =C95+C96 -> 43.84
B99: Investor class (fully diluted, post-VSOP) | C99: FD % | D99: Invested | E99: 1x pref | F99: Proceeds | G99: Multiple | J99: Notes
B100: MIG Funds (incl. EUR 2m of this round) | C100: 0.709 | D100: 14 | E100: 2 | F100: =MAX(IF(E100="",0,E100),C100*$C$97) -> 31.08256 | G100: =F100/D100 -> 2.2201829 | J100: Historic cost c.EUR 12m + EUR 2m now. Deck states historic preferences do not affect new money - taken at face value here; challenged in Case 2, finding 5.
B101: Other existing holders | C101: 0.034 | F101: =MAX(IF(E101="",0,E101),C101*$C$97) -> 1.49056
B102: Treasury shares | C102: 0.015 | F102: =MAX(IF(E102="",0,E102),C102*$C$97) -> 0.6576
B103: New co-investors 2026 (EUR 3m, incl. the EUR 2m assessed) | C103: 0.1421 | D103: 3 | E103: 3 | F103: =MAX(IF(E103="",0,E103),C103*$C$97) -> 6.229664 | G103: =F103/D103 -> 2.0765547 | J103: 1x non-participating, pari passu with MIG's 2026 money.
B104: VSOP (10%) | C104: 0.1 | F104: =MAX(IF(E104="",0,E104),C104*$C$97) -> 4.384 | J104: Virtual options - participate economically at exit.
B105: Total distributed | F105: =SUM(F100:F104) -> 43.844384 | J105: Approximation: each class takes the greater of preference or pro-rata; interactions ignored (immaterial when all classes convert).
B107: The EUR 2m participation - proceeds / multiple / IRR | C107: =2/3*F103 -> 4.1531093 | D107: =C107/2 -> 2.0765547 | E107: =(C107/2)^(1/3)-1 -> 0.27579567 | J107: EUR 2m = two-thirds of the EUR 3m new-investor class. Proceeds, multiple of money and 3-year IRR at the base exit above.
B108: memo: EUR 2m fully diluted share | C108: =2/3*C103 -> 0.094733333 | J108: c.9.5% FD - feeds the sensitivity on the Summary.
B110: All blue figures transcribed from the sponsors' model of 17-07-2026 (Base, probability-weighted) and its dashboard; FD percentages from the term sheet's illustrative capitalisation. This page IS their case - the argument with it lives in Case 2.

Sheet Case 2 - As Understood
B2: Case 2 - the case as we understand it - expanded: findings, corrections, and what they do to the returns
B3: Same skeleton as Case 1. RED = our additions and corrections, each with its rationale. Staging follows the management discussion of 04-08-2026. EUR m unless marked.
B5: STAGES ON THE TIMELINE AS WE UNDERSTAND IT
C6: 2026 H2 | D6: 2027 | E6: 2028 | F6: 2029
C7: Framework year (partner tests) | D7: Top-up round + commercial agreements from Oct-27 | E7: Certified utility entry | F7: Approach to profitability - exit window
B9: A. OUR FINDINGS - THE FIVE GAPS BETWEEN THE STORY AND THE PAPER
B10: 1. No certification budget anywhere in the use of funds | J10: Case 1, sections B and D: the NA-utilities and OEM segments assume certified sales, yet not one euro of KTW/DVGW/NSF money appears in their costs. The utility track AND the exit multiple depend on starting now. We add the EUR 2.2m programme in section D below.
B11: 2. Frameworks are 12-month tests, not volume | J11: Partner frameworks effective c.Oct-26 are tests; volume and price commitments only from c.Oct-27. That strains 'profitable in 18-24 months' and makes a 2027 top-up likely - management half-conceded both on the call. We model the top-up in section F.
B12: 3. AFFF is project revenue in a closing window | J12: The 2030 EU foam-replacement deadline caps Track 1. The recurring story that justifies EUR 15m pre-money is the utility track - which is certification-gated (finding 1). Our revenue build in section C keeps the tracks separate so this is visible.
B13: 4. Destruction-only disposal for POP-loaded resin | J13: AFFF-loaded resin above POP thresholds may not be regenerated - it must be destroyed. Their REGEN product line (Case 1, section B) has no revenue attached in the Base case, rightly; a destruction contract must be priced before volumes start. Contracting cost sits in section D.
B14: 5. The historic preference stack is real | J14: MIG on the call: 'we did a lot of down rounds - we want our money'. The deck says new money is unaffected; the term sheet PRESERVES historic preferences (order EUR 12m). If they rank ahead at mid exits, converting holders lose c.40% of pro-rata proceeds - worth c.EUR 1m to us. See the waterfall memo in section H.
B16: B. WHAT WE CHANGE VS THEIR MODEL (RED = OUR ASSUMPTION)
B17: Revenue: their four layers replaced by the three tracks | C17: see C | J17: Management's own strategy (04-08-2026): Track 1 AFFF partner channel, Track 2 certification-gated utilities, Track 3 integrators/bulk - Track 3 excluded from the base as 'not tangible enough' (their words), despite the Solenis US agreement in finalisation.
B18: Cost of sales | C18: 0.4 | J18: 60% gross margin early vs their c.72% at scale - partner-channel discounts and small batches.
B19: Running costs kept at c.90% of their plan | C19: 0.9 | J19: Costs never fall as fast as revenue slips - benchmark evidence (Pyrum delivered 55-58% of guidance with signed customers).
B20: Working capital introduced | C20: 0.15 | J20: 15% of revenue - resin inventory and partner receivables, absent from their plan entirely (Case 1, section F).
B21: Certification + disposal programme added | C21: see D | J21: EUR 2.2m across 2026-29, itemised below - the money finding 1 says is missing.
B22: EUR 5m top-up round, 2027 | C22: 5 | J22: At an assumed EUR 20m pre-money after Track-1 proof; dilutes all pre-top-up holders x0.8. Finding 2.
B23: Exit multiple unchanged | C23: 5 | J23: Same 5.0x revenue as Case 1 - arguably earned by then (certified product + commercial agreements) but on lower revenue.
B25: C. REVENUE - THE THREE TRACKS AS MANAGEMENT DESCRIBED THEM (EUR m)
B26: EUR m | C26: 2026 H2 | D26: 2027 | E26: 2028 | F26: 2029 | J26: Notes
B27: Track 1 - AFFF partner channel | C27: 0.3 | D27: 0.9 | E27: 2.6 | F27: 4.5 | J27: Cornelsen (DE), AquaCorp (AUS), Amazon Filters (UK) - frameworks expected signed within weeks, effective c.Oct-26; 12-month tests, volume/price agreements from c.Oct-27; partners buy for stock. Scales into the 2030 replacement wave. CEO himself reset 2026 to EUR 0.25-0.35m.
B28: Track 2 - water utilities (certification-gated) | C28: 0 | D28: 0 | E28: 0.4 | F28: 1.5 | J28: First certified sales 2028 - the benchmark says 12-24 months per market; management's Q1/Q2-27 is the optimistic end. This is the recurring story behind the EUR 15m pre.
B29: Track 3 - integrators / bulk resin (excluded) | C29: 0 | D29: 0 | E29: 0 | F29: 0 | J29: Upside, not plan - management's own words; Solenis US agreement in finalisation. Becomes real after Track 1 proves volume manufacturing; revisit at the 2027 round.
B30: Total revenue | C30: =SUM(C27:C29) -> 0.3 | D30: =SUM(D27:D29) -> 0.9 | E30: =SUM(E27:E29) -> 3 | F30: =SUM(F27:F29) -> 6
B31: memo: their plan total (Case 1) | C31: ='Case 1 - As Given'!C65 -> 0.21 | D31: ='Case 1 - As Given'!D65 -> 2.17 | E31: ='Case 1 - As Given'!E65 -> 6.86 | F31: ='Case 1 - As Given'!F65 -> 8.02 | J31: Their EUR 6.86m in 2028 vs our EUR 3.00m - the gap is almost entirely the unnamed top-down segments of Case 1, section D.
B32: memo: revenue we do not underwrite | C32: =C31-C30 -> -0.09 | D32: =D31-D30 -> 1.27 | E32: =E31-E30 -> 3.86 | F32: =F31-F30 -> 2.02
B34: D. THE CERTIFICATION + DISPOSAL PROGRAMME - ITEMISED (EUR m; RED = OUR ESTIMATE)
B35: EUR m | C35: 2026 H2 | D35: 2027 | E35: 2028 | F35: 2029 | J35: Notes
B36: Germany: KTW-BWGL + DVGW W270 (resin + filter) | C36: 0.15 | D36: 0.3 | E36: 0 | F36: 0 | J36: Without these no German utility may buy, however well it works. 12-18 months.
B37: EU drinking-water positive lists / migration testing | C37: 0.05 | D37: 0.15 | E37: 0.1 | F37: 0 | J37: EU framework binding from 2026; national rules still apply per country.
B38: US: NSF/ANSI 61 + 53 (resin + cartridge family) | C38: 0 | D38: 0.2 | E38: 0.2 | F38: 0 | J38: The US equivalent - Case 1's NA-utilities segment is impossible without it.
B39: UK (DWI Reg 31) + France (ACS) | C39: 0 | D39: 0.1 | E39: 0.1 | F39: 0.1 | J39: Two further markets in their plan.
B40: Independent performance testing (lifetime, real water) | C40: 0.1 | D40: 0.15 | E40: 0.1 | F40: 0 | J40: The data a bank's - or an acquirer's - technical adviser reads first.
B41: Annual audits, retests and fees | C41: 0 | D41: 0.05 | E41: 0.1 | F41: 0.096 | J41: Approvals are a programme, not a certificate; fees continue while the product sells.
B42: Destruction-route contracting for POP-loaded resin | C42: 0.1 | D42: 0.05 | E42: 0 | F42: 0 | J42: Waste profile + priced contract (rotary-kiln incinerators DE/BE/FR - Indaver, Seche, Veolia; gate fees c.USD 2,300-5,000/t). A contracting task, not research. Finding 4.
B43: Certification + disposal - total | C43: =SUM(C36:C42) -> 0.4 | D43: =SUM(D36:D42) -> 1 | E43: =SUM(E36:E42) -> 0.6 | F43: =SUM(F36:F42) -> 0.196 | J43: EUR 2.2m over the window - re-phased from the Programme workbook of 31-07 (its full estimate EUR 2.3m incl. rolling fees beyond 2029). Feeds the P&L below.
B45: E. P&L - THE SAME COMPANY UNDER OUR ASSUMPTIONS
B46: EUR m | C46: 2026 H2 | D46: 2027 | E46: 2028 | F46: 2029 | J46: Notes
B47: Total revenue | C47: =C30 -> 0.3 | D47: =D30 -> 0.9 | E47: =E30 -> 3 | F47: =F30 -> 6
B48: Cost of sales (40% of revenue) | C48: =$C$18*C47 -> 0.12 | D48: =$C$18*D47 -> 0.36 | E48: =$C$18*E47 -> 1.2 | F48: =$C$18*F47 -> 2.4
B49: Gross profit | C49: =C47-C48 -> 0.18 | D49: =D47-D48 -> 0.54 | E49: =E47-E48 -> 1.8 | F49: =F47-F48 -> 3.6
B50: Gross margin | C50: =C49/C47 -> 0.6 | D50: =D49/D47 -> 0.6 | E50: =E49/E47 -> 0.6 | F50: =F49/F47 -> 0.6
B51: Personnel (c.90% of their plan) | C51: 0.6995 | D51: 1.45 | E51: 1.7 | F51: 1.95
B52: Other operating costs (c.90% of their plan) | C52: 0.65 | D52: 1.2 | E52: 1.45 | F52: 1.7 | J52: Cost factor from section B applied to their schedule - costs do not wait for the sales.
B53: Certification programme + disposal contracting | C53: =C43 -> 0.4 | D53: =D43 -> 1 | E53: =E43 -> 0.6 | F53: =F43 -> 0.196
B54: EBITDA | C54: =C49-C51-C52-C53 -> -1.5695 | D54: =D49-D51-D52-D53 -> -3.11 | E54: =E49-E51-E52-E53 -> -1.95 | F54: =F49-F51-F52-F53 -> -0.246 | J54: Not profitable within 18-24 months on this build-up - profitability arrives c.2030, or late 2029 on a run-rate basis. Their claim: positive from 2028 (Case 1: +1.51).
B55: memo: depreciation | C55: 0.03 | D55: 0.11 | E55: 0.18 | F55: 0.23
B57: F. CASH FLOW - AND THE TOP-UP ROUND THE PLAN DOES NOT MENTION
B58: EUR m | C58: 2026 H2 | D58: 2027 | E58: 2028 | F58: 2029 | J58: Notes
B59: EBITDA | C59: =C54 -> -1.5695 | D59: =D54 -> -3.11 | E59: =E54 -> -1.95 | F59: =F54 -> -0.246
B60: Equipment spend (their schedule) | C60: 0.15 | D60: 0.38 | E60: 0.33 | F60: 0.245
B61: Change in working capital (15% of revenue) | C61: =$C$20*C47 -> 0.045 | D61: =$C$20*(D47-C47) -> 0.09 | E61: =$C$20*(E47-D47) -> 0.315 | F61: =$C$20*(F47-E47) -> 0.45
B62: New equity raised | C62: 4 | D62: 5 | E62: 0 | F62: 0 | J62: EUR 4m second close as planned + the RED EUR 5m top-up in 2027 at an assumed EUR 20m pre-money after Track-1 proof. Finding 2.
B63: Net cash flow | C63: =C59-C60-C61+C62 -> 2.2355 | D63: =D59-D60-D61+D62 -> 1.42 | E63: =E59-E60-E61+E62 -> -2.595 | F63: =F59-F60-F61+F62 -> -0.941
B64: Opening cash | C64: 0.35 | D64: =C65 -> 2.5855 | E64: =D65 -> 4.0055 | F64: =E65 -> 1.4105
B65: Closing cash | C65: =C64+C63 -> 2.5855 | D65: =D64+D63 -> 4.0055 | E65: =E64+E63 -> 1.4105 | F65: =F64+F63 -> 0.4695 | J65: Stays positive ONLY because of the red top-up.
B66: memo: closing cash WITHOUT the top-up | C66: =C65 -> 2.5855 | D66: =D65-5 -> -0.9945 | E66: =E65-5 -> -3.5895 | F66: =F65-5 -> -4.5305 | J66: Remove the EUR 5m and the company is out of cash during 2028 - the number that makes finding 2 non-negotiable.
B68: G. BALANCE SHEET (year-end, simplified)
B69: EUR m | C69: 2026 H2 | D69: 2027 | E69: 2028 | F69: 2029 | J69: Notes
B70: Cash | C70: =C65 -> 2.5855 | D70: =D65 -> 4.0055 | E70: =E65 -> 1.4105 | F70: =F65 -> 0.4695
B71: Working capital | C71: =$C$20*C47 -> 0.045 | D71: =$C$20*D47 -> 0.135 | E71: =$C$20*E47 -> 0.45 | F71: =$C$20*F47 -> 0.9
B72: Fixed assets, net | C72: =C60-C55 -> 0.12 | D72: =C72+D60-D55 -> 0.39 | E72: =D72+E60-E55 -> 0.54 | F72: =E72+F60-F55 -> 0.555
B73: Total assets | C73: =C70+C71+C72 -> 2.7505 | D73: =D70+D71+D72 -> 4.5305 | E73: =E70+E71+E72 -> 2.4005 | F73: =F70+F71+F72 -> 1.9245
B74: Equity (capital raised less accumulated losses) | C74: =C73 -> 2.7505 | D74: =D73 -> 4.5305 | E74: =E73 -> 2.4005 | F74: =F73 -> 1.9245
B76: H. EXIT 2029 - CASH WATERFALL AND RETURNS, POST TOP-UP DILUTION
B77: EV / revenue multiple at exit | C77: 5
B78: Enterprise value | C78: =C77*F30 -> 30
B79: plus: cash at exit | C79: =F65 -> 0.4695
B80: Equity value | C80: =C78+C79 -> 30.4695
B82: Investor class (FD, post-VSOP, post-top-up) | C82: FD % | D82: Invested | E82: 1x pref | F82: Proceeds | G82: Multiple | J82: Rationale
B83: MIG Funds (incl. EUR 2m of this round) | C83: 0.567 | D83: 14 | E83: 2 | F83: =MAX(IF(E83="",0,E83),C83*$C$80) -> 17.276207 | G83: =F83/D83 -> 1.2340148 | J83: Case-1 stake diluted x0.8 by the top-up round (no pro-rata assumed).
B84: Other existing holders + treasury | C84: 0.039 | F84: =MAX(IF(E84="",0,E84),C84*$C$80) -> 1.1883105
B85: New co-investors 2026 (EUR 3m, incl. the EUR 2m assessed) | C85: 0.1137 | D85: 3 | E85: 3 | F85: =MAX(IF(E85="",0,E85),C85*$C$80) -> 3.4643822 | G85: =F85/D85 -> 1.1547941 | J85: 14.2% diluted x0.8 - the EUR 2m participation becomes c.7.6% FD.
B86: Top-up investor 2027 (RED) | C86: 0.2 | D86: 5 | E86: 5 | F86: =MAX(IF(E86="",0,E86),C86*$C$80) -> 6.0939 | G86: =F86/D86 -> 1.21878 | J86: Enters at EUR 20m pre after Track-1 proof - takes 20% and ranks pari passu or better.
B87: VSOP (8% post-top-up) | C87: 0.08 | F87: =MAX(IF(E87="",0,E87),C87*$C$80) -> 2.43756
B88: Total distributed | F88: =SUM(F83:F87) -> 30.460359
B89: Memo - the historic preference question | J89: Past down rounds imply a senior preference stack (order EUR 12m). The deck says new money is unaffected; the term sheet preserves historic preferences. If they rank ahead at this exit level, pro-rata proceeds fall c.40% for every converting holder - the single most valuable clause to settle in the documents. Finding 5.
B91: The EUR 2m participation - proceeds / multiple / IRR | C91: =2/3*F85 -> 2.3095881 | D91: =C91/2 -> 1.1547941 | E91: =(C91/2)^(1/3)-1 -> 0.049143383 | J91: At the base exit here the participation roughly returns its money - it clears hurdles only at EUR 55m+ equity value, or with the structure below.
B92: memo: EUR 2m fully diluted share (post-top-up) | C92: =2/3*C85 -> 0.0758
B93: I. WHAT WE DO ABOUT IT - THE RECOMMENDED STRUCTURE FOR THE EUR 2m LEAD
B94: YES to leading the EUR 2m - the round is waiting on this lead | J94: Other investors are queued behind it, so the conditions below cost MIG nothing and close their round. Keep the EUR 15m headline; build the relationship.
B95: Tranche it | J95: EUR 1m at close; EUR 1m on Track-1 proof - partner framework signed + destruction contract + certification budget committed (findings 1, 2 and 4 made contractual).
B96: Sweetener instead of a price fight | J96: 15-20% warrant coverage at EUR 15m, or their own convertible with the cap set at EUR 15m (not 25m) - repairs the Case-2 return without reopening the headline.
B97: Paper tidied | J97: Deck governance (1 investor / 1 MIG / 1 independent) and the deck's waterfall wording INTO the documents - finding 5 resolved at signing, when it is free.
B98: Pro-rata + first look at the 2027 round | J98: Alongside MIG - the top-up in section F is where the next EUR 5m of allocation (and the dilution protection) sits.
B100: Red assumptions are ours, stated for challenge. Staging follows the management discussion of 04-08-2026: framework year, commercial agreements from Oct-27, certification-gated utility entry, profitability approached late in the period.
